package b.b.p;

import android.content.Context;
import android.graphics.Canvas;
import android.graphics.drawable.Drawable;
import android.util.AttributeSet;
import android.view.View;
import android.widget.SeekBar;

public class t extends SeekBar {
  public final u b;
  
  public t(Context paramContext, AttributeSet paramAttributeSet) {
    super(paramContext, paramAttributeSet, i);
    s0.a((View)this, getContext());
    u u1 = new u(this);
    this.b = u1;
    u1.a(paramAttributeSet, i);
  }
  
  public void drawableStateChanged() {
    super.drawableStateChanged();
    u u1 = this.b;
    Drawable drawable = u1.e;
    if (drawable != null && drawable.isStateful() && drawable.setState(u1.d.getDrawableState()))
      u1.d.invalidateDrawable(drawable); 
  }
  
  public void jumpDrawablesToCurrentState() {
    super.jumpDrawablesToCurrentState();
    Drawable drawable = this.b.e;
    if (drawable != null)
      drawable.jumpToCurrentState(); 
  }
  
  public void onDraw(Canvas paramCanvas) {
    // Byte code:
    //   0: aload_0
    //   1: monitorenter
    //   2: aload_0
    //   3: aload_1
    //   4: invokespecial onDraw : (Landroid/graphics/Canvas;)V
    //   7: aload_0
    //   8: getfield b : Lb/b/p/u;
    //   11: aload_1
    //   12: invokevirtual d : (Landroid/graphics/Canvas;)V
    //   15: aload_0
    //   16: monitorexit
    //   17: return
    //   18: astore_1
    //   19: aload_0
    //   20: monitorexit
    //   21: aload_1
    //   22: athrow
    // Exception table:
    //   from	to	target	type
    //   2	15	18	finally
  }
}


/* Location:              C:\Users\panch\Downloads\dvba_v1.1.0-dex2jar.jar!\b\b\p\t.class
 * Java compiler version: 6 (50.0)
 * JD-Core Version:       1.1.3
 */