package androidx.constraintlayout.widget;

import android.annotation.SuppressLint;
import android.annotation.TargetApi;
import android.content.Context;
import android.content.res.Resources;
import android.content.res.TypedArray;
import android.graphics.Canvas;
import android.graphics.Paint;
import android.util.AttributeSet;
import android.util.SparseArray;
import android.util.SparseIntArray;
import android.view.View;
import android.view.ViewGroup;
import b.g.b.d;
import b.g.b.i.d;
import b.g.b.i.e;
import b.g.b.i.f;
import b.g.b.i.i;
import b.g.b.i.k;
import b.g.c.c;
import b.g.c.d;
import b.g.c.e;
import b.g.c.g;
import b.g.c.i;
import b.g.c.k;
import java.util.ArrayList;
import java.util.HashMap;

public class ConstraintLayout extends ViewGroup {
  public SparseArray<View> b = new SparseArray();
  
  public ArrayList<c> c = new ArrayList<c>(4);
  
  public e d = new e();
  
  public int e = 0;
  
  public int f = 0;
  
  public int g = Integer.MAX_VALUE;
  
  public int h = Integer.MAX_VALUE;
  
  public boolean i = true;
  
  public int j = 263;
  
  public e k = null;
  
  public d l = null;
  
  public int m = -1;
  
  public HashMap<String, Integer> n = new HashMap<String, Integer>();
  
  public int o = -1;
  
  public int p = -1;
  
  public SparseArray<d> q = new SparseArray();
  
  public b r;
  
  public ConstraintLayout(Context paramContext, AttributeSet paramAttributeSet) {
    super(paramContext, paramAttributeSet);
    b b1 = new b(this, this);
    this.r = b1;
    e e1 = this.d;
    ((d)e1).W = this;
    e1.i0 = b1;
    e1.h0.f = b1;
    this.b.put(getId(), this);
    this.k = null;
    if (paramAttributeSet != null) {
      TypedArray typedArray = getContext().obtainStyledAttributes(paramAttributeSet, k.ConstraintLayout_Layout, 0, 0);
      int i = typedArray.getIndexCount();
      for (byte b2 = 0; b2 < i; b2++) {
        int j = typedArray.getIndex(b2);
        if (j == k.ConstraintLayout_Layout_android_minWidth) {
          this.e = typedArray.getDimensionPixelOffset(j, this.e);
        } else if (j == k.ConstraintLayout_Layout_android_minHeight) {
          this.f = typedArray.getDimensionPixelOffset(j, this.f);
        } else if (j == k.ConstraintLayout_Layout_android_maxWidth) {
          this.g = typedArray.getDimensionPixelOffset(j, this.g);
        } else if (j == k.ConstraintLayout_Layout_android_maxHeight) {
          this.h = typedArray.getDimensionPixelOffset(j, this.h);
        } else if (j == k.ConstraintLayout_Layout_layout_optimizationLevel) {
          this.j = typedArray.getInt(j, this.j);
        } else if (j == k.ConstraintLayout_Layout_layoutDescription) {
          j = typedArray.getResourceId(j, 0);
          if (j != 0)
            try {
              d d1 = new d();
              this(getContext(), this, j);
              this.l = d1;
            } catch (android.content.res.Resources.NotFoundException notFoundException) {
              this.l = null;
            }  
        } else if (j == k.ConstraintLayout_Layout_constraintSet) {
          j = typedArray.getResourceId(j, 0);
          try {
            e e2 = new e();
            this();
            this.k = e2;
            e2.e(getContext(), j);
          } catch (android.content.res.Resources.NotFoundException notFoundException) {
            this.k = null;
          } 
          this.m = j;
        } 
      } 
      typedArray.recycle();
    } 
    this.d.J(this.j);
  }
  
  private int getPaddingWidth() {
    int i = Math.max(0, getPaddingLeft());
    i = Math.max(0, getPaddingRight()) + i;
    int j = Math.max(0, getPaddingStart());
    j = Math.max(0, getPaddingEnd()) + j;
    if (j > 0)
      i = j; 
    return i;
  }
  
  public void a(boolean paramBoolean, View paramView, d paramd, a parama, SparseArray<d> paramSparseArray) {
    // Byte code:
    //   0: getstatic b/g/b/i/c$a.g : Lb/g/b/i/c$a;
    //   3: astore #25
    //   5: getstatic b/g/b/i/d$a.e : Lb/g/b/i/d$a;
    //   8: astore #18
    //   10: getstatic b/g/b/i/d$a.c : Lb/g/b/i/d$a;
    //   13: astore #22
    //   15: getstatic b/g/b/i/d$a.b : Lb/g/b/i/d$a;
    //   18: astore #21
    //   20: getstatic b/g/b/i/d$a.d : Lb/g/b/i/d$a;
    //   23: astore #24
    //   25: getstatic b/g/b/i/c$a.e : Lb/g/b/i/c$a;
    //   28: astore #20
    //   30: getstatic b/g/b/i/c$a.c : Lb/g/b/i/c$a;
    //   33: astore #19
    //   35: getstatic b/g/b/i/c$a.f : Lb/g/b/i/c$a;
    //   38: astore #23
    //   40: getstatic b/g/b/i/c$a.d : Lb/g/b/i/c$a;
    //   43: astore #17
    //   45: aload #4
    //   47: invokevirtual a : ()V
    //   50: aload_3
    //   51: aload_2
    //   52: invokevirtual getVisibility : ()I
    //   55: putfield X : I
    //   58: aload #4
    //   60: getfield a0 : Z
    //   63: ifeq -> 77
    //   66: aload_3
    //   67: iconst_1
    //   68: putfield x : Z
    //   71: aload_3
    //   72: bipush #8
    //   74: putfield X : I
    //   77: aload_3
    //   78: aload_2
    //   79: putfield W : Ljava/lang/Object;
    //   82: aload_2
    //   83: instanceof b/g/c/c
    //   86: ifeq -> 193
    //   89: aload_2
    //   90: checkcast b/g/c/c
    //   93: astore_2
    //   94: aload_0
    //   95: getfield d : Lb/g/b/i/e;
    //   98: getfield j0 : Z
    //   101: istore #15
    //   103: aload_2
    //   104: checkcast b/g/c/a
    //   107: astore_2
    //   108: aload_2
    //   109: getfield i : I
    //   112: istore #8
    //   114: aload_2
    //   115: iload #8
    //   117: putfield j : I
    //   120: iload #15
    //   122: ifeq -> 144
    //   125: iload #8
    //   127: iconst_5
    //   128: if_icmpne -> 134
    //   131: goto -> 163
    //   134: iload #8
    //   136: bipush #6
    //   138: if_icmpne -> 172
    //   141: goto -> 150
    //   144: iload #8
    //   146: iconst_5
    //   147: if_icmpne -> 156
    //   150: iconst_0
    //   151: istore #8
    //   153: goto -> 166
    //   156: iload #8
    //   158: bipush #6
    //   160: if_icmpne -> 172
    //   163: iconst_1
    //   164: istore #8
    //   166: aload_2
    //   167: iload #8
    //   169: putfield j : I
    //   172: aload_3
    //   173: instanceof b/g/b/i/a
    //   176: ifeq -> 193
    //   179: aload_3
    //   180: checkcast b/g/b/i/a
    //   183: aload_2
    //   184: getfield j : I
    //   187: putfield h0 : I
    //   190: goto -> 193
    //   193: aload #4
    //   195: getfield Y : Z
    //   198: ifeq -> 330
    //   201: aload_3
    //   202: checkcast b/g/b/i/f
    //   205: astore_2
    //   206: aload #4
    //   208: getfield j0 : I
    //   211: istore #10
    //   213: aload #4
    //   215: getfield k0 : I
    //   218: istore #8
    //   220: aload #4
    //   222: getfield l0 : F
    //   225: fstore #6
    //   227: fload #6
    //   229: ldc_w -1.0
    //   232: fcmpl
    //   233: istore #9
    //   235: iload #9
    //   237: ifeq -> 264
    //   240: iload #9
    //   242: ifle -> 1913
    //   245: aload_2
    //   246: fload #6
    //   248: putfield f0 : F
    //   251: aload_2
    //   252: iconst_m1
    //   253: putfield g0 : I
    //   256: aload_2
    //   257: iconst_m1
    //   258: putfield h0 : I
    //   261: goto -> 1913
    //   264: iload #10
    //   266: iconst_m1
    //   267: if_icmpeq -> 297
    //   270: iload #10
    //   272: iconst_m1
    //   273: if_icmple -> 1913
    //   276: aload_2
    //   277: ldc_w -1.0
    //   280: putfield f0 : F
    //   283: aload_2
    //   284: iload #10
    //   286: putfield g0 : I
    //   289: aload_2
    //   290: iconst_m1
    //   291: putfield h0 : I
    //   294: goto -> 1913
    //   297: iload #8
    //   299: iconst_m1
    //   300: if_icmpeq -> 1913
    //   303: iload #8
    //   305: iconst_m1
    //   306: if_icmple -> 1913
    //   309: aload_2
    //   310: ldc_w -1.0
    //   313: putfield f0 : F
    //   316: aload_2
    //   317: iconst_m1
    //   318: putfield g0 : I
    //   321: aload_2
    //   322: iload #8
    //   324: putfield h0 : I
    //   327: goto -> 1913
    //   330: aload #4
    //   332: getfield c0 : I
    //   335: istore #13
    //   337: aload #4
    //   339: getfield d0 : I
    //   342: istore #8
    //   344: aload #4
    //   346: getfield e0 : I
    //   349: istore #11
    //   351: aload #4
    //   353: getfield f0 : I
    //   356: istore #10
    //   358: aload #4
    //   360: getfield g0 : I
    //   363: istore #12
    //   365: aload #4
    //   367: getfield h0 : I
    //   370: istore #9
    //   372: aload #4
    //   374: getfield i0 : F
    //   377: fstore #6
    //   379: aload #4
    //   381: getfield m : I
    //   384: istore #14
    //   386: iload #14
    //   388: iconst_m1
    //   389: if_icmpeq -> 455
    //   392: aload #5
    //   394: iload #14
    //   396: invokevirtual get : (I)Ljava/lang/Object;
    //   399: checkcast b/g/b/i/d
    //   402: astore_2
    //   403: aload_2
    //   404: ifnull -> 1106
    //   407: aload #4
    //   409: getfield o : F
    //   412: fstore #6
    //   414: aload #4
    //   416: getfield n : I
    //   419: istore #8
    //   421: getstatic b/g/b/i/c$a.h : Lb/g/b/i/c$a;
    //   424: astore #5
    //   426: aload_3
    //   427: aload #5
    //   429: invokevirtual f : (Lb/g/b/i/c$a;)Lb/g/b/i/c;
    //   432: aload_2
    //   433: aload #5
    //   435: invokevirtual f : (Lb/g/b/i/c$a;)Lb/g/b/i/c;
    //   438: iload #8
    //   440: iconst_0
    //   441: iconst_1
    //   442: invokevirtual a : (Lb/g/b/i/c;IIZ)Z
    //   445: pop
    //   446: aload_3
    //   447: fload #6
    //   449: putfield v : F
    //   452: goto -> 1106
    //   455: iload #13
    //   457: iconst_m1
    //   458: if_icmpeq -> 504
    //   461: aload #5
    //   463: iload #13
    //   465: invokevirtual get : (I)Ljava/lang/Object;
    //   468: checkcast b/g/b/i/d
    //   471: astore #16
    //   473: aload #16
    //   475: ifnull -> 565
    //   478: aload #4
    //   480: getfield leftMargin : I
    //   483: istore #8
    //   485: aload_3
    //   486: aload #19
    //   488: invokevirtual f : (Lb/g/b/i/c$a;)Lb/g/b/i/c;
    //   491: astore_2
    //   492: aload #16
    //   494: aload #19
    //   496: invokevirtual f : (Lb/g/b/i/c$a;)Lb/g/b/i/c;
    //   499: astore #16
    //   501: goto -> 553
    //   504: iload #8
    //   506: iconst_m1
    //   507: if_icmpeq -> 565
    //   510: aload #5
    //   512: iload #8
    //   514: invokevirtual get : (I)Ljava/lang/Object;
    //   517: checkcast b/g/b/i/d
    //   520: astore #16
    //   522: aload #16
    //   524: ifnull -> 565
    //   527: aload #4
    //   529: getfield leftMargin : I
    //   532: istore #8
    //   534: aload_3
    //   535: aload #19
    //   537: invokevirtual f : (Lb/g/b/i/c$a;)Lb/g/b/i/c;
    //   540: astore_2
    //   541: aload #16
    //   543: aload #20
    //   545: invokevirtual f : (Lb/g/b/i/c$a;)Lb/g/b/i/c;
    //   548: astore #16
    //   550: goto -> 501
    //   553: aload_2
    //   554: aload #16
    //   556: iload #8
    //   558: iload #12
    //   560: iconst_1
    //   561: invokevirtual a : (Lb/g/b/i/c;IIZ)Z
    //   564: pop
    //   565: iload #11
    //   567: iconst_m1
    //   568: if_icmpeq -> 611
    //   571: aload #5
    //   573: iload #11
    //   575: invokevirtual get : (I)Ljava/lang/Object;
    //   578: checkcast b/g/b/i/d
    //   581: astore_2
    //   582: aload_2
    //   583: ifnull -> 669
    //   586: aload #4
    //   588: getfield rightMargin : I
    //   591: istore #8
    //   593: aload_3
    //   594: aload #20
    //   596: invokevirtual f : (Lb/g/b/i/c$a;)Lb/g/b/i/c;
    //   599: astore #16
    //   601: aload_2
    //   602: aload #19
    //   604: invokevirtual f : (Lb/g/b/i/c$a;)Lb/g/b/i/c;
    //   607: astore_2
    //   608: goto -> 657
    //   611: iload #10
    //   613: iconst_m1
    //   614: if_icmpeq -> 669
    //   617: aload #5
    //   619: iload #10
    //   621: invokevirtual get : (I)Ljava/lang/Object;
    //   624: checkcast b/g/b/i/d
    //   627: astore_2
    //   628: aload_2
    //   629: ifnull -> 669
    //   632: aload #4
    //   634: getfield rightMargin : I
    //   637: istore #8
    //   639: aload_3
    //   640: aload #20
    //   642: invokevirtual f : (Lb/g/b/i/c$a;)Lb/g/b/i/c;
    //   645: astore #16
    //   647: aload_2
    //   648: aload #20
    //   650: invokevirtual f : (Lb/g/b/i/c$a;)Lb/g/b/i/c;
    //   653: astore_2
    //   654: goto -> 608
    //   657: aload #16
    //   659: aload_2
    //   660: iload #8
    //   662: iload #9
    //   664: iconst_1
    //   665: invokevirtual a : (Lb/g/b/i/c;IIZ)Z
    //   668: pop
    //   669: aload #4
    //   671: getfield h : I
    //   674: istore #8
    //   676: iload #8
    //   678: iconst_m1
    //   679: if_icmpeq -> 732
    //   682: aload #5
    //   684: iload #8
    //   686: invokevirtual get : (I)Ljava/lang/Object;
    //   689: checkcast b/g/b/i/d
    //   692: astore #16
    //   694: aload #16
    //   696: ifnull -> 807
    //   699: aload #4
    //   701: getfield topMargin : I
    //   704: istore #9
    //   706: aload #4
    //   708: getfield u : I
    //   711: istore #8
    //   713: aload_3
    //   714: aload #17
    //   716: invokevirtual f : (Lb/g/b/i/c$a;)Lb/g/b/i/c;
    //   719: astore_2
    //   720: aload #16
    //   722: aload #17
    //   724: invokevirtual f : (Lb/g/b/i/c$a;)Lb/g/b/i/c;
    //   727: astore #16
    //   729: goto -> 795
    //   732: aload #4
    //   734: getfield i : I
    //   737: istore #8
    //   739: iload #8
    //   741: iconst_m1
    //   742: if_icmpeq -> 807
    //   745: aload #5
    //   747: iload #8
    //   749: invokevirtual get : (I)Ljava/lang/Object;
    //   752: checkcast b/g/b/i/d
    //   755: astore #16
    //   757: aload #16
    //   759: ifnull -> 807
    //   762: aload #4
    //   764: getfield topMargin : I
    //   767: istore #9
    //   769: aload #4
    //   771: getfield u : I
    //   774: istore #8
    //   776: aload_3
    //   777: aload #17
    //   779: invokevirtual f : (Lb/g/b/i/c$a;)Lb/g/b/i/c;
    //   782: astore_2
    //   783: aload #16
    //   785: aload #23
    //   787: invokevirtual f : (Lb/g/b/i/c$a;)Lb/g/b/i/c;
    //   790: astore #16
    //   792: goto -> 729
    //   795: aload_2
    //   796: aload #16
    //   798: iload #9
    //   800: iload #8
    //   802: iconst_1
    //   803: invokevirtual a : (Lb/g/b/i/c;IIZ)Z
    //   806: pop
    //   807: aload #4
    //   809: getfield j : I
    //   812: istore #8
    //   814: iload #8
    //   816: iconst_m1
    //   817: if_icmpeq -> 867
    //   820: aload #5
    //   822: iload #8
    //   824: invokevirtual get : (I)Ljava/lang/Object;
    //   827: checkcast b/g/b/i/d
    //   830: astore_2
    //   831: aload_2
    //   832: ifnull -> 939
    //   835: aload #4
    //   837: getfield bottomMargin : I
    //   840: istore #8
    //   842: aload #4
    //   844: getfield w : I
    //   847: istore #9
    //   849: aload_3
    //   850: aload #23
    //   852: invokevirtual f : (Lb/g/b/i/c$a;)Lb/g/b/i/c;
    //   855: astore #16
    //   857: aload_2
    //   858: aload #17
    //   860: invokevirtual f : (Lb/g/b/i/c$a;)Lb/g/b/i/c;
    //   863: astore_2
    //   864: goto -> 927
    //   867: aload #4
    //   869: getfield k : I
    //   872: istore #8
    //   874: iload #8
    //   876: iconst_m1
    //   877: if_icmpeq -> 939
    //   880: aload #5
    //   882: iload #8
    //   884: invokevirtual get : (I)Ljava/lang/Object;
    //   887: checkcast b/g/b/i/d
    //   890: astore_2
    //   891: aload_2
    //   892: ifnull -> 939
    //   895: aload #4
    //   897: getfield bottomMargin : I
    //   900: istore #8
    //   902: aload #4
    //   904: getfield w : I
    //   907: istore #9
    //   909: aload_3
    //   910: aload #23
    //   912: invokevirtual f : (Lb/g/b/i/c$a;)Lb/g/b/i/c;
    //   915: astore #16
    //   917: aload_2
    //   918: aload #23
    //   920: invokevirtual f : (Lb/g/b/i/c$a;)Lb/g/b/i/c;
    //   923: astore_2
    //   924: goto -> 864
    //   927: aload #16
    //   929: aload_2
    //   930: iload #8
    //   932: iload #9
    //   934: iconst_1
    //   935: invokevirtual a : (Lb/g/b/i/c;IIZ)Z
    //   938: pop
    //   939: aload #4
    //   941: getfield l : I
    //   944: istore #8
    //   946: iload #8
    //   948: iconst_m1
    //   949: if_icmpeq -> 1073
    //   952: aload_0
    //   953: getfield b : Landroid/util/SparseArray;
    //   956: iload #8
    //   958: invokevirtual get : (I)Ljava/lang/Object;
    //   961: checkcast android/view/View
    //   964: astore #16
    //   966: aload #5
    //   968: aload #4
    //   970: getfield l : I
    //   973: invokevirtual get : (I)Ljava/lang/Object;
    //   976: checkcast b/g/b/i/d
    //   979: astore_2
    //   980: aload_2
    //   981: ifnull -> 1073
    //   984: aload #16
    //   986: ifnull -> 1073
    //   989: aload #16
    //   991: invokevirtual getLayoutParams : ()Landroid/view/ViewGroup$LayoutParams;
    //   994: instanceof androidx/constraintlayout/widget/ConstraintLayout$a
    //   997: ifeq -> 1073
    //   1000: aload #16
    //   1002: invokevirtual getLayoutParams : ()Landroid/view/ViewGroup$LayoutParams;
    //   1005: checkcast androidx/constraintlayout/widget/ConstraintLayout$a
    //   1008: astore #5
    //   1010: aload #4
    //   1012: iconst_1
    //   1013: putfield X : Z
    //   1016: aload #5
    //   1018: iconst_1
    //   1019: putfield X : Z
    //   1022: aload_3
    //   1023: aload #25
    //   1025: invokevirtual f : (Lb/g/b/i/c$a;)Lb/g/b/i/c;
    //   1028: aload_2
    //   1029: aload #25
    //   1031: invokevirtual f : (Lb/g/b/i/c$a;)Lb/g/b/i/c;
    //   1034: iconst_0
    //   1035: iconst_m1
    //   1036: iconst_1
    //   1037: invokevirtual a : (Lb/g/b/i/c;IIZ)Z
    //   1040: pop
    //   1041: aload_3
    //   1042: iconst_1
    //   1043: putfield w : Z
    //   1046: aload #5
    //   1048: getfield m0 : Lb/g/b/i/d;
    //   1051: iconst_1
    //   1052: putfield w : Z
    //   1055: aload_3
    //   1056: aload #17
    //   1058: invokevirtual f : (Lb/g/b/i/c$a;)Lb/g/b/i/c;
    //   1061: invokevirtual e : ()V
    //   1064: aload_3
    //   1065: aload #23
    //   1067: invokevirtual f : (Lb/g/b/i/c$a;)Lb/g/b/i/c;
    //   1070: invokevirtual e : ()V
    //   1073: fload #6
    //   1075: fconst_0
    //   1076: fcmpl
    //   1077: iflt -> 1086
    //   1080: aload_3
    //   1081: fload #6
    //   1083: putfield U : F
    //   1086: aload #4
    //   1088: getfield A : F
    //   1091: fstore #6
    //   1093: fload #6
    //   1095: fconst_0
    //   1096: fcmpl
    //   1097: iflt -> 1106
    //   1100: aload_3
    //   1101: fload #6
    //   1103: putfield V : F
    //   1106: iload_1
    //   1107: ifeq -> 1154
    //   1110: aload #4
    //   1112: getfield P : I
    //   1115: iconst_m1
    //   1116: if_icmpne -> 1128
    //   1119: aload #4
    //   1121: getfield Q : I
    //   1124: iconst_m1
    //   1125: if_icmpeq -> 1154
    //   1128: aload #4
    //   1130: getfield P : I
    //   1133: istore #9
    //   1135: aload #4
    //   1137: getfield Q : I
    //   1140: istore #8
    //   1142: aload_3
    //   1143: iload #9
    //   1145: putfield P : I
    //   1148: aload_3
    //   1149: iload #8
    //   1151: putfield Q : I
    //   1154: aload #4
    //   1156: getfield V : Z
    //   1159: ifne -> 1245
    //   1162: aload #4
    //   1164: getfield width : I
    //   1167: iconst_m1
    //   1168: if_icmpne -> 1229
    //   1171: aload #4
    //   1173: getfield S : Z
    //   1176: ifeq -> 1190
    //   1179: aload_3
    //   1180: getfield J : [Lb/g/b/i/d$a;
    //   1183: iconst_0
    //   1184: aload #24
    //   1186: aastore
    //   1187: goto -> 1198
    //   1190: aload_3
    //   1191: getfield J : [Lb/g/b/i/d$a;
    //   1194: iconst_0
    //   1195: aload #18
    //   1197: aastore
    //   1198: aload_3
    //   1199: aload #19
    //   1201: invokevirtual f : (Lb/g/b/i/c$a;)Lb/g/b/i/c;
    //   1204: aload #4
    //   1206: getfield leftMargin : I
    //   1209: putfield e : I
    //   1212: aload_3
    //   1213: aload #20
    //   1215: invokevirtual f : (Lb/g/b/i/c$a;)Lb/g/b/i/c;
    //   1218: aload #4
    //   1220: getfield rightMargin : I
    //   1223: putfield e : I
    //   1226: goto -> 1280
    //   1229: aload_3
    //   1230: getfield J : [Lb/g/b/i/d$a;
    //   1233: iconst_0
    //   1234: aload #24
    //   1236: aastore
    //   1237: aload_3
    //   1238: iconst_0
    //   1239: invokevirtual B : (I)V
    //   1242: goto -> 1280
    //   1245: aload_3
    //   1246: getfield J : [Lb/g/b/i/d$a;
    //   1249: iconst_0
    //   1250: aload #21
    //   1252: aastore
    //   1253: aload_3
    //   1254: aload #4
    //   1256: getfield width : I
    //   1259: invokevirtual B : (I)V
    //   1262: aload #4
    //   1264: getfield width : I
    //   1267: bipush #-2
    //   1269: if_icmpne -> 1280
    //   1272: aload_3
    //   1273: getfield J : [Lb/g/b/i/d$a;
    //   1276: iconst_0
    //   1277: aload #22
    //   1279: aastore
    //   1280: aload #4
    //   1282: getfield W : Z
    //   1285: ifne -> 1371
    //   1288: aload #4
    //   1290: getfield height : I
    //   1293: iconst_m1
    //   1294: if_icmpne -> 1355
    //   1297: aload #4
    //   1299: getfield T : Z
    //   1302: ifeq -> 1316
    //   1305: aload_3
    //   1306: getfield J : [Lb/g/b/i/d$a;
    //   1309: iconst_1
    //   1310: aload #24
    //   1312: aastore
    //   1313: goto -> 1324
    //   1316: aload_3
    //   1317: getfield J : [Lb/g/b/i/d$a;
    //   1320: iconst_1
    //   1321: aload #18
    //   1323: aastore
    //   1324: aload_3
    //   1325: aload #17
    //   1327: invokevirtual f : (Lb/g/b/i/c$a;)Lb/g/b/i/c;
    //   1330: aload #4
    //   1332: getfield topMargin : I
    //   1335: putfield e : I
    //   1338: aload_3
    //   1339: aload #23
    //   1341: invokevirtual f : (Lb/g/b/i/c$a;)Lb/g/b/i/c;
    //   1344: aload #4
    //   1346: getfield bottomMargin : I
    //   1349: putfield e : I
    //   1352: goto -> 1406
    //   1355: aload_3
    //   1356: getfield J : [Lb/g/b/i/d$a;
    //   1359: iconst_1
    //   1360: aload #24
    //   1362: aastore
    //   1363: aload_3
    //   1364: iconst_0
    //   1365: invokevirtual w : (I)V
    //   1368: goto -> 1406
    //   1371: aload_3
    //   1372: getfield J : [Lb/g/b/i/d$a;
    //   1375: iconst_1
    //   1376: aload #21
    //   1378: aastore
    //   1379: aload_3
    //   1380: aload #4
    //   1382: getfield height : I
    //   1385: invokevirtual w : (I)V
    //   1388: aload #4
    //   1390: getfield height : I
    //   1393: bipush #-2
    //   1395: if_icmpne -> 1406
    //   1398: aload_3
    //   1399: getfield J : [Lb/g/b/i/d$a;
    //   1402: iconst_1
    //   1403: aload #22
    //   1405: aastore
    //   1406: iconst_m1
    //   1407: istore #8
    //   1409: aload #4
    //   1411: getfield B : Ljava/lang/String;
    //   1414: astore #5
    //   1416: aload #5
    //   1418: ifnull -> 1682
    //   1421: aload #5
    //   1423: invokevirtual length : ()I
    //   1426: ifne -> 1432
    //   1429: goto -> 1682
    //   1432: aload #5
    //   1434: invokevirtual length : ()I
    //   1437: istore #10
    //   1439: aload #5
    //   1441: bipush #44
    //   1443: invokevirtual indexOf : (I)I
    //   1446: istore #9
    //   1448: iload #9
    //   1450: ifle -> 1512
    //   1453: iload #9
    //   1455: iload #10
    //   1457: iconst_1
    //   1458: isub
    //   1459: if_icmpge -> 1512
    //   1462: aload #5
    //   1464: iconst_0
    //   1465: iload #9
    //   1467: invokevirtual substring : (II)Ljava/lang/String;
    //   1470: astore_2
    //   1471: aload_2
    //   1472: ldc_w 'W'
    //   1475: invokevirtual equalsIgnoreCase : (Ljava/lang/String;)Z
    //   1478: ifeq -> 1487
    //   1481: iconst_0
    //   1482: istore #8
    //   1484: goto -> 1506
    //   1487: aload_2
    //   1488: ldc_w 'H'
    //   1491: invokevirtual equalsIgnoreCase : (Ljava/lang/String;)Z
    //   1494: ifeq -> 1503
    //   1497: iconst_1
    //   1498: istore #8
    //   1500: goto -> 1506
    //   1503: iconst_m1
    //   1504: istore #8
    //   1506: iinc #9, 1
    //   1509: goto -> 1515
    //   1512: iconst_0
    //   1513: istore #9
    //   1515: aload #5
    //   1517: bipush #58
    //   1519: invokevirtual indexOf : (I)I
    //   1522: istore #11
    //   1524: iload #11
    //   1526: iflt -> 1633
    //   1529: iload #11
    //   1531: iload #10
    //   1533: iconst_1
    //   1534: isub
    //   1535: if_icmpge -> 1633
    //   1538: aload #5
    //   1540: iload #9
    //   1542: iload #11
    //   1544: invokevirtual substring : (II)Ljava/lang/String;
    //   1547: astore_2
    //   1548: aload #5
    //   1550: iload #11
    //   1552: iconst_1
    //   1553: iadd
    //   1554: invokevirtual substring : (I)Ljava/lang/String;
    //   1557: astore #5
    //   1559: aload_2
    //   1560: invokevirtual length : ()I
    //   1563: ifle -> 1657
    //   1566: aload #5
    //   1568: invokevirtual length : ()I
    //   1571: ifle -> 1657
    //   1574: aload_2
    //   1575: invokestatic parseFloat : (Ljava/lang/String;)F
    //   1578: fstore #6
    //   1580: aload #5
    //   1582: invokestatic parseFloat : (Ljava/lang/String;)F
    //   1585: fstore #7
    //   1587: fload #6
    //   1589: fconst_0
    //   1590: fcmpl
    //   1591: ifle -> 1657
    //   1594: fload #7
    //   1596: fconst_0
    //   1597: fcmpl
    //   1598: ifle -> 1657
    //   1601: iload #8
    //   1603: iconst_1
    //   1604: if_icmpne -> 1620
    //   1607: fload #7
    //   1609: fload #6
    //   1611: fdiv
    //   1612: invokestatic abs : (F)F
    //   1615: fstore #6
    //   1617: goto -> 1660
    //   1620: fload #6
    //   1622: fload #7
    //   1624: fdiv
    //   1625: invokestatic abs : (F)F
    //   1628: fstore #6
    //   1630: goto -> 1660
    //   1633: aload #5
    //   1635: iload #9
    //   1637: invokevirtual substring : (I)Ljava/lang/String;
    //   1640: astore_2
    //   1641: aload_2
    //   1642: invokevirtual length : ()I
    //   1645: ifle -> 1657
    //   1648: aload_2
    //   1649: invokestatic parseFloat : (Ljava/lang/String;)F
    //   1652: fstore #6
    //   1654: goto -> 1660
    //   1657: fconst_0
    //   1658: fstore #6
    //   1660: fload #6
    //   1662: fconst_0
    //   1663: fcmpl
    //   1664: ifle -> 1687
    //   1667: aload_3
    //   1668: fload #6
    //   1670: putfield N : F
    //   1673: aload_3
    //   1674: iload #8
    //   1676: putfield O : I
    //   1679: goto -> 1687
    //   1682: aload_3
    //   1683: fconst_0
    //   1684: putfield N : F
    //   1687: aload #4
    //   1689: getfield D : F
    //   1692: fstore #6
    //   1694: aload_3
    //   1695: getfield c0 : [F
    //   1698: astore_2
    //   1699: aload_2
    //   1700: iconst_0
    //   1701: fload #6
    //   1703: fastore
    //   1704: aload_2
    //   1705: iconst_1
    //   1706: aload #4
    //   1708: getfield E : F
    //   1711: fastore
    //   1712: aload_3
    //   1713: aload #4
    //   1715: getfield F : I
    //   1718: putfield a0 : I
    //   1721: aload_3
    //   1722: aload #4
    //   1724: getfield G : I
    //   1727: putfield b0 : I
    //   1730: aload #4
    //   1732: getfield H : I
    //   1735: istore #8
    //   1737: aload #4
    //   1739: getfield J : I
    //   1742: istore #10
    //   1744: aload #4
    //   1746: getfield L : I
    //   1749: istore #9
    //   1751: aload #4
    //   1753: getfield N : F
    //   1756: fstore #6
    //   1758: aload_3
    //   1759: iload #8
    //   1761: putfield j : I
    //   1764: aload_3
    //   1765: iload #10
    //   1767: putfield m : I
    //   1770: iload #9
    //   1772: istore #8
    //   1774: iload #9
    //   1776: ldc 2147483647
    //   1778: if_icmpne -> 1784
    //   1781: iconst_0
    //   1782: istore #8
    //   1784: aload_3
    //   1785: iload #8
    //   1787: putfield n : I
    //   1790: aload_3
    //   1791: fload #6
    //   1793: putfield o : F
    //   1796: fload #6
    //   1798: fconst_0
    //   1799: fcmpl
    //   1800: ifle -> 1822
    //   1803: fload #6
    //   1805: fconst_1
    //   1806: fcmpg
    //   1807: ifge -> 1822
    //   1810: aload_3
    //   1811: getfield j : I
    //   1814: ifne -> 1822
    //   1817: aload_3
    //   1818: iconst_2
    //   1819: putfield j : I
    //   1822: aload #4
    //   1824: getfield I : I
    //   1827: istore #9
    //   1829: aload #4
    //   1831: getfield K : I
    //   1834: istore #10
    //   1836: aload #4
    //   1838: getfield M : I
    //   1841: istore #8
    //   1843: aload #4
    //   1845: getfield O : F
    //   1848: fstore #6
    //   1850: aload_3
    //   1851: iload #9
    //   1853: putfield k : I
    //   1856: aload_3
    //   1857: iload #10
    //   1859: putfield p : I
    //   1862: iload #8
    //   1864: ldc 2147483647
    //   1866: if_icmpne -> 1875
    //   1869: iconst_0
    //   1870: istore #8
    //   1872: goto -> 1875
    //   1875: aload_3
    //   1876: iload #8
    //   1878: putfield q : I
    //   1881: aload_3
    //   1882: fload #6
    //   1884: putfield r : F
    //   1887: fload #6
    //   1889: fconst_0
    //   1890: fcmpl
    //   1891: ifle -> 1913
    //   1894: fload #6
    //   1896: fconst_1
    //   1897: fcmpg
    //   1898: ifge -> 1913
    //   1901: aload_3
    //   1902: getfield k : I
    //   1905: ifne -> 1913
    //   1908: aload_3
    //   1909: iconst_2
    //   1910: putfield k : I
    //   1913: return
    //   1914: astore_2
    //   1915: goto -> 1657
    // Exception table:
    //   from	to	target	type
    //   1574	1587	1914	java/lang/NumberFormatException
    //   1607	1617	1914	java/lang/NumberFormatException
    //   1620	1630	1914	java/lang/NumberFormatException
    //   1648	1654	1914	java/lang/NumberFormatException
  }
  
  public void addView(View paramView, int paramInt, ViewGroup.LayoutParams paramLayoutParams) {
    super.addView(paramView, paramInt, paramLayoutParams);
  }
  
  public a b() {
    return new a(-2, -2);
  }
  
  public Object c(int paramInt, Object<String, Integer> paramObject) {
    if (paramInt == 0 && paramObject instanceof String) {
      String str = (String)paramObject;
      paramObject = (Object<String, Integer>)this.n;
      if (paramObject != null && paramObject.containsKey(str))
        return this.n.get(str); 
    } 
    return null;
  }
  
  public boolean checkLayoutParams(ViewGroup.LayoutParams paramLayoutParams) {
    return paramLayoutParams instanceof a;
  }
  
  public View d(int paramInt) {
    return (View)this.b.get(paramInt);
  }
  
  public void dispatchDraw(Canvas paramCanvas) {
    ArrayList<c> arrayList = this.c;
    if (arrayList != null) {
      int i = arrayList.size();
      if (i > 0)
        for (byte b1 = 0; b1 < i; b1++)
          ((c)this.c.get(b1)).h();  
    } 
    super.dispatchDraw(paramCanvas);
    if (isInEditMode()) {
      int i = getChildCount();
      float f2 = getWidth();
      float f1 = getHeight();
      for (byte b1 = 0; b1 < i; b1++) {
        View view = getChildAt(b1);
        if (view.getVisibility() != 8) {
          Object object = view.getTag();
          if (object != null && object instanceof String) {
            object = ((String)object).split(",");
            if (object.length == 4) {
              int k = Integer.parseInt((String)object[0]);
              int n = Integer.parseInt((String)object[1]);
              int m = Integer.parseInt((String)object[2]);
              int j = Integer.parseInt((String)object[3]);
              k = (int)(k / 1080.0F * f2);
              n = (int)(n / 1920.0F * f1);
              m = (int)(m / 1080.0F * f2);
              j = (int)(j / 1920.0F * f1);
              object = new Paint();
              object.setColor(-65536);
              float f3 = k;
              float f5 = n;
              float f4 = (k + m);
              paramCanvas.drawLine(f3, f5, f4, f5, (Paint)object);
              float f6 = (n + j);
              paramCanvas.drawLine(f4, f5, f4, f6, (Paint)object);
              paramCanvas.drawLine(f4, f6, f3, f6, (Paint)object);
              paramCanvas.drawLine(f3, f6, f3, f5, (Paint)object);
              object.setColor(-16711936);
              paramCanvas.drawLine(f3, f5, f4, f6, (Paint)object);
              paramCanvas.drawLine(f3, f6, f4, f5, (Paint)object);
            } 
          } 
        } 
      } 
    } 
  }
  
  public final d e(View paramView) {
    d d1;
    if (paramView == this)
      return (d)this.d; 
    if (paramView == null) {
      paramView = null;
    } else {
      d1 = ((a)paramView.getLayoutParams()).m0;
    } 
    return d1;
  }
  
  public boolean f() {
    int i = (getContext().getApplicationInfo()).flags;
    boolean bool2 = false;
    if ((i & 0x400000) != 0) {
      i = 1;
    } else {
      i = 0;
    } 
    boolean bool1 = bool2;
    if (i != 0) {
      bool1 = bool2;
      if (1 == getLayoutDirection())
        bool1 = true; 
    } 
    return bool1;
  }
  
  public void forceLayout() {
    this.i = true;
    this.o = -1;
    this.p = -1;
    super.forceLayout();
  }
  
  public void g(int paramInt, Object paramObject1, Object paramObject2) {
    if (paramInt == 0 && paramObject1 instanceof String && paramObject2 instanceof Integer) {
      if (this.n == null)
        this.n = new HashMap<String, Integer>(); 
      String str = (String)paramObject1;
      paramInt = str.indexOf("/");
      paramObject1 = str;
      if (paramInt != -1)
        paramObject1 = str.substring(paramInt + 1); 
      paramInt = ((Integer)paramObject2).intValue();
      this.n.put(paramObject1, Integer.valueOf(paramInt));
    } 
  }
  
  public ViewGroup.LayoutParams generateLayoutParams(AttributeSet paramAttributeSet) {
    return (ViewGroup.LayoutParams)new a(getContext(), paramAttributeSet);
  }
  
  public ViewGroup.LayoutParams generateLayoutParams(ViewGroup.LayoutParams paramLayoutParams) {
    return (ViewGroup.LayoutParams)new a(paramLayoutParams);
  }
  
  public int getMaxHeight() {
    return this.h;
  }
  
  public int getMaxWidth() {
    return this.g;
  }
  
  public int getMinHeight() {
    return this.f;
  }
  
  public int getMinWidth() {
    return this.e;
  }
  
  public int getOptimizationLevel() {
    return this.d.r0;
  }
  
  public final boolean h() {
    // Byte code:
    //   0: aload_0
    //   1: invokevirtual getChildCount : ()I
    //   4: istore_2
    //   5: iconst_0
    //   6: istore_1
    //   7: iload_1
    //   8: iload_2
    //   9: if_icmpge -> 35
    //   12: aload_0
    //   13: iload_1
    //   14: invokevirtual getChildAt : (I)Landroid/view/View;
    //   17: invokevirtual isLayoutRequested : ()Z
    //   20: ifeq -> 29
    //   23: iconst_1
    //   24: istore #7
    //   26: goto -> 38
    //   29: iinc #1, 1
    //   32: goto -> 7
    //   35: iconst_0
    //   36: istore #7
    //   38: iload #7
    //   40: ifeq -> 2738
    //   43: aload_0
    //   44: invokevirtual isInEditMode : ()Z
    //   47: istore #8
    //   49: aload_0
    //   50: invokevirtual getChildCount : ()I
    //   53: istore_1
    //   54: iconst_0
    //   55: istore_2
    //   56: iload_2
    //   57: iload_1
    //   58: if_icmpge -> 91
    //   61: aload_0
    //   62: aload_0
    //   63: iload_2
    //   64: invokevirtual getChildAt : (I)Landroid/view/View;
    //   67: invokevirtual e : (Landroid/view/View;)Lb/g/b/i/d;
    //   70: astore #10
    //   72: aload #10
    //   74: ifnonnull -> 80
    //   77: goto -> 85
    //   80: aload #10
    //   82: invokevirtual u : ()V
    //   85: iinc #2, 1
    //   88: goto -> 56
    //   91: iload #8
    //   93: ifeq -> 302
    //   96: iconst_0
    //   97: istore_2
    //   98: iload_2
    //   99: iload_1
    //   100: if_icmpge -> 302
    //   103: aload_0
    //   104: iload_2
    //   105: invokevirtual getChildAt : (I)Landroid/view/View;
    //   108: astore #12
    //   110: aload_0
    //   111: invokevirtual getResources : ()Landroid/content/res/Resources;
    //   114: aload #12
    //   116: invokevirtual getId : ()I
    //   119: invokevirtual getResourceName : (I)Ljava/lang/String;
    //   122: astore #10
    //   124: aload_0
    //   125: iconst_0
    //   126: aload #10
    //   128: aload #12
    //   130: invokevirtual getId : ()I
    //   133: invokestatic valueOf : (I)Ljava/lang/Integer;
    //   136: invokevirtual g : (ILjava/lang/Object;Ljava/lang/Object;)V
    //   139: aload #10
    //   141: bipush #47
    //   143: invokevirtual indexOf : (I)I
    //   146: istore_3
    //   147: aload #10
    //   149: astore #11
    //   151: iload_3
    //   152: iconst_m1
    //   153: if_icmpeq -> 166
    //   156: aload #10
    //   158: iload_3
    //   159: iconst_1
    //   160: iadd
    //   161: invokevirtual substring : (I)Ljava/lang/String;
    //   164: astore #11
    //   166: aload #12
    //   168: invokevirtual getId : ()I
    //   171: istore_3
    //   172: iload_3
    //   173: ifne -> 179
    //   176: goto -> 256
    //   179: aload_0
    //   180: getfield b : Landroid/util/SparseArray;
    //   183: iload_3
    //   184: invokevirtual get : (I)Ljava/lang/Object;
    //   187: checkcast android/view/View
    //   190: astore #12
    //   192: aload #12
    //   194: astore #10
    //   196: aload #12
    //   198: ifnonnull -> 250
    //   201: aload_0
    //   202: iload_3
    //   203: invokevirtual findViewById : (I)Landroid/view/View;
    //   206: astore #12
    //   208: aload #12
    //   210: astore #10
    //   212: aload #12
    //   214: ifnull -> 250
    //   217: aload #12
    //   219: astore #10
    //   221: aload #12
    //   223: aload_0
    //   224: if_acmpeq -> 250
    //   227: aload #12
    //   229: astore #10
    //   231: aload #12
    //   233: invokevirtual getParent : ()Landroid/view/ViewParent;
    //   236: aload_0
    //   237: if_acmpne -> 250
    //   240: aload_0
    //   241: aload #12
    //   243: invokevirtual onViewAdded : (Landroid/view/View;)V
    //   246: aload #12
    //   248: astore #10
    //   250: aload #10
    //   252: aload_0
    //   253: if_acmpne -> 265
    //   256: aload_0
    //   257: getfield d : Lb/g/b/i/e;
    //   260: astore #10
    //   262: goto -> 289
    //   265: aload #10
    //   267: ifnonnull -> 276
    //   270: aconst_null
    //   271: astore #10
    //   273: goto -> 289
    //   276: aload #10
    //   278: invokevirtual getLayoutParams : ()Landroid/view/ViewGroup$LayoutParams;
    //   281: checkcast androidx/constraintlayout/widget/ConstraintLayout$a
    //   284: getfield m0 : Lb/g/b/i/d;
    //   287: astore #10
    //   289: aload #10
    //   291: aload #11
    //   293: putfield Y : Ljava/lang/String;
    //   296: iinc #2, 1
    //   299: goto -> 98
    //   302: aload_0
    //   303: getfield m : I
    //   306: iconst_m1
    //   307: if_icmpeq -> 362
    //   310: iconst_0
    //   311: istore_2
    //   312: iload_2
    //   313: iload_1
    //   314: if_icmpge -> 362
    //   317: aload_0
    //   318: iload_2
    //   319: invokevirtual getChildAt : (I)Landroid/view/View;
    //   322: astore #10
    //   324: aload #10
    //   326: invokevirtual getId : ()I
    //   329: aload_0
    //   330: getfield m : I
    //   333: if_icmpne -> 356
    //   336: aload #10
    //   338: instanceof b/g/c/f
    //   341: ifeq -> 356
    //   344: aload_0
    //   345: aload #10
    //   347: checkcast b/g/c/f
    //   350: invokevirtual getConstraintSet : ()Lb/g/c/e;
    //   353: putfield k : Lb/g/c/e;
    //   356: iinc #2, 1
    //   359: goto -> 312
    //   362: aload_0
    //   363: getfield k : Lb/g/c/e;
    //   366: astore #12
    //   368: aload #12
    //   370: ifnull -> 2063
    //   373: aload_0
    //   374: invokevirtual getChildCount : ()I
    //   377: istore_3
    //   378: new java/util/HashSet
    //   381: dup
    //   382: aload #12
    //   384: getfield c : Ljava/util/HashMap;
    //   387: invokevirtual keySet : ()Ljava/util/Set;
    //   390: invokespecial <init> : (Ljava/util/Collection;)V
    //   393: astore #13
    //   395: iconst_0
    //   396: istore_2
    //   397: iload #8
    //   399: istore #6
    //   401: iload_2
    //   402: iload_3
    //   403: if_icmpge -> 1776
    //   406: aload_0
    //   407: iload_2
    //   408: invokevirtual getChildAt : (I)Landroid/view/View;
    //   411: astore #14
    //   413: aload #14
    //   415: invokevirtual getId : ()I
    //   418: istore #4
    //   420: aload #12
    //   422: getfield c : Ljava/util/HashMap;
    //   425: iload #4
    //   427: invokestatic valueOf : (I)Ljava/lang/Integer;
    //   430: invokevirtual containsKey : (Ljava/lang/Object;)Z
    //   433: ifne -> 495
    //   436: ldc_w 'id unknown '
    //   439: invokestatic e : (Ljava/lang/String;)Ljava/lang/StringBuilder;
    //   442: astore #11
    //   444: aload #14
    //   446: invokevirtual getContext : ()Landroid/content/Context;
    //   449: invokevirtual getResources : ()Landroid/content/res/Resources;
    //   452: aload #14
    //   454: invokevirtual getId : ()I
    //   457: invokevirtual getResourceEntryName : (I)Ljava/lang/String;
    //   460: astore #10
    //   462: goto -> 472
    //   465: astore #10
    //   467: ldc_w 'UNKNOWN'
    //   470: astore #10
    //   472: aload #11
    //   474: aload #10
    //   476: invokevirtual append : (Ljava/lang/String;)Ljava/lang/StringBuilder;
    //   479: pop
    //   480: ldc_w 'ConstraintSet'
    //   483: aload #11
    //   485: invokevirtual toString : ()Ljava/lang/String;
    //   488: invokestatic w : (Ljava/lang/String;Ljava/lang/String;)I
    //   491: pop
    //   492: goto -> 529
    //   495: aload #12
    //   497: getfield b : Z
    //   500: ifeq -> 523
    //   503: iload #4
    //   505: iconst_m1
    //   506: if_icmpeq -> 512
    //   509: goto -> 523
    //   512: new java/lang/RuntimeException
    //   515: dup
    //   516: ldc_w 'All children of ConstraintLayout must have ids to use ConstraintSet'
    //   519: invokespecial <init> : (Ljava/lang/String;)V
    //   522: athrow
    //   523: iload #4
    //   525: iconst_m1
    //   526: if_icmpne -> 532
    //   529: goto -> 1770
    //   532: aload #12
    //   534: getfield c : Ljava/util/HashMap;
    //   537: iload #4
    //   539: invokestatic valueOf : (I)Ljava/lang/Integer;
    //   542: invokevirtual containsKey : (Ljava/lang/Object;)Z
    //   545: ifeq -> 1732
    //   548: aload #13
    //   550: iload #4
    //   552: invokestatic valueOf : (I)Ljava/lang/Integer;
    //   555: invokevirtual remove : (Ljava/lang/Object;)Z
    //   558: pop
    //   559: aload #12
    //   561: getfield c : Ljava/util/HashMap;
    //   564: iload #4
    //   566: invokestatic valueOf : (I)Ljava/lang/Integer;
    //   569: invokevirtual get : (Ljava/lang/Object;)Ljava/lang/Object;
    //   572: checkcast b/g/c/e$a
    //   575: astore #15
    //   577: aload #14
    //   579: instanceof b/g/c/a
    //   582: ifeq -> 594
    //   585: aload #15
    //   587: getfield d : Lb/g/c/e$b;
    //   590: iconst_1
    //   591: putfield d0 : I
    //   594: aload #15
    //   596: getfield d : Lb/g/c/e$b;
    //   599: getfield d0 : I
    //   602: istore #5
    //   604: iload #5
    //   606: iconst_m1
    //   607: if_icmpeq -> 740
    //   610: iload #5
    //   612: iconst_1
    //   613: if_icmpeq -> 619
    //   616: goto -> 740
    //   619: aload #14
    //   621: checkcast b/g/c/a
    //   624: astore #10
    //   626: aload #10
    //   628: iload #4
    //   630: invokevirtual setId : (I)V
    //   633: aload #10
    //   635: aload #15
    //   637: getfield d : Lb/g/c/e$b;
    //   640: getfield b0 : I
    //   643: invokevirtual setType : (I)V
    //   646: aload #10
    //   648: aload #15
    //   650: getfield d : Lb/g/c/e$b;
    //   653: getfield c0 : I
    //   656: invokevirtual setMargin : (I)V
    //   659: aload #10
    //   661: aload #15
    //   663: getfield d : Lb/g/c/e$b;
    //   666: getfield j0 : Z
    //   669: invokevirtual setAllowsGoneWidget : (Z)V
    //   672: aload #15
    //   674: getfield d : Lb/g/c/e$b;
    //   677: astore #11
    //   679: aload #11
    //   681: getfield e0 : [I
    //   684: astore #16
    //   686: aload #16
    //   688: ifnull -> 701
    //   691: aload #10
    //   693: aload #16
    //   695: invokevirtual setReferencedIds : ([I)V
    //   698: goto -> 740
    //   701: aload #11
    //   703: getfield f0 : Ljava/lang/String;
    //   706: astore #16
    //   708: aload #16
    //   710: ifnull -> 740
    //   713: aload #11
    //   715: aload #12
    //   717: aload #10
    //   719: aload #16
    //   721: invokevirtual c : (Landroid/view/View;Ljava/lang/String;)[I
    //   724: putfield e0 : [I
    //   727: aload #10
    //   729: aload #15
    //   731: getfield d : Lb/g/c/e$b;
    //   734: getfield e0 : [I
    //   737: invokevirtual setReferencedIds : ([I)V
    //   740: aload #14
    //   742: invokevirtual getLayoutParams : ()Landroid/view/ViewGroup$LayoutParams;
    //   745: checkcast androidx/constraintlayout/widget/ConstraintLayout$a
    //   748: astore #16
    //   750: aload #16
    //   752: invokevirtual a : ()V
    //   755: aload #15
    //   757: aload #16
    //   759: invokevirtual a : (Landroidx/constraintlayout/widget/ConstraintLayout$a;)V
    //   762: aload #15
    //   764: getfield f : Ljava/util/HashMap;
    //   767: astore #10
    //   769: aload #14
    //   771: invokevirtual getClass : ()Ljava/lang/Class;
    //   774: astore #18
    //   776: aload #10
    //   778: invokevirtual keySet : ()Ljava/util/Set;
    //   781: invokeinterface iterator : ()Ljava/util/Iterator;
    //   786: astore #17
    //   788: aload #17
    //   790: invokeinterface hasNext : ()Z
    //   795: ifeq -> 1468
    //   798: aload #17
    //   800: invokeinterface next : ()Ljava/lang/Object;
    //   805: checkcast java/lang/String
    //   808: astore #19
    //   810: aload #10
    //   812: aload #19
    //   814: invokevirtual get : (Ljava/lang/Object;)Ljava/lang/Object;
    //   817: checkcast b/g/c/b
    //   820: astore #21
    //   822: ldc_w 'set'
    //   825: aload #19
    //   827: invokestatic c : (Ljava/lang/String;Ljava/lang/String;)Ljava/lang/String;
    //   830: astore #20
    //   832: aload #21
    //   834: getfield b : Lb/g/c/b$a;
    //   837: invokevirtual ordinal : ()I
    //   840: istore #4
    //   842: iload #4
    //   844: tableswitch default -> 888, 0 -> 1152, 1 -> 1111, 2 -> 1070, 3 -> 1011, 4 -> 973, 5 -> 932, 6 -> 891
    //   888: goto -> 1465
    //   891: aload #18
    //   893: aload #20
    //   895: iconst_1
    //   896: anewarray java/lang/Class
    //   899: dup
    //   900: iconst_0
    //   901: getstatic java/lang/Float.TYPE : Ljava/lang/Class;
    //   904: aastore
    //   905: invokevirtual getMethod : (Ljava/lang/String;[Ljava/lang/Class;)Ljava/lang/reflect/Method;
    //   908: aload #14
    //   910: iconst_1
    //   911: anewarray java/lang/Object
    //   914: dup
    //   915: iconst_0
    //   916: aload #21
    //   918: getfield d : F
    //   921: invokestatic valueOf : (F)Ljava/lang/Float;
    //   924: aastore
    //   925: invokevirtual invoke : (Ljava/lang/Object;[Ljava/lang/Object;)Ljava/lang/Object;
    //   928: pop
    //   929: goto -> 1465
    //   932: aload #18
    //   934: aload #20
    //   936: iconst_1
    //   937: anewarray java/lang/Class
    //   940: dup
    //   941: iconst_0
    //   942: getstatic java/lang/Boolean.TYPE : Ljava/lang/Class;
    //   945: aastore
    //   946: invokevirtual getMethod : (Ljava/lang/String;[Ljava/lang/Class;)Ljava/lang/reflect/Method;
    //   949: aload #14
    //   951: iconst_1
    //   952: anewarray java/lang/Object
    //   955: dup
    //   956: iconst_0
    //   957: aload #21
    //   959: getfield f : Z
    //   962: invokestatic valueOf : (Z)Ljava/lang/Boolean;
    //   965: aastore
    //   966: invokevirtual invoke : (Ljava/lang/Object;[Ljava/lang/Object;)Ljava/lang/Object;
    //   969: pop
    //   970: goto -> 1465
    //   973: aload #18
    //   975: aload #20
    //   977: iconst_1
    //   978: anewarray java/lang/Class
    //   981: dup
    //   982: iconst_0
    //   983: ldc_w java/lang/CharSequence
    //   986: aastore
    //   987: invokevirtual getMethod : (Ljava/lang/String;[Ljava/lang/Class;)Ljava/lang/reflect/Method;
    //   990: aload #14
    //   992: iconst_1
    //   993: anewarray java/lang/Object
    //   996: dup
    //   997: iconst_0
    //   998: aload #21
    //   1000: getfield e : Ljava/lang/String;
    //   1003: aastore
    //   1004: invokevirtual invoke : (Ljava/lang/Object;[Ljava/lang/Object;)Ljava/lang/Object;
    //   1007: pop
    //   1008: goto -> 1465
    //   1011: aload #18
    //   1013: aload #20
    //   1015: iconst_1
    //   1016: anewarray java/lang/Class
    //   1019: dup
    //   1020: iconst_0
    //   1021: ldc_w android/graphics/drawable/Drawable
    //   1024: aastore
    //   1025: invokevirtual getMethod : (Ljava/lang/String;[Ljava/lang/Class;)Ljava/lang/reflect/Method;
    //   1028: astore #11
    //   1030: new android/graphics/drawable/ColorDrawable
    //   1033: astore #22
    //   1035: aload #22
    //   1037: invokespecial <init> : ()V
    //   1040: aload #22
    //   1042: aload #21
    //   1044: getfield g : I
    //   1047: invokevirtual setColor : (I)V
    //   1050: aload #11
    //   1052: aload #14
    //   1054: iconst_1
    //   1055: anewarray java/lang/Object
    //   1058: dup
    //   1059: iconst_0
    //   1060: aload #22
    //   1062: aastore
    //   1063: invokevirtual invoke : (Ljava/lang/Object;[Ljava/lang/Object;)Ljava/lang/Object;
    //   1066: pop
    //   1067: goto -> 1465
    //   1070: aload #18
    //   1072: aload #20
    //   1074: iconst_1
    //   1075: anewarray java/lang/Class
    //   1078: dup
    //   1079: iconst_0
    //   1080: getstatic java/lang/Integer.TYPE : Ljava/lang/Class;
    //   1083: aastore
    //   1084: invokevirtual getMethod : (Ljava/lang/String;[Ljava/lang/Class;)Ljava/lang/reflect/Method;
    //   1087: aload #14
    //   1089: iconst_1
    //   1090: anewarray java/lang/Object
    //   1093: dup
    //   1094: iconst_0
    //   1095: aload #21
    //   1097: getfield g : I
    //   1100: invokestatic valueOf : (I)Ljava/lang/Integer;
    //   1103: aastore
    //   1104: invokevirtual invoke : (Ljava/lang/Object;[Ljava/lang/Object;)Ljava/lang/Object;
    //   1107: pop
    //   1108: goto -> 1465
    //   1111: aload #18
    //   1113: aload #20
    //   1115: iconst_1
    //   1116: anewarray java/lang/Class
    //   1119: dup
    //   1120: iconst_0
    //   1121: getstatic java/lang/Float.TYPE : Ljava/lang/Class;
    //   1124: aastore
    //   1125: invokevirtual getMethod : (Ljava/lang/String;[Ljava/lang/Class;)Ljava/lang/reflect/Method;
    //   1128: aload #14
    //   1130: iconst_1
    //   1131: anewarray java/lang/Object
    //   1134: dup
    //   1135: iconst_0
    //   1136: aload #21
    //   1138: getfield d : F
    //   1141: invokestatic valueOf : (F)Ljava/lang/Float;
    //   1144: aastore
    //   1145: invokevirtual invoke : (Ljava/lang/Object;[Ljava/lang/Object;)Ljava/lang/Object;
    //   1148: pop
    //   1149: goto -> 1465
    //   1152: aload #18
    //   1154: aload #20
    //   1156: iconst_1
    //   1157: anewarray java/lang/Class
    //   1160: dup
    //   1161: iconst_0
    //   1162: getstatic java/lang/Integer.TYPE : Ljava/lang/Class;
    //   1165: aastore
    //   1166: invokevirtual getMethod : (Ljava/lang/String;[Ljava/lang/Class;)Ljava/lang/reflect/Method;
    //   1169: aload #14
    //   1171: iconst_1
    //   1172: anewarray java/lang/Object
    //   1175: dup
    //   1176: iconst_0
    //   1177: aload #21
    //   1179: getfield c : I
    //   1182: invokestatic valueOf : (I)Ljava/lang/Integer;
    //   1185: aastore
    //   1186: invokevirtual invoke : (Ljava/lang/Object;[Ljava/lang/Object;)Ljava/lang/Object;
    //   1189: pop
    //   1190: goto -> 1465
    //   1193: astore #11
    //   1195: goto -> 1210
    //   1198: astore #11
    //   1200: goto -> 1278
    //   1203: astore #11
    //   1205: goto -> 1346
    //   1208: astore #11
    //   1210: new java/lang/StringBuilder
    //   1213: dup
    //   1214: invokespecial <init> : ()V
    //   1217: astore #20
    //   1219: aload #20
    //   1221: ldc_w ' Custom Attribute "'
    //   1224: invokevirtual append : (Ljava/lang/String;)Ljava/lang/StringBuilder;
    //   1227: pop
    //   1228: aload #20
    //   1230: aload #19
    //   1232: invokevirtual append : (Ljava/lang/String;)Ljava/lang/StringBuilder;
    //   1235: pop
    //   1236: aload #20
    //   1238: ldc_w '" not found on '
    //   1241: invokevirtual append : (Ljava/lang/String;)Ljava/lang/StringBuilder;
    //   1244: pop
    //   1245: aload #20
    //   1247: aload #18
    //   1249: invokevirtual getName : ()Ljava/lang/String;
    //   1252: invokevirtual append : (Ljava/lang/String;)Ljava/lang/StringBuilder;
    //   1255: pop
    //   1256: ldc_w 'TransitionLayout'
    //   1259: aload #20
    //   1261: invokevirtual toString : ()Ljava/lang/String;
    //   1264: invokestatic e : (Ljava/lang/String;Ljava/lang/String;)I
    //   1267: pop
    //   1268: aload #11
    //   1270: invokevirtual printStackTrace : ()V
    //   1273: goto -> 1465
    //   1276: astore #11
    //   1278: new java/lang/StringBuilder
    //   1281: dup
    //   1282: invokespecial <init> : ()V
    //   1285: astore #20
    //   1287: aload #20
    //   1289: ldc_w ' Custom Attribute "'
    //   1292: invokevirtual append : (Ljava/lang/String;)Ljava/lang/StringBuilder;
    //   1295: pop
    //   1296: aload #20
    //   1298: aload #19
    //   1300: invokevirtual append : (Ljava/lang/String;)Ljava/lang/StringBuilder;
    //   1303: pop
    //   1304: aload #20
    //   1306: ldc_w '" not found on '
    //   1309: invokevirtual append : (Ljava/lang/String;)Ljava/lang/StringBuilder;
    //   1312: pop
    //   1313: aload #20
    //   1315: aload #18
    //   1317: invokevirtual getName : ()Ljava/lang/String;
    //   1320: invokevirtual append : (Ljava/lang/String;)Ljava/lang/StringBuilder;
    //   1323: pop
    //   1324: ldc_w 'TransitionLayout'
    //   1327: aload #20
    //   1329: invokevirtual toString : ()Ljava/lang/String;
    //   1332: invokestatic e : (Ljava/lang/String;Ljava/lang/String;)I
    //   1335: pop
    //   1336: aload #11
    //   1338: invokevirtual printStackTrace : ()V
    //   1341: goto -> 1465
    //   1344: astore #11
    //   1346: ldc_w 'TransitionLayout'
    //   1349: aload #11
    //   1351: invokevirtual getMessage : ()Ljava/lang/String;
    //   1354: invokestatic e : (Ljava/lang/String;Ljava/lang/String;)I
    //   1357: pop
    //   1358: new java/lang/StringBuilder
    //   1361: dup
    //   1362: invokespecial <init> : ()V
    //   1365: astore #11
    //   1367: aload #11
    //   1369: ldc_w ' Custom Attribute "'
    //   1372: invokevirtual append : (Ljava/lang/String;)Ljava/lang/StringBuilder;
    //   1375: pop
    //   1376: aload #11
    //   1378: aload #19
    //   1380: invokevirtual append : (Ljava/lang/String;)Ljava/lang/StringBuilder;
    //   1383: pop
    //   1384: aload #11
    //   1386: ldc_w '" not found on '
    //   1389: invokevirtual append : (Ljava/lang/String;)Ljava/lang/StringBuilder;
    //   1392: pop
    //   1393: aload #11
    //   1395: aload #18
    //   1397: invokevirtual getName : ()Ljava/lang/String;
    //   1400: invokevirtual append : (Ljava/lang/String;)Ljava/lang/StringBuilder;
    //   1403: pop
    //   1404: ldc_w 'TransitionLayout'
    //   1407: aload #11
    //   1409: invokevirtual toString : ()Ljava/lang/String;
    //   1412: invokestatic e : (Ljava/lang/String;Ljava/lang/String;)I
    //   1415: pop
    //   1416: new java/lang/StringBuilder
    //   1419: dup
    //   1420: invokespecial <init> : ()V
    //   1423: astore #11
    //   1425: aload #11
    //   1427: aload #18
    //   1429: invokevirtual getName : ()Ljava/lang/String;
    //   1432: invokevirtual append : (Ljava/lang/String;)Ljava/lang/StringBuilder;
    //   1435: pop
    //   1436: aload #11
    //   1438: ldc_w ' must have a method '
    //   1441: invokevirtual append : (Ljava/lang/String;)Ljava/lang/StringBuilder;
    //   1444: pop
    //   1445: aload #11
    //   1447: aload #20
    //   1449: invokevirtual append : (Ljava/lang/String;)Ljava/lang/StringBuilder;
    //   1452: pop
    //   1453: ldc_w 'TransitionLayout'
    //   1456: aload #11
    //   1458: invokevirtual toString : ()Ljava/lang/String;
    //   1461: invokestatic e : (Ljava/lang/String;Ljava/lang/String;)I
    //   1464: pop
    //   1465: goto -> 788
    //   1468: iload #7
    //   1470: istore #8
    //   1472: iload #6
    //   1474: istore #9
    //   1476: iload_1
    //   1477: istore #4
    //   1479: aload #14
    //   1481: aload #16
    //   1483: invokevirtual setLayoutParams : (Landroid/view/ViewGroup$LayoutParams;)V
    //   1486: aload #15
    //   1488: getfield b : Lb/g/c/e$d;
    //   1491: astore #10
    //   1493: aload #10
    //   1495: getfield c : I
    //   1498: ifne -> 1511
    //   1501: aload #14
    //   1503: aload #10
    //   1505: getfield b : I
    //   1508: invokevirtual setVisibility : (I)V
    //   1511: aload #14
    //   1513: aload #15
    //   1515: getfield b : Lb/g/c/e$d;
    //   1518: getfield d : F
    //   1521: invokevirtual setAlpha : (F)V
    //   1524: aload #14
    //   1526: aload #15
    //   1528: getfield e : Lb/g/c/e$e;
    //   1531: getfield b : F
    //   1534: invokevirtual setRotation : (F)V
    //   1537: aload #14
    //   1539: aload #15
    //   1541: getfield e : Lb/g/c/e$e;
    //   1544: getfield c : F
    //   1547: invokevirtual setRotationX : (F)V
    //   1550: aload #14
    //   1552: aload #15
    //   1554: getfield e : Lb/g/c/e$e;
    //   1557: getfield d : F
    //   1560: invokevirtual setRotationY : (F)V
    //   1563: aload #14
    //   1565: aload #15
    //   1567: getfield e : Lb/g/c/e$e;
    //   1570: getfield e : F
    //   1573: invokevirtual setScaleX : (F)V
    //   1576: aload #14
    //   1578: aload #15
    //   1580: getfield e : Lb/g/c/e$e;
    //   1583: getfield f : F
    //   1586: invokevirtual setScaleY : (F)V
    //   1589: aload #15
    //   1591: getfield e : Lb/g/c/e$e;
    //   1594: getfield g : F
    //   1597: invokestatic isNaN : (F)Z
    //   1600: ifne -> 1616
    //   1603: aload #14
    //   1605: aload #15
    //   1607: getfield e : Lb/g/c/e$e;
    //   1610: getfield g : F
    //   1613: invokevirtual setPivotX : (F)V
    //   1616: aload #15
    //   1618: getfield e : Lb/g/c/e$e;
    //   1621: getfield h : F
    //   1624: invokestatic isNaN : (F)Z
    //   1627: ifne -> 1643
    //   1630: aload #14
    //   1632: aload #15
    //   1634: getfield e : Lb/g/c/e$e;
    //   1637: getfield h : F
    //   1640: invokevirtual setPivotY : (F)V
    //   1643: aload #14
    //   1645: aload #15
    //   1647: getfield e : Lb/g/c/e$e;
    //   1650: getfield i : F
    //   1653: invokevirtual setTranslationX : (F)V
    //   1656: aload #14
    //   1658: aload #15
    //   1660: getfield e : Lb/g/c/e$e;
    //   1663: getfield j : F
    //   1666: invokevirtual setTranslationY : (F)V
    //   1669: aload #14
    //   1671: aload #15
    //   1673: getfield e : Lb/g/c/e$e;
    //   1676: getfield k : F
    //   1679: invokevirtual setTranslationZ : (F)V
    //   1682: aload #15
    //   1684: getfield e : Lb/g/c/e$e;
    //   1687: astore #10
    //   1689: iload #8
    //   1691: istore #7
    //   1693: iload #9
    //   1695: istore #6
    //   1697: iload #4
    //   1699: istore_1
    //   1700: aload #10
    //   1702: getfield l : Z
    //   1705: ifeq -> 1770
    //   1708: aload #14
    //   1710: aload #10
    //   1712: getfield m : F
    //   1715: invokevirtual setElevation : (F)V
    //   1718: iload #8
    //   1720: istore #7
    //   1722: iload #9
    //   1724: istore #6
    //   1726: iload #4
    //   1728: istore_1
    //   1729: goto -> 1770
    //   1732: new java/lang/StringBuilder
    //   1735: dup
    //   1736: invokespecial <init> : ()V
    //   1739: astore #10
    //   1741: aload #10
    //   1743: ldc_w 'WARNING NO CONSTRAINTS for view '
    //   1746: invokevirtual append : (Ljava/lang/String;)Ljava/lang/StringBuilder;
    //   1749: pop
    //   1750: aload #10
    //   1752: iload #4
    //   1754: invokevirtual append : (I)Ljava/lang/StringBuilder;
    //   1757: pop
    //   1758: ldc_w 'ConstraintSet'
    //   1761: aload #10
    //   1763: invokevirtual toString : ()Ljava/lang/String;
    //   1766: invokestatic v : (Ljava/lang/String;Ljava/lang/String;)I
    //   1769: pop
    //   1770: iinc #2, 1
    //   1773: goto -> 401
    //   1776: iload #7
    //   1778: istore #8
    //   1780: iload #6
    //   1782: istore #9
    //   1784: iload_1
    //   1785: istore_2
    //   1786: aload #13
    //   1788: invokevirtual iterator : ()Ljava/util/Iterator;
    //   1791: astore #10
    //   1793: iload #8
    //   1795: istore #6
    //   1797: iload #9
    //   1799: istore #7
    //   1801: iload_2
    //   1802: istore_1
    //   1803: aload #10
    //   1805: invokeinterface hasNext : ()Z
    //   1810: ifeq -> 2071
    //   1813: aload #10
    //   1815: invokeinterface next : ()Ljava/lang/Object;
    //   1820: checkcast java/lang/Integer
    //   1823: astore #13
    //   1825: aload #12
    //   1827: getfield c : Ljava/util/HashMap;
    //   1830: aload #13
    //   1832: invokevirtual get : (Ljava/lang/Object;)Ljava/lang/Object;
    //   1835: checkcast b/g/c/e$a
    //   1838: astore #11
    //   1840: aload #11
    //   1842: getfield d : Lb/g/c/e$b;
    //   1845: getfield d0 : I
    //   1848: istore_1
    //   1849: iload_1
    //   1850: iconst_m1
    //   1851: if_icmpeq -> 2005
    //   1854: iload_1
    //   1855: iconst_1
    //   1856: if_icmpeq -> 1862
    //   1859: goto -> 2005
    //   1862: new b/g/c/a
    //   1865: dup
    //   1866: aload_0
    //   1867: invokevirtual getContext : ()Landroid/content/Context;
    //   1870: invokespecial <init> : (Landroid/content/Context;)V
    //   1873: astore #14
    //   1875: aload #14
    //   1877: aload #13
    //   1879: invokevirtual intValue : ()I
    //   1882: invokevirtual setId : (I)V
    //   1885: aload #11
    //   1887: getfield d : Lb/g/c/e$b;
    //   1890: astore #15
    //   1892: aload #15
    //   1894: getfield e0 : [I
    //   1897: astore #16
    //   1899: aload #16
    //   1901: ifnull -> 1914
    //   1904: aload #14
    //   1906: aload #16
    //   1908: invokevirtual setReferencedIds : ([I)V
    //   1911: goto -> 1953
    //   1914: aload #15
    //   1916: getfield f0 : Ljava/lang/String;
    //   1919: astore #16
    //   1921: aload #16
    //   1923: ifnull -> 1953
    //   1926: aload #15
    //   1928: aload #12
    //   1930: aload #14
    //   1932: aload #16
    //   1934: invokevirtual c : (Landroid/view/View;Ljava/lang/String;)[I
    //   1937: putfield e0 : [I
    //   1940: aload #14
    //   1942: aload #11
    //   1944: getfield d : Lb/g/c/e$b;
    //   1947: getfield e0 : [I
    //   1950: invokevirtual setReferencedIds : ([I)V
    //   1953: aload #14
    //   1955: aload #11
    //   1957: getfield d : Lb/g/c/e$b;
    //   1960: getfield b0 : I
    //   1963: invokevirtual setType : (I)V
    //   1966: aload #14
    //   1968: aload #11
    //   1970: getfield d : Lb/g/c/e$b;
    //   1973: getfield c0 : I
    //   1976: invokevirtual setMargin : (I)V
    //   1979: aload_0
    //   1980: invokevirtual b : ()Landroidx/constraintlayout/widget/ConstraintLayout$a;
    //   1983: astore #15
    //   1985: aload #14
    //   1987: invokevirtual i : ()V
    //   1990: aload #11
    //   1992: aload #15
    //   1994: invokevirtual a : (Landroidx/constraintlayout/widget/ConstraintLayout$a;)V
    //   1997: aload_0
    //   1998: aload #14
    //   2000: aload #15
    //   2002: invokevirtual addView : (Landroid/view/View;Landroid/view/ViewGroup$LayoutParams;)V
    //   2005: aload #11
    //   2007: getfield d : Lb/g/c/e$b;
    //   2010: getfield a : Z
    //   2013: ifeq -> 1793
    //   2016: new b/g/c/h
    //   2019: dup
    //   2020: aload_0
    //   2021: invokevirtual getContext : ()Landroid/content/Context;
    //   2024: invokespecial <init> : (Landroid/content/Context;)V
    //   2027: astore #14
    //   2029: aload #14
    //   2031: aload #13
    //   2033: invokevirtual intValue : ()I
    //   2036: invokevirtual setId : (I)V
    //   2039: aload_0
    //   2040: invokevirtual b : ()Landroidx/constraintlayout/widget/ConstraintLayout$a;
    //   2043: astore #13
    //   2045: aload #11
    //   2047: aload #13
    //   2049: invokevirtual a : (Landroidx/constraintlayout/widget/ConstraintLayout$a;)V
    //   2052: aload_0
    //   2053: aload #14
    //   2055: aload #13
    //   2057: invokevirtual addView : (Landroid/view/View;Landroid/view/ViewGroup$LayoutParams;)V
    //   2060: goto -> 1793
    //   2063: iload #7
    //   2065: istore #6
    //   2067: iload #8
    //   2069: istore #7
    //   2071: aload_0
    //   2072: getfield d : Lb/g/b/i/e;
    //   2075: getfield f0 : Ljava/util/ArrayList;
    //   2078: invokevirtual clear : ()V
    //   2081: aload_0
    //   2082: getfield c : Ljava/util/ArrayList;
    //   2085: invokevirtual size : ()I
    //   2088: istore #4
    //   2090: iload #4
    //   2092: ifle -> 2428
    //   2095: iconst_0
    //   2096: istore_2
    //   2097: iload_2
    //   2098: iload #4
    //   2100: if_icmpge -> 2428
    //   2103: aload_0
    //   2104: getfield c : Ljava/util/ArrayList;
    //   2107: iload_2
    //   2108: invokevirtual get : (I)Ljava/lang/Object;
    //   2111: checkcast b/g/c/c
    //   2114: astore #12
    //   2116: aload #12
    //   2118: invokevirtual isInEditMode : ()Z
    //   2121: ifeq -> 2134
    //   2124: aload #12
    //   2126: aload #12
    //   2128: getfield g : Ljava/lang/String;
    //   2131: invokevirtual setIds : (Ljava/lang/String;)V
    //   2134: aload #12
    //   2136: getfield e : Lb/g/b/i/g;
    //   2139: astore #10
    //   2141: aload #10
    //   2143: ifnonnull -> 2149
    //   2146: goto -> 2422
    //   2149: aload #10
    //   2151: checkcast b/g/b/i/h
    //   2154: astore #10
    //   2156: aload #10
    //   2158: iconst_0
    //   2159: putfield g0 : I
    //   2162: aload #10
    //   2164: getfield f0 : [Lb/g/b/i/d;
    //   2167: aconst_null
    //   2168: invokestatic fill : ([Ljava/lang/Object;Ljava/lang/Object;)V
    //   2171: iconst_0
    //   2172: istore_3
    //   2173: iload_3
    //   2174: aload #12
    //   2176: getfield c : I
    //   2179: if_icmpge -> 2408
    //   2182: aload #12
    //   2184: getfield b : [I
    //   2187: iload_3
    //   2188: iaload
    //   2189: istore #5
    //   2191: aload_0
    //   2192: iload #5
    //   2194: invokevirtual d : (I)Landroid/view/View;
    //   2197: astore #11
    //   2199: aload #11
    //   2201: astore #10
    //   2203: aload #11
    //   2205: ifnonnull -> 2278
    //   2208: aload #12
    //   2210: getfield h : Ljava/util/HashMap;
    //   2213: iload #5
    //   2215: invokestatic valueOf : (I)Ljava/lang/Integer;
    //   2218: invokevirtual get : (Ljava/lang/Object;)Ljava/lang/Object;
    //   2221: checkcast java/lang/String
    //   2224: astore #13
    //   2226: aload #12
    //   2228: aload_0
    //   2229: aload #13
    //   2231: invokevirtual d : (Landroidx/constraintlayout/widget/ConstraintLayout;Ljava/lang/String;)I
    //   2234: istore #5
    //   2236: aload #11
    //   2238: astore #10
    //   2240: iload #5
    //   2242: ifeq -> 2278
    //   2245: aload #12
    //   2247: getfield b : [I
    //   2250: iload_3
    //   2251: iload #5
    //   2253: iastore
    //   2254: aload #12
    //   2256: getfield h : Ljava/util/HashMap;
    //   2259: iload #5
    //   2261: invokestatic valueOf : (I)Ljava/lang/Integer;
    //   2264: aload #13
    //   2266: invokevirtual put : (Ljava/lang/Object;Ljava/lang/Object;)Ljava/lang/Object;
    //   2269: pop
    //   2270: aload_0
    //   2271: iload #5
    //   2273: invokevirtual d : (I)Landroid/view/View;
    //   2276: astore #10
    //   2278: aload #10
    //   2280: ifnull -> 2402
    //   2283: aload #12
    //   2285: getfield e : Lb/g/b/i/g;
    //   2288: astore #11
    //   2290: aload_0
    //   2291: aload #10
    //   2293: invokevirtual e : (Landroid/view/View;)Lb/g/b/i/d;
    //   2296: astore #10
    //   2298: aload #11
    //   2300: checkcast b/g/b/i/h
    //   2303: astore #11
    //   2305: aload #11
    //   2307: ifnull -> 2400
    //   2310: aload #10
    //   2312: aload #11
    //   2314: if_acmpeq -> 2402
    //   2317: aload #10
    //   2319: ifnonnull -> 2325
    //   2322: goto -> 2402
    //   2325: aload #11
    //   2327: getfield g0 : I
    //   2330: istore #5
    //   2332: aload #11
    //   2334: getfield f0 : [Lb/g/b/i/d;
    //   2337: astore #13
    //   2339: iload #5
    //   2341: iconst_1
    //   2342: iadd
    //   2343: aload #13
    //   2345: arraylength
    //   2346: if_icmple -> 2367
    //   2349: aload #11
    //   2351: aload #13
    //   2353: aload #13
    //   2355: arraylength
    //   2356: iconst_2
    //   2357: imul
    //   2358: invokestatic copyOf : ([Ljava/lang/Object;I)[Ljava/lang/Object;
    //   2361: checkcast [Lb/g/b/i/d;
    //   2364: putfield f0 : [Lb/g/b/i/d;
    //   2367: aload #11
    //   2369: getfield f0 : [Lb/g/b/i/d;
    //   2372: astore #13
    //   2374: aload #11
    //   2376: getfield g0 : I
    //   2379: istore #5
    //   2381: aload #13
    //   2383: iload #5
    //   2385: aload #10
    //   2387: aastore
    //   2388: aload #11
    //   2390: iload #5
    //   2392: iconst_1
    //   2393: iadd
    //   2394: putfield g0 : I
    //   2397: goto -> 2402
    //   2400: aconst_null
    //   2401: athrow
    //   2402: iinc #3, 1
    //   2405: goto -> 2173
    //   2408: aload #12
    //   2410: getfield e : Lb/g/b/i/g;
    //   2413: aload_0
    //   2414: getfield d : Lb/g/b/i/e;
    //   2417: invokeinterface a : (Lb/g/b/i/e;)V
    //   2422: iinc #2, 1
    //   2425: goto -> 2097
    //   2428: iconst_0
    //   2429: istore_2
    //   2430: iload_2
    //   2431: iload_1
    //   2432: if_icmpge -> 2540
    //   2435: aload_0
    //   2436: iload_2
    //   2437: invokevirtual getChildAt : (I)Landroid/view/View;
    //   2440: astore #10
    //   2442: aload #10
    //   2444: instanceof b/g/c/i
    //   2447: ifeq -> 2534
    //   2450: aload #10
    //   2452: checkcast b/g/c/i
    //   2455: astore #10
    //   2457: aload #10
    //   2459: getfield b : I
    //   2462: iconst_m1
    //   2463: if_icmpne -> 2484
    //   2466: aload #10
    //   2468: invokevirtual isInEditMode : ()Z
    //   2471: ifne -> 2484
    //   2474: aload #10
    //   2476: aload #10
    //   2478: getfield d : I
    //   2481: invokevirtual setVisibility : (I)V
    //   2484: aload_0
    //   2485: aload #10
    //   2487: getfield b : I
    //   2490: invokevirtual findViewById : (I)Landroid/view/View;
    //   2493: astore #11
    //   2495: aload #10
    //   2497: aload #11
    //   2499: putfield c : Landroid/view/View;
    //   2502: aload #11
    //   2504: ifnull -> 2534
    //   2507: aload #11
    //   2509: invokevirtual getLayoutParams : ()Landroid/view/ViewGroup$LayoutParams;
    //   2512: checkcast androidx/constraintlayout/widget/ConstraintLayout$a
    //   2515: iconst_1
    //   2516: putfield a0 : Z
    //   2519: aload #10
    //   2521: getfield c : Landroid/view/View;
    //   2524: iconst_0
    //   2525: invokevirtual setVisibility : (I)V
    //   2528: aload #10
    //   2530: iconst_0
    //   2531: invokevirtual setVisibility : (I)V
    //   2534: iinc #2, 1
    //   2537: goto -> 2430
    //   2540: aload_0
    //   2541: getfield q : Landroid/util/SparseArray;
    //   2544: invokevirtual clear : ()V
    //   2547: aload_0
    //   2548: getfield q : Landroid/util/SparseArray;
    //   2551: iconst_0
    //   2552: aload_0
    //   2553: getfield d : Lb/g/b/i/e;
    //   2556: invokevirtual put : (ILjava/lang/Object;)V
    //   2559: aload_0
    //   2560: getfield q : Landroid/util/SparseArray;
    //   2563: aload_0
    //   2564: invokevirtual getId : ()I
    //   2567: aload_0
    //   2568: getfield d : Lb/g/b/i/e;
    //   2571: invokevirtual put : (ILjava/lang/Object;)V
    //   2574: iconst_0
    //   2575: istore_2
    //   2576: iload_2
    //   2577: iload_1
    //   2578: if_icmpge -> 2616
    //   2581: aload_0
    //   2582: iload_2
    //   2583: invokevirtual getChildAt : (I)Landroid/view/View;
    //   2586: astore #11
    //   2588: aload_0
    //   2589: aload #11
    //   2591: invokevirtual e : (Landroid/view/View;)Lb/g/b/i/d;
    //   2594: astore #10
    //   2596: aload_0
    //   2597: getfield q : Landroid/util/SparseArray;
    //   2600: aload #11
    //   2602: invokevirtual getId : ()I
    //   2605: aload #10
    //   2607: invokevirtual put : (ILjava/lang/Object;)V
    //   2610: iinc #2, 1
    //   2613: goto -> 2576
    //   2616: iconst_0
    //   2617: istore_2
    //   2618: iload #6
    //   2620: istore #8
    //   2622: iload_2
    //   2623: iload_1
    //   2624: if_icmpge -> 2742
    //   2627: aload_0
    //   2628: iload_2
    //   2629: invokevirtual getChildAt : (I)Landroid/view/View;
    //   2632: astore #11
    //   2634: aload_0
    //   2635: aload #11
    //   2637: invokevirtual e : (Landroid/view/View;)Lb/g/b/i/d;
    //   2640: astore #13
    //   2642: aload #13
    //   2644: ifnonnull -> 2650
    //   2647: goto -> 2732
    //   2650: aload #11
    //   2652: invokevirtual getLayoutParams : ()Landroid/view/ViewGroup$LayoutParams;
    //   2655: checkcast androidx/constraintlayout/widget/ConstraintLayout$a
    //   2658: astore #14
    //   2660: aload_0
    //   2661: getfield d : Lb/g/b/i/e;
    //   2664: astore #12
    //   2666: aload #12
    //   2668: getfield f0 : Ljava/util/ArrayList;
    //   2671: aload #13
    //   2673: invokevirtual add : (Ljava/lang/Object;)Z
    //   2676: pop
    //   2677: aload #13
    //   2679: getfield K : Lb/g/b/i/d;
    //   2682: astore #10
    //   2684: aload #10
    //   2686: ifnull -> 2709
    //   2689: aload #10
    //   2691: checkcast b/g/b/i/k
    //   2694: getfield f0 : Ljava/util/ArrayList;
    //   2697: aload #13
    //   2699: invokevirtual remove : (Ljava/lang/Object;)Z
    //   2702: pop
    //   2703: aload #13
    //   2705: aconst_null
    //   2706: putfield K : Lb/g/b/i/d;
    //   2709: aload #13
    //   2711: aload #12
    //   2713: putfield K : Lb/g/b/i/d;
    //   2716: aload_0
    //   2717: iload #7
    //   2719: aload #11
    //   2721: aload #13
    //   2723: aload #14
    //   2725: aload_0
    //   2726: getfield q : Landroid/util/SparseArray;
    //   2729: invokevirtual a : (ZLandroid/view/View;Lb/g/b/i/d;Landroidx/constraintlayout/widget/ConstraintLayout$a;Landroid/util/SparseArray;)V
    //   2732: iinc #2, 1
    //   2735: goto -> 2618
    //   2738: iload #7
    //   2740: istore #8
    //   2742: iload #8
    //   2744: ireturn
    //   2745: astore #10
    //   2747: goto -> 296
    // Exception table:
    //   from	to	target	type
    //   110	147	2745	android/content/res/Resources$NotFoundException
    //   156	166	2745	android/content/res/Resources$NotFoundException
    //   166	172	2745	android/content/res/Resources$NotFoundException
    //   179	192	2745	android/content/res/Resources$NotFoundException
    //   201	208	2745	android/content/res/Resources$NotFoundException
    //   231	246	2745	android/content/res/Resources$NotFoundException
    //   256	262	2745	android/content/res/Resources$NotFoundException
    //   276	289	2745	android/content/res/Resources$NotFoundException
    //   289	296	2745	android/content/res/Resources$NotFoundException
    //   444	462	465	java/lang/Exception
    //   832	842	1344	java/lang/NoSuchMethodException
    //   832	842	1276	java/lang/IllegalAccessException
    //   832	842	1208	java/lang/reflect/InvocationTargetException
    //   891	929	1203	java/lang/NoSuchMethodException
    //   891	929	1198	java/lang/IllegalAccessException
    //   891	929	1193	java/lang/reflect/InvocationTargetException
    //   932	970	1203	java/lang/NoSuchMethodException
    //   932	970	1198	java/lang/IllegalAccessException
    //   932	970	1193	java/lang/reflect/InvocationTargetException
    //   973	1008	1203	java/lang/NoSuchMethodException
    //   973	1008	1198	java/lang/IllegalAccessException
    //   973	1008	1193	java/lang/reflect/InvocationTargetException
    //   1011	1067	1203	java/lang/NoSuchMethodException
    //   1011	1067	1198	java/lang/IllegalAccessException
    //   1011	1067	1193	java/lang/reflect/InvocationTargetException
    //   1070	1108	1203	java/lang/NoSuchMethodException
    //   1070	1108	1198	java/lang/IllegalAccessException
    //   1070	1108	1193	java/lang/reflect/InvocationTargetException
    //   1111	1149	1203	java/lang/NoSuchMethodException
    //   1111	1149	1198	java/lang/IllegalAccessException
    //   1111	1149	1193	java/lang/reflect/InvocationTargetException
    //   1152	1190	1203	java/lang/NoSuchMethodException
    //   1152	1190	1198	java/lang/IllegalAccessException
    //   1152	1190	1193	java/lang/reflect/InvocationTargetException
  }
  
  public void onLayout(boolean paramBoolean, int paramInt1, int paramInt2, int paramInt3, int paramInt4) {
    paramInt3 = getChildCount();
    paramBoolean = isInEditMode();
    paramInt2 = 0;
    for (paramInt1 = 0; paramInt1 < paramInt3; paramInt1++) {
      View view = getChildAt(paramInt1);
      a a = (a)view.getLayoutParams();
      d d1 = a.m0;
      if ((view.getVisibility() != 8 || a.Y || a.Z || a.b0 || paramBoolean) && !a.a0) {
        int j = d1.p();
        int i = d1.q();
        paramInt4 = d1.o() + j;
        int k = d1.i() + i;
        view.layout(j, i, paramInt4, k);
        if (view instanceof i) {
          view = ((i)view).getContent();
          if (view != null) {
            view.setVisibility(0);
            view.layout(j, i, paramInt4, k);
          } 
        } 
      } 
    } 
    paramInt3 = this.c.size();
    if (paramInt3 > 0)
      for (paramInt1 = paramInt2; paramInt1 < paramInt3; paramInt1++)
        ((c)this.c.get(paramInt1)).f();  
  }
  
  public void onMeasure(int paramInt1, int paramInt2) {
    // Byte code:
    //   0: getstatic b/g/b/i/d$a.e : Lb/g/b/i/d$a;
    //   3: astore #32
    //   5: getstatic b/g/b/i/d$a.d : Lb/g/b/i/d$a;
    //   8: astore #30
    //   10: aload_0
    //   11: getfield d : Lb/g/b/i/e;
    //   14: aload_0
    //   15: invokevirtual f : ()Z
    //   18: putfield j0 : Z
    //   21: aload_0
    //   22: getfield i : Z
    //   25: ifeq -> 155
    //   28: aload_0
    //   29: iconst_0
    //   30: putfield i : Z
    //   33: aload_0
    //   34: invokevirtual h : ()Z
    //   37: ifeq -> 155
    //   40: aload_0
    //   41: getfield d : Lb/g/b/i/e;
    //   44: astore #24
    //   46: aload #24
    //   48: getfield g0 : Lb/g/b/i/l/b;
    //   51: astore #22
    //   53: aload #22
    //   55: getfield a : Ljava/util/ArrayList;
    //   58: invokevirtual clear : ()V
    //   61: aload #24
    //   63: getfield f0 : Ljava/util/ArrayList;
    //   66: invokevirtual size : ()I
    //   69: istore #4
    //   71: iconst_0
    //   72: istore_3
    //   73: iload_3
    //   74: iload #4
    //   76: if_icmpge -> 150
    //   79: aload #24
    //   81: getfield f0 : Ljava/util/ArrayList;
    //   84: iload_3
    //   85: invokevirtual get : (I)Ljava/lang/Object;
    //   88: checkcast b/g/b/i/d
    //   91: astore #23
    //   93: aload #23
    //   95: invokevirtual j : ()Lb/g/b/i/d$a;
    //   98: aload #30
    //   100: if_acmpeq -> 133
    //   103: aload #23
    //   105: invokevirtual j : ()Lb/g/b/i/d$a;
    //   108: aload #32
    //   110: if_acmpeq -> 133
    //   113: aload #23
    //   115: invokevirtual n : ()Lb/g/b/i/d$a;
    //   118: aload #30
    //   120: if_acmpeq -> 133
    //   123: aload #23
    //   125: invokevirtual n : ()Lb/g/b/i/d$a;
    //   128: aload #32
    //   130: if_acmpne -> 144
    //   133: aload #22
    //   135: getfield a : Ljava/util/ArrayList;
    //   138: aload #23
    //   140: invokevirtual add : (Ljava/lang/Object;)Z
    //   143: pop
    //   144: iinc #3, 1
    //   147: goto -> 73
    //   150: aload #24
    //   152: invokevirtual I : ()V
    //   155: aload_0
    //   156: getfield d : Lb/g/b/i/e;
    //   159: astore #26
    //   161: aload_0
    //   162: getfield j : I
    //   165: istore #6
    //   167: getstatic b/g/b/i/d$a.b : Lb/g/b/i/d$a;
    //   170: astore #23
    //   172: getstatic b/g/b/i/d$a.c : Lb/g/b/i/d$a;
    //   175: astore #22
    //   177: iload_1
    //   178: invokestatic getMode : (I)I
    //   181: istore #10
    //   183: iload_1
    //   184: invokestatic getSize : (I)I
    //   187: istore #12
    //   189: iload_2
    //   190: invokestatic getMode : (I)I
    //   193: istore #11
    //   195: iload_2
    //   196: invokestatic getSize : (I)I
    //   199: istore #5
    //   201: iconst_0
    //   202: aload_0
    //   203: invokevirtual getPaddingTop : ()I
    //   206: invokestatic max : (II)I
    //   209: istore #8
    //   211: iconst_0
    //   212: aload_0
    //   213: invokevirtual getPaddingBottom : ()I
    //   216: invokestatic max : (II)I
    //   219: istore_3
    //   220: iload #8
    //   222: iload_3
    //   223: iadd
    //   224: istore #9
    //   226: aload_0
    //   227: invokespecial getPaddingWidth : ()I
    //   230: istore #7
    //   232: aload_0
    //   233: getfield r : Landroidx/constraintlayout/widget/ConstraintLayout$b;
    //   236: astore #24
    //   238: aload #24
    //   240: iload #8
    //   242: putfield b : I
    //   245: aload #24
    //   247: iload_3
    //   248: putfield c : I
    //   251: aload #24
    //   253: iload #7
    //   255: putfield d : I
    //   258: aload #24
    //   260: iload #9
    //   262: putfield e : I
    //   265: aload #24
    //   267: iload_1
    //   268: putfield f : I
    //   271: aload #24
    //   273: iload_2
    //   274: putfield g : I
    //   277: iconst_0
    //   278: aload_0
    //   279: invokevirtual getPaddingStart : ()I
    //   282: invokestatic max : (II)I
    //   285: istore_3
    //   286: iconst_0
    //   287: aload_0
    //   288: invokevirtual getPaddingEnd : ()I
    //   291: invokestatic max : (II)I
    //   294: istore #4
    //   296: iload_3
    //   297: ifgt -> 320
    //   300: iload #4
    //   302: ifle -> 308
    //   305: goto -> 320
    //   308: iconst_0
    //   309: aload_0
    //   310: invokevirtual getPaddingLeft : ()I
    //   313: invokestatic max : (II)I
    //   316: istore_3
    //   317: goto -> 330
    //   320: aload_0
    //   321: invokevirtual f : ()Z
    //   324: ifeq -> 330
    //   327: iload #4
    //   329: istore_3
    //   330: iload #12
    //   332: iload #7
    //   334: isub
    //   335: istore #7
    //   337: iload #5
    //   339: iload #9
    //   341: isub
    //   342: istore #9
    //   344: aload_0
    //   345: getfield r : Landroidx/constraintlayout/widget/ConstraintLayout$b;
    //   348: astore #24
    //   350: aload #24
    //   352: getfield e : I
    //   355: istore #13
    //   357: aload #24
    //   359: getfield d : I
    //   362: istore #12
    //   364: aload_0
    //   365: invokevirtual getChildCount : ()I
    //   368: istore #14
    //   370: iload #10
    //   372: ldc_w -2147483648
    //   375: if_icmpeq -> 441
    //   378: iload #10
    //   380: ifeq -> 419
    //   383: iload #10
    //   385: ldc_w 1073741824
    //   388: if_icmpeq -> 398
    //   391: aload #23
    //   393: astore #24
    //   395: goto -> 431
    //   398: aload_0
    //   399: getfield g : I
    //   402: iload #12
    //   404: isub
    //   405: iload #7
    //   407: invokestatic min : (II)I
    //   410: istore #4
    //   412: aload #23
    //   414: astore #24
    //   416: goto -> 467
    //   419: iload #14
    //   421: ifne -> 427
    //   424: goto -> 446
    //   427: aload #22
    //   429: astore #24
    //   431: iconst_0
    //   432: istore #5
    //   434: aload #24
    //   436: astore #27
    //   438: goto -> 475
    //   441: iload #14
    //   443: ifne -> 459
    //   446: iconst_0
    //   447: aload_0
    //   448: getfield e : I
    //   451: invokestatic max : (II)I
    //   454: istore #4
    //   456: goto -> 463
    //   459: iload #7
    //   461: istore #4
    //   463: aload #22
    //   465: astore #24
    //   467: iload #4
    //   469: istore #5
    //   471: aload #24
    //   473: astore #27
    //   475: aload #22
    //   477: astore #24
    //   479: iload #11
    //   481: ldc_w -2147483648
    //   484: if_icmpeq -> 546
    //   487: iload #11
    //   489: ifeq -> 528
    //   492: iload #11
    //   494: ldc_w 1073741824
    //   497: if_icmpeq -> 507
    //   500: aload #23
    //   502: astore #25
    //   504: goto -> 540
    //   507: aload_0
    //   508: getfield h : I
    //   511: iload #13
    //   513: isub
    //   514: iload #9
    //   516: invokestatic min : (II)I
    //   519: istore #4
    //   521: aload #23
    //   523: astore #25
    //   525: goto -> 575
    //   528: iload #14
    //   530: ifne -> 536
    //   533: goto -> 551
    //   536: aload #24
    //   538: astore #25
    //   540: iconst_0
    //   541: istore #4
    //   543: goto -> 575
    //   546: iload #14
    //   548: ifne -> 568
    //   551: iconst_0
    //   552: aload_0
    //   553: getfield f : I
    //   556: invokestatic max : (II)I
    //   559: istore #4
    //   561: aload #24
    //   563: astore #25
    //   565: goto -> 575
    //   568: iload #9
    //   570: istore #4
    //   572: goto -> 561
    //   575: iload #5
    //   577: aload #26
    //   579: invokevirtual o : ()I
    //   582: if_icmpne -> 595
    //   585: iload #4
    //   587: aload #26
    //   589: invokevirtual i : ()I
    //   592: if_icmpeq -> 604
    //   595: aload #26
    //   597: getfield h0 : Lb/g/b/i/l/e;
    //   600: iconst_1
    //   601: putfield c : Z
    //   604: aload #26
    //   606: iconst_0
    //   607: putfield P : I
    //   610: aload #26
    //   612: iconst_0
    //   613: putfield Q : I
    //   616: aload_0
    //   617: getfield g : I
    //   620: istore #14
    //   622: aload #26
    //   624: getfield u : [I
    //   627: astore #28
    //   629: aload #28
    //   631: iconst_0
    //   632: iload #14
    //   634: iload #12
    //   636: isub
    //   637: iastore
    //   638: aload #28
    //   640: iconst_1
    //   641: aload_0
    //   642: getfield h : I
    //   645: iload #13
    //   647: isub
    //   648: iastore
    //   649: aload #26
    //   651: iconst_0
    //   652: invokevirtual z : (I)V
    //   655: aload #26
    //   657: iconst_0
    //   658: invokevirtual y : (I)V
    //   661: aload #26
    //   663: getfield J : [Lb/g/b/i/d$a;
    //   666: iconst_0
    //   667: aload #27
    //   669: aastore
    //   670: aload #26
    //   672: iload #5
    //   674: invokevirtual B : (I)V
    //   677: aload #26
    //   679: getfield J : [Lb/g/b/i/d$a;
    //   682: iconst_1
    //   683: aload #25
    //   685: aastore
    //   686: aload #26
    //   688: iload #4
    //   690: invokevirtual w : (I)V
    //   693: aload #26
    //   695: aload_0
    //   696: getfield e : I
    //   699: iload #12
    //   701: isub
    //   702: invokevirtual z : (I)V
    //   705: aload #26
    //   707: aload_0
    //   708: getfield f : I
    //   711: iload #13
    //   713: isub
    //   714: invokevirtual y : (I)V
    //   717: aload #26
    //   719: iload_3
    //   720: putfield l0 : I
    //   723: aload #26
    //   725: iload #8
    //   727: putfield m0 : I
    //   730: aload #26
    //   732: getfield g0 : Lb/g/b/i/l/b;
    //   735: astore #31
    //   737: aload #31
    //   739: ifnull -> 3694
    //   742: getstatic b/g/b/i/c$a.f : Lb/g/b/i/c$a;
    //   745: astore #27
    //   747: getstatic b/g/b/i/c$a.e : Lb/g/b/i/c$a;
    //   750: astore #28
    //   752: aload #26
    //   754: getfield i0 : Lb/g/b/i/l/b$b;
    //   757: astore #29
    //   759: aload #26
    //   761: getfield f0 : Ljava/util/ArrayList;
    //   764: invokevirtual size : ()I
    //   767: istore #12
    //   769: aload #26
    //   771: invokevirtual o : ()I
    //   774: istore #8
    //   776: aload #26
    //   778: invokevirtual i : ()I
    //   781: istore #15
    //   783: iload #6
    //   785: sipush #128
    //   788: invokestatic a : (II)Z
    //   791: istore #20
    //   793: iload #20
    //   795: ifne -> 816
    //   798: iload #6
    //   800: bipush #64
    //   802: invokestatic a : (II)Z
    //   805: ifeq -> 811
    //   808: goto -> 816
    //   811: iconst_0
    //   812: istore_3
    //   813: goto -> 818
    //   816: iconst_1
    //   817: istore_3
    //   818: iload_3
    //   819: istore #4
    //   821: iload_3
    //   822: ifeq -> 993
    //   825: iconst_0
    //   826: istore #5
    //   828: iload_3
    //   829: istore #4
    //   831: iload #5
    //   833: iload #12
    //   835: if_icmpge -> 993
    //   838: aload #26
    //   840: getfield f0 : Ljava/util/ArrayList;
    //   843: iload #5
    //   845: invokevirtual get : (I)Ljava/lang/Object;
    //   848: checkcast b/g/b/i/d
    //   851: astore #25
    //   853: aload #25
    //   855: invokevirtual j : ()Lb/g/b/i/d$a;
    //   858: aload #30
    //   860: if_acmpne -> 869
    //   863: iconst_1
    //   864: istore #4
    //   866: goto -> 872
    //   869: iconst_0
    //   870: istore #4
    //   872: aload #25
    //   874: invokevirtual n : ()Lb/g/b/i/d$a;
    //   877: aload #30
    //   879: if_acmpne -> 888
    //   882: iconst_1
    //   883: istore #6
    //   885: goto -> 891
    //   888: iconst_0
    //   889: istore #6
    //   891: iload #4
    //   893: ifeq -> 917
    //   896: iload #6
    //   898: ifeq -> 917
    //   901: aload #25
    //   903: getfield N : F
    //   906: fconst_0
    //   907: fcmpl
    //   908: ifle -> 917
    //   911: iconst_1
    //   912: istore #4
    //   914: goto -> 920
    //   917: iconst_0
    //   918: istore #4
    //   920: aload #25
    //   922: invokevirtual s : ()Z
    //   925: ifeq -> 936
    //   928: iload #4
    //   930: ifeq -> 936
    //   933: goto -> 988
    //   936: aload #25
    //   938: invokevirtual t : ()Z
    //   941: ifeq -> 952
    //   944: iload #4
    //   946: ifeq -> 952
    //   949: goto -> 988
    //   952: aload #25
    //   954: instanceof b/g/b/i/j
    //   957: ifeq -> 963
    //   960: goto -> 988
    //   963: aload #25
    //   965: invokevirtual s : ()Z
    //   968: ifne -> 988
    //   971: aload #25
    //   973: invokevirtual t : ()Z
    //   976: ifeq -> 982
    //   979: goto -> 988
    //   982: iinc #5, 1
    //   985: goto -> 828
    //   988: iconst_0
    //   989: istore_3
    //   990: goto -> 996
    //   993: iload #4
    //   995: istore_3
    //   996: iload #10
    //   998: ldc_w 1073741824
    //   1001: if_icmpne -> 1012
    //   1004: iload #11
    //   1006: ldc_w 1073741824
    //   1009: if_icmpeq -> 1017
    //   1012: iload #20
    //   1014: ifeq -> 1023
    //   1017: iconst_1
    //   1018: istore #4
    //   1020: goto -> 1026
    //   1023: iconst_0
    //   1024: istore #4
    //   1026: iload_3
    //   1027: iload #4
    //   1029: iand
    //   1030: ifeq -> 2348
    //   1033: aload #26
    //   1035: getfield u : [I
    //   1038: iconst_0
    //   1039: iaload
    //   1040: iload #7
    //   1042: invokestatic min : (II)I
    //   1045: istore_3
    //   1046: aload #26
    //   1048: getfield u : [I
    //   1051: iconst_1
    //   1052: iaload
    //   1053: iload #9
    //   1055: invokestatic min : (II)I
    //   1058: istore #4
    //   1060: iload #10
    //   1062: ldc_w 1073741824
    //   1065: if_icmpne -> 1088
    //   1068: aload #26
    //   1070: invokevirtual o : ()I
    //   1073: iload_3
    //   1074: if_icmpeq -> 1088
    //   1077: aload #26
    //   1079: iload_3
    //   1080: invokevirtual B : (I)V
    //   1083: aload #26
    //   1085: invokevirtual I : ()V
    //   1088: iload #11
    //   1090: ldc_w 1073741824
    //   1093: if_icmpne -> 1118
    //   1096: aload #26
    //   1098: invokevirtual i : ()I
    //   1101: iload #4
    //   1103: if_icmpeq -> 1118
    //   1106: aload #26
    //   1108: iload #4
    //   1110: invokevirtual w : (I)V
    //   1113: aload #26
    //   1115: invokevirtual I : ()V
    //   1118: iload #10
    //   1120: ldc_w 1073741824
    //   1123: if_icmpne -> 1974
    //   1126: iload #11
    //   1128: ldc_w 1073741824
    //   1131: if_icmpne -> 1974
    //   1134: aload #26
    //   1136: getfield h0 : Lb/g/b/i/l/e;
    //   1139: astore #33
    //   1141: iload #20
    //   1143: iconst_1
    //   1144: iand
    //   1145: istore #5
    //   1147: aload #33
    //   1149: getfield b : Z
    //   1152: ifne -> 1169
    //   1155: aload #33
    //   1157: getfield c : Z
    //   1160: ifeq -> 1166
    //   1163: goto -> 1169
    //   1166: goto -> 1267
    //   1169: aload #33
    //   1171: getfield a : Lb/g/b/i/e;
    //   1174: getfield f0 : Ljava/util/ArrayList;
    //   1177: invokevirtual iterator : ()Ljava/util/Iterator;
    //   1180: astore #25
    //   1182: aload #25
    //   1184: invokeinterface hasNext : ()Z
    //   1189: ifeq -> 1229
    //   1192: aload #25
    //   1194: invokeinterface next : ()Ljava/lang/Object;
    //   1199: checkcast b/g/b/i/d
    //   1202: astore #34
    //   1204: aload #34
    //   1206: iconst_0
    //   1207: putfield a : Z
    //   1210: aload #34
    //   1212: getfield d : Lb/g/b/i/l/j;
    //   1215: invokevirtual n : ()V
    //   1218: aload #34
    //   1220: getfield e : Lb/g/b/i/l/l;
    //   1223: invokevirtual m : ()V
    //   1226: goto -> 1182
    //   1229: aload #33
    //   1231: getfield a : Lb/g/b/i/e;
    //   1234: astore #25
    //   1236: aload #25
    //   1238: iconst_0
    //   1239: putfield a : Z
    //   1242: aload #25
    //   1244: getfield d : Lb/g/b/i/l/j;
    //   1247: invokevirtual n : ()V
    //   1250: aload #33
    //   1252: getfield a : Lb/g/b/i/e;
    //   1255: getfield e : Lb/g/b/i/l/l;
    //   1258: invokevirtual m : ()V
    //   1261: aload #33
    //   1263: iconst_0
    //   1264: putfield c : Z
    //   1267: aload #33
    //   1269: aload #33
    //   1271: getfield d : Lb/g/b/i/e;
    //   1274: invokevirtual b : (Lb/g/b/i/e;)Z
    //   1277: pop
    //   1278: aload #33
    //   1280: getfield a : Lb/g/b/i/e;
    //   1283: astore #25
    //   1285: aload #25
    //   1287: iconst_0
    //   1288: putfield P : I
    //   1291: aload #25
    //   1293: iconst_0
    //   1294: putfield Q : I
    //   1297: aload #25
    //   1299: iconst_0
    //   1300: invokevirtual h : (I)Lb/g/b/i/d$a;
    //   1303: astore #25
    //   1305: aload #33
    //   1307: getfield a : Lb/g/b/i/e;
    //   1310: iconst_1
    //   1311: invokevirtual h : (I)Lb/g/b/i/d$a;
    //   1314: astore #34
    //   1316: aload #33
    //   1318: getfield b : Z
    //   1321: ifeq -> 1329
    //   1324: aload #33
    //   1326: invokevirtual c : ()V
    //   1329: aload #33
    //   1331: getfield a : Lb/g/b/i/e;
    //   1334: invokevirtual p : ()I
    //   1337: istore #7
    //   1339: aload #33
    //   1341: getfield a : Lb/g/b/i/e;
    //   1344: invokevirtual q : ()I
    //   1347: istore #6
    //   1349: aload #33
    //   1351: getfield a : Lb/g/b/i/e;
    //   1354: getfield d : Lb/g/b/i/l/j;
    //   1357: getfield h : Lb/g/b/i/l/f;
    //   1360: iload #7
    //   1362: invokevirtual c : (I)V
    //   1365: aload #33
    //   1367: getfield a : Lb/g/b/i/e;
    //   1370: getfield e : Lb/g/b/i/l/l;
    //   1373: getfield h : Lb/g/b/i/l/f;
    //   1376: iload #6
    //   1378: invokevirtual c : (I)V
    //   1381: aload #33
    //   1383: invokevirtual g : ()V
    //   1386: aload #25
    //   1388: aload #24
    //   1390: if_acmpeq -> 1406
    //   1393: aload #34
    //   1395: aload #24
    //   1397: if_acmpne -> 1403
    //   1400: goto -> 1406
    //   1403: goto -> 1590
    //   1406: iload #5
    //   1408: istore_3
    //   1409: iload_3
    //   1410: istore #4
    //   1412: iload #5
    //   1414: ifeq -> 1459
    //   1417: aload #33
    //   1419: getfield e : Ljava/util/ArrayList;
    //   1422: invokevirtual iterator : ()Ljava/util/Iterator;
    //   1425: astore #35
    //   1427: iload_3
    //   1428: istore #4
    //   1430: aload #35
    //   1432: invokeinterface hasNext : ()Z
    //   1437: ifeq -> 1459
    //   1440: aload #35
    //   1442: invokeinterface next : ()Ljava/lang/Object;
    //   1447: checkcast b/g/b/i/l/m
    //   1450: invokevirtual k : ()Z
    //   1453: ifne -> 1427
    //   1456: iconst_0
    //   1457: istore #4
    //   1459: iload #4
    //   1461: ifeq -> 1526
    //   1464: aload #25
    //   1466: aload #24
    //   1468: if_acmpne -> 1526
    //   1471: aload #33
    //   1473: getfield a : Lb/g/b/i/e;
    //   1476: astore #35
    //   1478: aload #35
    //   1480: getfield J : [Lb/g/b/i/d$a;
    //   1483: iconst_0
    //   1484: aload #23
    //   1486: aastore
    //   1487: aload #35
    //   1489: aload #33
    //   1491: aload #35
    //   1493: iconst_0
    //   1494: invokevirtual d : (Lb/g/b/i/e;I)I
    //   1497: invokevirtual B : (I)V
    //   1500: aload #33
    //   1502: getfield a : Lb/g/b/i/e;
    //   1505: astore #35
    //   1507: aload #35
    //   1509: getfield d : Lb/g/b/i/l/j;
    //   1512: getfield e : Lb/g/b/i/l/g;
    //   1515: aload #35
    //   1517: invokevirtual o : ()I
    //   1520: invokevirtual c : (I)V
    //   1523: goto -> 1526
    //   1526: iload #4
    //   1528: ifeq -> 1590
    //   1531: aload #34
    //   1533: aload #24
    //   1535: if_acmpne -> 1590
    //   1538: aload #33
    //   1540: getfield a : Lb/g/b/i/e;
    //   1543: astore #35
    //   1545: aload #35
    //   1547: getfield J : [Lb/g/b/i/d$a;
    //   1550: iconst_1
    //   1551: aload #23
    //   1553: aastore
    //   1554: aload #35
    //   1556: aload #33
    //   1558: aload #35
    //   1560: iconst_1
    //   1561: invokevirtual d : (Lb/g/b/i/e;I)I
    //   1564: invokevirtual w : (I)V
    //   1567: aload #33
    //   1569: getfield a : Lb/g/b/i/e;
    //   1572: astore #35
    //   1574: aload #35
    //   1576: getfield e : Lb/g/b/i/l/l;
    //   1579: getfield e : Lb/g/b/i/l/g;
    //   1582: aload #35
    //   1584: invokevirtual i : ()I
    //   1587: invokevirtual c : (I)V
    //   1590: aload #33
    //   1592: getfield a : Lb/g/b/i/e;
    //   1595: getfield J : [Lb/g/b/i/d$a;
    //   1598: astore #35
    //   1600: aload #35
    //   1602: iconst_0
    //   1603: aaload
    //   1604: astore #36
    //   1606: aload #36
    //   1608: aload #23
    //   1610: if_acmpeq -> 1630
    //   1613: aload #35
    //   1615: iconst_0
    //   1616: aaload
    //   1617: aload #32
    //   1619: if_acmpne -> 1625
    //   1622: goto -> 1630
    //   1625: iconst_0
    //   1626: istore_3
    //   1627: goto -> 1760
    //   1630: aload #33
    //   1632: getfield a : Lb/g/b/i/e;
    //   1635: invokevirtual o : ()I
    //   1638: iload #7
    //   1640: iadd
    //   1641: istore_3
    //   1642: aload #33
    //   1644: getfield a : Lb/g/b/i/e;
    //   1647: getfield d : Lb/g/b/i/l/j;
    //   1650: getfield i : Lb/g/b/i/l/f;
    //   1653: iload_3
    //   1654: invokevirtual c : (I)V
    //   1657: aload #33
    //   1659: getfield a : Lb/g/b/i/e;
    //   1662: getfield d : Lb/g/b/i/l/j;
    //   1665: getfield e : Lb/g/b/i/l/g;
    //   1668: iload_3
    //   1669: iload #7
    //   1671: isub
    //   1672: invokevirtual c : (I)V
    //   1675: aload #33
    //   1677: invokevirtual g : ()V
    //   1680: aload #33
    //   1682: getfield a : Lb/g/b/i/e;
    //   1685: getfield J : [Lb/g/b/i/d$a;
    //   1688: astore #24
    //   1690: aload #24
    //   1692: iconst_1
    //   1693: aaload
    //   1694: aload #23
    //   1696: if_acmpeq -> 1708
    //   1699: aload #24
    //   1701: iconst_1
    //   1702: aaload
    //   1703: aload #32
    //   1705: if_acmpne -> 1753
    //   1708: aload #33
    //   1710: getfield a : Lb/g/b/i/e;
    //   1713: invokevirtual i : ()I
    //   1716: iload #6
    //   1718: iadd
    //   1719: istore_3
    //   1720: aload #33
    //   1722: getfield a : Lb/g/b/i/e;
    //   1725: getfield e : Lb/g/b/i/l/l;
    //   1728: getfield i : Lb/g/b/i/l/f;
    //   1731: iload_3
    //   1732: invokevirtual c : (I)V
    //   1735: aload #33
    //   1737: getfield a : Lb/g/b/i/e;
    //   1740: getfield e : Lb/g/b/i/l/l;
    //   1743: getfield e : Lb/g/b/i/l/g;
    //   1746: iload_3
    //   1747: iload #6
    //   1749: isub
    //   1750: invokevirtual c : (I)V
    //   1753: aload #33
    //   1755: invokevirtual g : ()V
    //   1758: iconst_1
    //   1759: istore_3
    //   1760: aload #33
    //   1762: getfield e : Ljava/util/ArrayList;
    //   1765: invokevirtual iterator : ()Ljava/util/Iterator;
    //   1768: astore #23
    //   1770: aload #23
    //   1772: invokeinterface hasNext : ()Z
    //   1777: ifeq -> 1824
    //   1780: aload #23
    //   1782: invokeinterface next : ()Ljava/lang/Object;
    //   1787: checkcast b/g/b/i/l/m
    //   1790: astore #24
    //   1792: aload #24
    //   1794: getfield b : Lb/g/b/i/d;
    //   1797: aload #33
    //   1799: getfield a : Lb/g/b/i/e;
    //   1802: if_acmpne -> 1816
    //   1805: aload #24
    //   1807: getfield g : Z
    //   1810: ifne -> 1816
    //   1813: goto -> 1770
    //   1816: aload #24
    //   1818: invokevirtual e : ()V
    //   1821: goto -> 1770
    //   1824: aload #33
    //   1826: getfield e : Ljava/util/ArrayList;
    //   1829: invokevirtual iterator : ()Ljava/util/Iterator;
    //   1832: astore #24
    //   1834: aload #24
    //   1836: invokeinterface hasNext : ()Z
    //   1841: ifeq -> 1944
    //   1844: aload #24
    //   1846: invokeinterface next : ()Ljava/lang/Object;
    //   1851: checkcast b/g/b/i/l/m
    //   1854: astore #23
    //   1856: iload_3
    //   1857: ifne -> 1876
    //   1860: aload #23
    //   1862: getfield b : Lb/g/b/i/d;
    //   1865: aload #33
    //   1867: getfield a : Lb/g/b/i/e;
    //   1870: if_acmpne -> 1876
    //   1873: goto -> 1834
    //   1876: aload #23
    //   1878: getfield h : Lb/g/b/i/l/f;
    //   1881: getfield j : Z
    //   1884: ifne -> 1890
    //   1887: goto -> 1939
    //   1890: aload #23
    //   1892: getfield i : Lb/g/b/i/l/f;
    //   1895: getfield j : Z
    //   1898: ifne -> 1912
    //   1901: aload #23
    //   1903: instanceof b/g/b/i/l/h
    //   1906: ifne -> 1912
    //   1909: goto -> 1939
    //   1912: aload #23
    //   1914: getfield e : Lb/g/b/i/l/g;
    //   1917: getfield j : Z
    //   1920: ifne -> 1834
    //   1923: aload #23
    //   1925: instanceof b/g/b/i/l/c
    //   1928: ifne -> 1834
    //   1931: aload #23
    //   1933: instanceof b/g/b/i/l/h
    //   1936: ifne -> 1834
    //   1939: iconst_0
    //   1940: istore_3
    //   1941: goto -> 1946
    //   1944: iconst_1
    //   1945: istore_3
    //   1946: aload #33
    //   1948: getfield a : Lb/g/b/i/e;
    //   1951: aload #25
    //   1953: invokevirtual x : (Lb/g/b/i/d$a;)V
    //   1956: aload #33
    //   1958: getfield a : Lb/g/b/i/e;
    //   1961: aload #34
    //   1963: invokevirtual A : (Lb/g/b/i/d$a;)V
    //   1966: iload_3
    //   1967: istore #4
    //   1969: iconst_2
    //   1970: istore_3
    //   1971: goto -> 2279
    //   1974: aload #26
    //   1976: getfield h0 : Lb/g/b/i/l/e;
    //   1979: astore #23
    //   1981: aload #23
    //   1983: getfield b : Z
    //   1986: ifeq -> 2165
    //   1989: aload #23
    //   1991: getfield a : Lb/g/b/i/e;
    //   1994: getfield f0 : Ljava/util/ArrayList;
    //   1997: invokevirtual iterator : ()Ljava/util/Iterator;
    //   2000: astore #24
    //   2002: aload #24
    //   2004: invokeinterface hasNext : ()Z
    //   2009: ifeq -> 2087
    //   2012: aload #24
    //   2014: invokeinterface next : ()Ljava/lang/Object;
    //   2019: checkcast b/g/b/i/d
    //   2022: astore #25
    //   2024: aload #25
    //   2026: iconst_0
    //   2027: putfield a : Z
    //   2030: aload #25
    //   2032: getfield d : Lb/g/b/i/l/j;
    //   2035: astore #32
    //   2037: aload #32
    //   2039: getfield e : Lb/g/b/i/l/g;
    //   2042: iconst_0
    //   2043: putfield j : Z
    //   2046: aload #32
    //   2048: iconst_0
    //   2049: putfield g : Z
    //   2052: aload #32
    //   2054: invokevirtual n : ()V
    //   2057: aload #25
    //   2059: getfield e : Lb/g/b/i/l/l;
    //   2062: astore #25
    //   2064: aload #25
    //   2066: getfield e : Lb/g/b/i/l/g;
    //   2069: iconst_0
    //   2070: putfield j : Z
    //   2073: aload #25
    //   2075: iconst_0
    //   2076: putfield g : Z
    //   2079: aload #25
    //   2081: invokevirtual m : ()V
    //   2084: goto -> 2002
    //   2087: aload #23
    //   2089: getfield a : Lb/g/b/i/e;
    //   2092: astore #24
    //   2094: aload #24
    //   2096: iconst_0
    //   2097: putfield a : Z
    //   2100: aload #24
    //   2102: getfield d : Lb/g/b/i/l/j;
    //   2105: astore #24
    //   2107: aload #24
    //   2109: getfield e : Lb/g/b/i/l/g;
    //   2112: iconst_0
    //   2113: putfield j : Z
    //   2116: aload #24
    //   2118: iconst_0
    //   2119: putfield g : Z
    //   2122: aload #24
    //   2124: invokevirtual n : ()V
    //   2127: aload #23
    //   2129: getfield a : Lb/g/b/i/e;
    //   2132: getfield e : Lb/g/b/i/l/l;
    //   2135: astore #24
    //   2137: aload #24
    //   2139: getfield e : Lb/g/b/i/l/g;
    //   2142: iconst_0
    //   2143: putfield j : Z
    //   2146: aload #24
    //   2148: iconst_0
    //   2149: putfield g : Z
    //   2152: aload #24
    //   2154: invokevirtual m : ()V
    //   2157: aload #23
    //   2159: invokevirtual c : ()V
    //   2162: goto -> 2165
    //   2165: aload #23
    //   2167: aload #23
    //   2169: getfield d : Lb/g/b/i/e;
    //   2172: invokevirtual b : (Lb/g/b/i/e;)Z
    //   2175: pop
    //   2176: aload #23
    //   2178: getfield a : Lb/g/b/i/e;
    //   2181: astore #24
    //   2183: aload #24
    //   2185: iconst_0
    //   2186: putfield P : I
    //   2189: aload #24
    //   2191: iconst_0
    //   2192: putfield Q : I
    //   2195: aload #24
    //   2197: getfield d : Lb/g/b/i/l/j;
    //   2200: getfield h : Lb/g/b/i/l/f;
    //   2203: iconst_0
    //   2204: invokevirtual c : (I)V
    //   2207: aload #23
    //   2209: getfield a : Lb/g/b/i/e;
    //   2212: getfield e : Lb/g/b/i/l/l;
    //   2215: getfield h : Lb/g/b/i/l/f;
    //   2218: iconst_0
    //   2219: invokevirtual c : (I)V
    //   2222: iload #10
    //   2224: ldc_w 1073741824
    //   2227: if_icmpne -> 2247
    //   2230: aload #26
    //   2232: iload #20
    //   2234: iconst_0
    //   2235: invokevirtual H : (ZI)Z
    //   2238: iconst_1
    //   2239: iand
    //   2240: istore #4
    //   2242: iconst_1
    //   2243: istore_3
    //   2244: goto -> 2252
    //   2247: iconst_0
    //   2248: istore_3
    //   2249: iconst_1
    //   2250: istore #4
    //   2252: iload #11
    //   2254: ldc_w 1073741824
    //   2257: if_icmpne -> 2279
    //   2260: iload #4
    //   2262: aload #26
    //   2264: iload #20
    //   2266: iconst_1
    //   2267: invokevirtual H : (ZI)Z
    //   2270: iand
    //   2271: istore #4
    //   2273: iinc #3, 1
    //   2276: goto -> 2279
    //   2279: aload #22
    //   2281: astore #23
    //   2283: iload_3
    //   2284: istore #6
    //   2286: iload #4
    //   2288: istore #5
    //   2290: iload #4
    //   2292: ifeq -> 2354
    //   2295: iload #10
    //   2297: ldc_w 1073741824
    //   2300: if_icmpne -> 2309
    //   2303: iconst_1
    //   2304: istore #20
    //   2306: goto -> 2312
    //   2309: iconst_0
    //   2310: istore #20
    //   2312: iload #11
    //   2314: ldc_w 1073741824
    //   2317: if_icmpne -> 2326
    //   2320: iconst_1
    //   2321: istore #21
    //   2323: goto -> 2329
    //   2326: iconst_0
    //   2327: istore #21
    //   2329: aload #26
    //   2331: iload #20
    //   2333: iload #21
    //   2335: invokevirtual C : (ZZ)V
    //   2338: iload_3
    //   2339: istore #6
    //   2341: iload #4
    //   2343: istore #5
    //   2345: goto -> 2354
    //   2348: iconst_0
    //   2349: istore #6
    //   2351: iconst_0
    //   2352: istore #5
    //   2354: aload #22
    //   2356: astore #25
    //   2358: aload #29
    //   2360: astore #23
    //   2362: aload #28
    //   2364: astore #22
    //   2366: aload #27
    //   2368: astore #24
    //   2370: iload #5
    //   2372: ifeq -> 2381
    //   2375: iload #6
    //   2377: iconst_2
    //   2378: if_icmpeq -> 3551
    //   2381: iload #12
    //   2383: ifle -> 2657
    //   2386: aload #26
    //   2388: getfield f0 : Ljava/util/ArrayList;
    //   2391: invokevirtual size : ()I
    //   2394: istore #5
    //   2396: aload #26
    //   2398: getfield i0 : Lb/g/b/i/l/b$b;
    //   2401: astore #29
    //   2403: iconst_0
    //   2404: istore_3
    //   2405: iload_3
    //   2406: iload #5
    //   2408: if_icmpge -> 2549
    //   2411: aload #26
    //   2413: getfield f0 : Ljava/util/ArrayList;
    //   2416: iload_3
    //   2417: invokevirtual get : (I)Ljava/lang/Object;
    //   2420: checkcast b/g/b/i/d
    //   2423: astore #27
    //   2425: aload #27
    //   2427: instanceof b/g/b/i/f
    //   2430: ifeq -> 2436
    //   2433: goto -> 2543
    //   2436: aload #27
    //   2438: getfield d : Lb/g/b/i/l/j;
    //   2441: getfield e : Lb/g/b/i/l/g;
    //   2444: getfield j : Z
    //   2447: ifeq -> 2467
    //   2450: aload #27
    //   2452: getfield e : Lb/g/b/i/l/l;
    //   2455: getfield e : Lb/g/b/i/l/g;
    //   2458: getfield j : Z
    //   2461: ifeq -> 2467
    //   2464: goto -> 2543
    //   2467: aload #27
    //   2469: iconst_0
    //   2470: invokevirtual h : (I)Lb/g/b/i/d$a;
    //   2473: astore #32
    //   2475: aload #27
    //   2477: iconst_1
    //   2478: invokevirtual h : (I)Lb/g/b/i/d$a;
    //   2481: astore #28
    //   2483: aload #32
    //   2485: aload #30
    //   2487: if_acmpne -> 2521
    //   2490: aload #27
    //   2492: getfield j : I
    //   2495: iconst_1
    //   2496: if_icmpeq -> 2521
    //   2499: aload #28
    //   2501: aload #30
    //   2503: if_acmpne -> 2521
    //   2506: aload #27
    //   2508: getfield k : I
    //   2511: iconst_1
    //   2512: if_icmpeq -> 2521
    //   2515: iconst_1
    //   2516: istore #4
    //   2518: goto -> 2524
    //   2521: iconst_0
    //   2522: istore #4
    //   2524: iload #4
    //   2526: ifeq -> 2532
    //   2529: goto -> 2543
    //   2532: aload #31
    //   2534: aload #29
    //   2536: aload #27
    //   2538: iconst_0
    //   2539: invokevirtual a : (Lb/g/b/i/l/b$b;Lb/g/b/i/d;Z)Z
    //   2542: pop
    //   2543: iinc #3, 1
    //   2546: goto -> 2405
    //   2549: aload #29
    //   2551: checkcast androidx/constraintlayout/widget/ConstraintLayout$b
    //   2554: astore #28
    //   2556: aload #28
    //   2558: getfield a : Landroidx/constraintlayout/widget/ConstraintLayout;
    //   2561: invokevirtual getChildCount : ()I
    //   2564: istore #4
    //   2566: iconst_0
    //   2567: istore_3
    //   2568: iload_3
    //   2569: iload #4
    //   2571: if_icmpge -> 2607
    //   2574: aload #28
    //   2576: getfield a : Landroidx/constraintlayout/widget/ConstraintLayout;
    //   2579: iload_3
    //   2580: invokevirtual getChildAt : (I)Landroid/view/View;
    //   2583: astore #27
    //   2585: aload #27
    //   2587: instanceof b/g/c/i
    //   2590: ifeq -> 2601
    //   2593: aload #27
    //   2595: checkcast b/g/c/i
    //   2598: invokevirtual a : ()V
    //   2601: iinc #3, 1
    //   2604: goto -> 2568
    //   2607: aload #28
    //   2609: getfield a : Landroidx/constraintlayout/widget/ConstraintLayout;
    //   2612: getfield c : Ljava/util/ArrayList;
    //   2615: invokevirtual size : ()I
    //   2618: istore #4
    //   2620: iload #4
    //   2622: ifle -> 2657
    //   2625: iconst_0
    //   2626: istore_3
    //   2627: iload_3
    //   2628: iload #4
    //   2630: if_icmpge -> 2657
    //   2633: aload #28
    //   2635: getfield a : Landroidx/constraintlayout/widget/ConstraintLayout;
    //   2638: getfield c : Ljava/util/ArrayList;
    //   2641: iload_3
    //   2642: invokevirtual get : (I)Ljava/lang/Object;
    //   2645: checkcast b/g/c/c
    //   2648: invokevirtual g : ()V
    //   2651: iinc #3, 1
    //   2654: goto -> 2627
    //   2657: aload #26
    //   2659: getfield r0 : I
    //   2662: istore #5
    //   2664: aload #31
    //   2666: getfield a : Ljava/util/ArrayList;
    //   2669: invokevirtual size : ()I
    //   2672: istore #13
    //   2674: iload #12
    //   2676: ifle -> 2690
    //   2679: aload #31
    //   2681: aload #26
    //   2683: iload #8
    //   2685: iload #15
    //   2687: invokevirtual b : (Lb/g/b/i/e;II)V
    //   2690: iload #13
    //   2692: ifle -> 3538
    //   2695: aload #26
    //   2697: invokevirtual j : ()Lb/g/b/i/d$a;
    //   2700: aload #25
    //   2702: if_acmpne -> 2711
    //   2705: iconst_1
    //   2706: istore #9
    //   2708: goto -> 2714
    //   2711: iconst_0
    //   2712: istore #9
    //   2714: aload #26
    //   2716: invokevirtual n : ()Lb/g/b/i/d$a;
    //   2719: aload #25
    //   2721: if_acmpne -> 2730
    //   2724: iconst_1
    //   2725: istore #10
    //   2727: goto -> 2733
    //   2730: iconst_0
    //   2731: istore #10
    //   2733: aload #26
    //   2735: invokevirtual o : ()I
    //   2738: aload #31
    //   2740: getfield c : Lb/g/b/i/e;
    //   2743: getfield S : I
    //   2746: invokestatic max : (II)I
    //   2749: istore #4
    //   2751: aload #26
    //   2753: invokevirtual i : ()I
    //   2756: aload #31
    //   2758: getfield c : Lb/g/b/i/e;
    //   2761: getfield T : I
    //   2764: invokestatic max : (II)I
    //   2767: istore_3
    //   2768: iconst_0
    //   2769: istore #7
    //   2771: iconst_0
    //   2772: istore #6
    //   2774: aload #22
    //   2776: astore #25
    //   2778: iload #7
    //   2780: iload #13
    //   2782: if_icmpge -> 3004
    //   2785: aload #31
    //   2787: getfield a : Ljava/util/ArrayList;
    //   2790: iload #7
    //   2792: invokevirtual get : (I)Ljava/lang/Object;
    //   2795: checkcast b/g/b/i/d
    //   2798: astore #22
    //   2800: aload #22
    //   2802: instanceof b/g/b/i/j
    //   2805: ifne -> 2811
    //   2808: goto -> 2998
    //   2811: aload #22
    //   2813: invokevirtual o : ()I
    //   2816: istore #16
    //   2818: aload #22
    //   2820: invokevirtual i : ()I
    //   2823: istore #11
    //   2825: aload #31
    //   2827: aload #23
    //   2829: aload #22
    //   2831: iconst_1
    //   2832: invokevirtual a : (Lb/g/b/i/l/b$b;Lb/g/b/i/d;Z)Z
    //   2835: istore #20
    //   2837: aload #22
    //   2839: invokevirtual o : ()I
    //   2842: istore #14
    //   2844: iload #6
    //   2846: iload #20
    //   2848: ior
    //   2849: istore #6
    //   2851: aload #22
    //   2853: invokevirtual i : ()I
    //   2856: istore #12
    //   2858: iload #14
    //   2860: iload #16
    //   2862: if_icmpeq -> 2923
    //   2865: aload #22
    //   2867: iload #14
    //   2869: invokevirtual B : (I)V
    //   2872: iload #9
    //   2874: ifeq -> 2917
    //   2877: aload #22
    //   2879: invokevirtual m : ()I
    //   2882: iload #4
    //   2884: if_icmple -> 2917
    //   2887: aload #22
    //   2889: invokevirtual m : ()I
    //   2892: istore #6
    //   2894: iload #4
    //   2896: aload #22
    //   2898: aload #25
    //   2900: invokevirtual f : (Lb/g/b/i/c$a;)Lb/g/b/i/c;
    //   2903: invokevirtual b : ()I
    //   2906: iload #6
    //   2908: iadd
    //   2909: invokestatic max : (II)I
    //   2912: istore #4
    //   2914: goto -> 2917
    //   2917: iconst_1
    //   2918: istore #6
    //   2920: goto -> 2923
    //   2923: iload #12
    //   2925: iload #11
    //   2927: if_icmpeq -> 2985
    //   2930: aload #22
    //   2932: iload #12
    //   2934: invokevirtual w : (I)V
    //   2937: iload #10
    //   2939: ifeq -> 2979
    //   2942: aload #22
    //   2944: invokevirtual g : ()I
    //   2947: iload_3
    //   2948: if_icmple -> 2979
    //   2951: aload #22
    //   2953: invokevirtual g : ()I
    //   2956: istore #6
    //   2958: iload_3
    //   2959: aload #22
    //   2961: aload #24
    //   2963: invokevirtual f : (Lb/g/b/i/c$a;)Lb/g/b/i/c;
    //   2966: invokevirtual b : ()I
    //   2969: iload #6
    //   2971: iadd
    //   2972: invokestatic max : (II)I
    //   2975: istore_3
    //   2976: goto -> 2979
    //   2979: iconst_1
    //   2980: istore #6
    //   2982: goto -> 2985
    //   2985: aload #22
    //   2987: checkcast b/g/b/i/j
    //   2990: getfield h0 : Z
    //   2993: iload #6
    //   2995: ior
    //   2996: istore #6
    //   2998: iinc #7, 1
    //   3001: goto -> 2778
    //   3004: iload #5
    //   3006: istore #11
    //   3008: iconst_0
    //   3009: istore #14
    //   3011: iload #6
    //   3013: istore #7
    //   3015: iload_3
    //   3016: istore #12
    //   3018: aload #26
    //   3020: astore #22
    //   3022: iload #8
    //   3024: istore #5
    //   3026: iload #13
    //   3028: istore #6
    //   3030: iload #14
    //   3032: istore #8
    //   3034: iload #8
    //   3036: iconst_2
    //   3037: if_icmpge -> 3435
    //   3040: iconst_0
    //   3041: istore #13
    //   3043: iload #12
    //   3045: istore_3
    //   3046: iload #8
    //   3048: istore #12
    //   3050: iload #13
    //   3052: iload #6
    //   3054: if_icmpge -> 3401
    //   3057: aload #31
    //   3059: getfield a : Ljava/util/ArrayList;
    //   3062: iload #13
    //   3064: invokevirtual get : (I)Ljava/lang/Object;
    //   3067: checkcast b/g/b/i/d
    //   3070: astore #26
    //   3072: aload #26
    //   3074: instanceof b/g/b/i/g
    //   3077: ifeq -> 3088
    //   3080: aload #26
    //   3082: instanceof b/g/b/i/j
    //   3085: ifeq -> 3096
    //   3088: aload #26
    //   3090: instanceof b/g/b/i/f
    //   3093: ifeq -> 3099
    //   3096: goto -> 3151
    //   3099: aload #26
    //   3101: getfield X : I
    //   3104: bipush #8
    //   3106: if_icmpne -> 3112
    //   3109: goto -> 3151
    //   3112: aload #26
    //   3114: getfield d : Lb/g/b/i/l/j;
    //   3117: getfield e : Lb/g/b/i/l/g;
    //   3120: getfield j : Z
    //   3123: ifeq -> 3143
    //   3126: aload #26
    //   3128: getfield e : Lb/g/b/i/l/l;
    //   3131: getfield e : Lb/g/b/i/l/g;
    //   3134: getfield j : Z
    //   3137: ifeq -> 3143
    //   3140: goto -> 3151
    //   3143: aload #26
    //   3145: instanceof b/g/b/i/j
    //   3148: ifeq -> 3162
    //   3151: iload #4
    //   3153: istore #14
    //   3155: iload #7
    //   3157: istore #8
    //   3159: goto -> 3387
    //   3162: aload #26
    //   3164: invokevirtual o : ()I
    //   3167: istore #18
    //   3169: aload #26
    //   3171: invokevirtual i : ()I
    //   3174: istore #16
    //   3176: aload #26
    //   3178: getfield R : I
    //   3181: istore #14
    //   3183: iload #7
    //   3185: aload #31
    //   3187: aload #23
    //   3189: aload #26
    //   3191: iconst_1
    //   3192: invokevirtual a : (Lb/g/b/i/l/b$b;Lb/g/b/i/d;Z)Z
    //   3195: ior
    //   3196: istore #8
    //   3198: aload #26
    //   3200: invokevirtual o : ()I
    //   3203: istore #19
    //   3205: aload #26
    //   3207: invokevirtual i : ()I
    //   3210: istore #17
    //   3212: iload #4
    //   3214: istore #7
    //   3216: iload #19
    //   3218: iload #18
    //   3220: if_icmpeq -> 3283
    //   3223: aload #26
    //   3225: iload #19
    //   3227: invokevirtual B : (I)V
    //   3230: iload #4
    //   3232: istore #7
    //   3234: iload #9
    //   3236: ifeq -> 3280
    //   3239: iload #4
    //   3241: istore #7
    //   3243: aload #26
    //   3245: invokevirtual m : ()I
    //   3248: iload #4
    //   3250: if_icmple -> 3280
    //   3253: aload #26
    //   3255: invokevirtual m : ()I
    //   3258: istore #7
    //   3260: iload #4
    //   3262: aload #26
    //   3264: aload #25
    //   3266: invokevirtual f : (Lb/g/b/i/c$a;)Lb/g/b/i/c;
    //   3269: invokevirtual b : ()I
    //   3272: iload #7
    //   3274: iadd
    //   3275: invokestatic max : (II)I
    //   3278: istore #7
    //   3280: iconst_1
    //   3281: istore #8
    //   3283: iload_3
    //   3284: istore #4
    //   3286: iload #17
    //   3288: iload #16
    //   3290: if_icmpeq -> 3349
    //   3293: aload #26
    //   3295: iload #17
    //   3297: invokevirtual w : (I)V
    //   3300: iload_3
    //   3301: istore #4
    //   3303: iload #10
    //   3305: ifeq -> 3346
    //   3308: iload_3
    //   3309: istore #4
    //   3311: aload #26
    //   3313: invokevirtual g : ()I
    //   3316: iload_3
    //   3317: if_icmple -> 3346
    //   3320: aload #26
    //   3322: invokevirtual g : ()I
    //   3325: istore #4
    //   3327: iload_3
    //   3328: aload #26
    //   3330: aload #24
    //   3332: invokevirtual f : (Lb/g/b/i/c$a;)Lb/g/b/i/c;
    //   3335: invokevirtual b : ()I
    //   3338: iload #4
    //   3340: iadd
    //   3341: invokestatic max : (II)I
    //   3344: istore #4
    //   3346: iconst_1
    //   3347: istore #8
    //   3349: aload #26
    //   3351: getfield w : Z
    //   3354: ifeq -> 3380
    //   3357: iload #14
    //   3359: aload #26
    //   3361: getfield R : I
    //   3364: if_icmpeq -> 3380
    //   3367: iconst_1
    //   3368: istore #8
    //   3370: iload #7
    //   3372: istore #14
    //   3374: iload #4
    //   3376: istore_3
    //   3377: goto -> 3387
    //   3380: iload #4
    //   3382: istore_3
    //   3383: iload #7
    //   3385: istore #14
    //   3387: iinc #13, 1
    //   3390: iload #14
    //   3392: istore #4
    //   3394: iload #8
    //   3396: istore #7
    //   3398: goto -> 3050
    //   3401: iload #7
    //   3403: ifeq -> 3423
    //   3406: aload #31
    //   3408: aload #22
    //   3410: iload #5
    //   3412: iload #15
    //   3414: invokevirtual b : (Lb/g/b/i/e;II)V
    //   3417: iconst_0
    //   3418: istore #7
    //   3420: goto -> 3423
    //   3423: iload #12
    //   3425: iconst_1
    //   3426: iadd
    //   3427: istore #8
    //   3429: iload_3
    //   3430: istore #12
    //   3432: goto -> 3034
    //   3435: aload #22
    //   3437: astore #23
    //   3439: iload #11
    //   3441: istore_3
    //   3442: iload #7
    //   3444: ifeq -> 3545
    //   3447: aload #31
    //   3449: aload #22
    //   3451: iload #5
    //   3453: iload #15
    //   3455: invokevirtual b : (Lb/g/b/i/e;II)V
    //   3458: aload #22
    //   3460: invokevirtual o : ()I
    //   3463: iload #4
    //   3465: if_icmpge -> 3480
    //   3468: aload #22
    //   3470: iload #4
    //   3472: invokevirtual B : (I)V
    //   3475: iconst_1
    //   3476: istore_3
    //   3477: goto -> 3482
    //   3480: iconst_0
    //   3481: istore_3
    //   3482: iload_3
    //   3483: istore #4
    //   3485: aload #22
    //   3487: invokevirtual i : ()I
    //   3490: iload #12
    //   3492: if_icmpge -> 3505
    //   3495: aload #22
    //   3497: iload #12
    //   3499: invokevirtual w : (I)V
    //   3502: iconst_1
    //   3503: istore #4
    //   3505: aload #22
    //   3507: astore #23
    //   3509: iload #11
    //   3511: istore_3
    //   3512: iload #4
    //   3514: ifeq -> 3545
    //   3517: aload #31
    //   3519: aload #22
    //   3521: iload #5
    //   3523: iload #15
    //   3525: invokevirtual b : (Lb/g/b/i/e;II)V
    //   3528: aload #22
    //   3530: astore #23
    //   3532: iload #11
    //   3534: istore_3
    //   3535: goto -> 3545
    //   3538: iload #5
    //   3540: istore_3
    //   3541: aload #26
    //   3543: astore #23
    //   3545: aload #23
    //   3547: iload_3
    //   3548: invokevirtual J : (I)V
    //   3551: aload_0
    //   3552: getfield d : Lb/g/b/i/e;
    //   3555: invokevirtual o : ()I
    //   3558: istore #5
    //   3560: aload_0
    //   3561: getfield d : Lb/g/b/i/e;
    //   3564: invokevirtual i : ()I
    //   3567: istore_3
    //   3568: aload_0
    //   3569: getfield d : Lb/g/b/i/e;
    //   3572: astore #22
    //   3574: aload #22
    //   3576: getfield s0 : Z
    //   3579: istore #21
    //   3581: aload #22
    //   3583: getfield t0 : Z
    //   3586: istore #20
    //   3588: aload_0
    //   3589: getfield r : Landroidx/constraintlayout/widget/ConstraintLayout$b;
    //   3592: astore #22
    //   3594: aload #22
    //   3596: getfield e : I
    //   3599: istore #4
    //   3601: iload #5
    //   3603: aload #22
    //   3605: getfield d : I
    //   3608: iadd
    //   3609: iload_1
    //   3610: iconst_0
    //   3611: invokestatic resolveSizeAndState : (III)I
    //   3614: istore_1
    //   3615: iload_3
    //   3616: iload #4
    //   3618: iadd
    //   3619: iload_2
    //   3620: iconst_0
    //   3621: invokestatic resolveSizeAndState : (III)I
    //   3624: istore_3
    //   3625: aload_0
    //   3626: getfield g : I
    //   3629: iload_1
    //   3630: ldc_w 16777215
    //   3633: iand
    //   3634: invokestatic min : (II)I
    //   3637: istore_2
    //   3638: aload_0
    //   3639: getfield h : I
    //   3642: iload_3
    //   3643: ldc_w 16777215
    //   3646: iand
    //   3647: invokestatic min : (II)I
    //   3650: istore_3
    //   3651: iload_2
    //   3652: istore_1
    //   3653: iload #21
    //   3655: ifeq -> 3664
    //   3658: iload_2
    //   3659: ldc_w 16777216
    //   3662: ior
    //   3663: istore_1
    //   3664: iload_3
    //   3665: istore_2
    //   3666: iload #20
    //   3668: ifeq -> 3677
    //   3671: iload_3
    //   3672: ldc_w 16777216
    //   3675: ior
    //   3676: istore_2
    //   3677: aload_0
    //   3678: iload_1
    //   3679: iload_2
    //   3680: invokevirtual setMeasuredDimension : (II)V
    //   3683: aload_0
    //   3684: iload_1
    //   3685: putfield o : I
    //   3688: aload_0
    //   3689: iload_2
    //   3690: putfield p : I
    //   3693: return
    //   3694: aconst_null
    //   3695: athrow
  }
  
  public void onViewAdded(View paramView) {
    super.onViewAdded(paramView);
    d d1 = e(paramView);
    if (paramView instanceof b.g.c.h && !(d1 instanceof f)) {
      a a = (a)paramView.getLayoutParams();
      f f = new f();
      a.m0 = (d)f;
      a.Y = true;
      f.E(a.R);
    } 
    if (paramView instanceof c) {
      c c = (c)paramView;
      c.i();
      ((a)paramView.getLayoutParams()).Z = true;
      if (!this.c.contains(c))
        this.c.add(c); 
    } 
    this.b.put(paramView.getId(), paramView);
    this.i = true;
  }
  
  public void onViewRemoved(View paramView) {
    super.onViewRemoved(paramView);
    this.b.remove(paramView.getId());
    d d1 = e(paramView);
    ((k)this.d).f0.remove(d1);
    d1.K = null;
    this.c.remove(paramView);
    this.i = true;
  }
  
  public void removeView(View paramView) {
    super.removeView(paramView);
  }
  
  public void requestLayout() {
    this.i = true;
    this.o = -1;
    this.p = -1;
    super.requestLayout();
  }
  
  public void setConstraintSet(e parame) {
    this.k = parame;
  }
  
  public void setId(int paramInt) {
    this.b.remove(getId());
    super.setId(paramInt);
    this.b.put(getId(), this);
  }
  
  public void setMaxHeight(int paramInt) {
    if (paramInt == this.h)
      return; 
    this.h = paramInt;
    requestLayout();
  }
  
  public void setMaxWidth(int paramInt) {
    if (paramInt == this.g)
      return; 
    this.g = paramInt;
    requestLayout();
  }
  
  public void setMinHeight(int paramInt) {
    if (paramInt == this.f)
      return; 
    this.f = paramInt;
    requestLayout();
  }
  
  public void setMinWidth(int paramInt) {
    if (paramInt == this.e)
      return; 
    this.e = paramInt;
    requestLayout();
  }
  
  public void setOnConstraintsChanged(g paramg) {
    d d1 = this.l;
    if (d1 == null || d1 != null)
      return; 
    throw null;
  }
  
  public void setOptimizationLevel(int paramInt) {
    this.j = paramInt;
    this.d.r0 = paramInt;
    d.r = i.a(paramInt, 256);
  }
  
  public boolean shouldDelayChildPressedState() {
    return false;
  }
  
  public static class a extends ViewGroup.MarginLayoutParams {
    public float A = 0.5F;
    
    public String B = null;
    
    public int C = 1;
    
    public float D = -1.0F;
    
    public float E = -1.0F;
    
    public int F = 0;
    
    public int G = 0;
    
    public int H = 0;
    
    public int I = 0;
    
    public int J = 0;
    
    public int K = 0;
    
    public int L = 0;
    
    public int M = 0;
    
    public float N = 1.0F;
    
    public float O = 1.0F;
    
    public int P = -1;
    
    public int Q = -1;
    
    public int R = -1;
    
    public boolean S = false;
    
    public boolean T = false;
    
    public String U = null;
    
    public boolean V = true;
    
    public boolean W = true;
    
    public boolean X = false;
    
    public boolean Y = false;
    
    public boolean Z = false;
    
    public int a = -1;
    
    public boolean a0 = false;
    
    public int b = -1;
    
    public boolean b0 = false;
    
    public float c = -1.0F;
    
    public int c0 = -1;
    
    public int d = -1;
    
    public int d0 = -1;
    
    public int e = -1;
    
    public int e0 = -1;
    
    public int f = -1;
    
    public int f0 = -1;
    
    public int g = -1;
    
    public int g0 = -1;
    
    public int h = -1;
    
    public int h0 = -1;
    
    public int i = -1;
    
    public float i0 = 0.5F;
    
    public int j = -1;
    
    public int j0;
    
    public int k = -1;
    
    public int k0;
    
    public int l = -1;
    
    public float l0;
    
    public int m = -1;
    
    public d m0 = new d();
    
    public int n = 0;
    
    public float o = 0.0F;
    
    public int p = -1;
    
    public int q = -1;
    
    public int r = -1;
    
    public int s = -1;
    
    public int t = -1;
    
    public int u = -1;
    
    public int v = -1;
    
    public int w = -1;
    
    public int x = -1;
    
    public int y = -1;
    
    public float z = 0.5F;
    
    public a(int param1Int1, int param1Int2) {
      super(param1Int1, param1Int2);
    }
    
    public a(Context param1Context, AttributeSet param1AttributeSet) {
      // Byte code:
      //   0: aload_0
      //   1: aload_1
      //   2: aload_2
      //   3: invokespecial <init> : (Landroid/content/Context;Landroid/util/AttributeSet;)V
      //   6: aload_0
      //   7: iconst_m1
      //   8: putfield a : I
      //   11: aload_0
      //   12: iconst_m1
      //   13: putfield b : I
      //   16: aload_0
      //   17: ldc -1.0
      //   19: putfield c : F
      //   22: aload_0
      //   23: iconst_m1
      //   24: putfield d : I
      //   27: aload_0
      //   28: iconst_m1
      //   29: putfield e : I
      //   32: aload_0
      //   33: iconst_m1
      //   34: putfield f : I
      //   37: aload_0
      //   38: iconst_m1
      //   39: putfield g : I
      //   42: aload_0
      //   43: iconst_m1
      //   44: putfield h : I
      //   47: aload_0
      //   48: iconst_m1
      //   49: putfield i : I
      //   52: aload_0
      //   53: iconst_m1
      //   54: putfield j : I
      //   57: aload_0
      //   58: iconst_m1
      //   59: putfield k : I
      //   62: aload_0
      //   63: iconst_m1
      //   64: putfield l : I
      //   67: aload_0
      //   68: iconst_m1
      //   69: putfield m : I
      //   72: aload_0
      //   73: iconst_0
      //   74: putfield n : I
      //   77: aload_0
      //   78: fconst_0
      //   79: putfield o : F
      //   82: aload_0
      //   83: iconst_m1
      //   84: putfield p : I
      //   87: aload_0
      //   88: iconst_m1
      //   89: putfield q : I
      //   92: aload_0
      //   93: iconst_m1
      //   94: putfield r : I
      //   97: aload_0
      //   98: iconst_m1
      //   99: putfield s : I
      //   102: aload_0
      //   103: iconst_m1
      //   104: putfield t : I
      //   107: aload_0
      //   108: iconst_m1
      //   109: putfield u : I
      //   112: aload_0
      //   113: iconst_m1
      //   114: putfield v : I
      //   117: aload_0
      //   118: iconst_m1
      //   119: putfield w : I
      //   122: aload_0
      //   123: iconst_m1
      //   124: putfield x : I
      //   127: aload_0
      //   128: iconst_m1
      //   129: putfield y : I
      //   132: aload_0
      //   133: ldc 0.5
      //   135: putfield z : F
      //   138: aload_0
      //   139: ldc 0.5
      //   141: putfield A : F
      //   144: aload_0
      //   145: aconst_null
      //   146: putfield B : Ljava/lang/String;
      //   149: aload_0
      //   150: iconst_1
      //   151: putfield C : I
      //   154: aload_0
      //   155: ldc -1.0
      //   157: putfield D : F
      //   160: aload_0
      //   161: ldc -1.0
      //   163: putfield E : F
      //   166: aload_0
      //   167: iconst_0
      //   168: putfield F : I
      //   171: aload_0
      //   172: iconst_0
      //   173: putfield G : I
      //   176: aload_0
      //   177: iconst_0
      //   178: putfield H : I
      //   181: aload_0
      //   182: iconst_0
      //   183: putfield I : I
      //   186: aload_0
      //   187: iconst_0
      //   188: putfield J : I
      //   191: aload_0
      //   192: iconst_0
      //   193: putfield K : I
      //   196: aload_0
      //   197: iconst_0
      //   198: putfield L : I
      //   201: aload_0
      //   202: iconst_0
      //   203: putfield M : I
      //   206: aload_0
      //   207: fconst_1
      //   208: putfield N : F
      //   211: aload_0
      //   212: fconst_1
      //   213: putfield O : F
      //   216: aload_0
      //   217: iconst_m1
      //   218: putfield P : I
      //   221: aload_0
      //   222: iconst_m1
      //   223: putfield Q : I
      //   226: aload_0
      //   227: iconst_m1
      //   228: putfield R : I
      //   231: aload_0
      //   232: iconst_0
      //   233: putfield S : Z
      //   236: aload_0
      //   237: iconst_0
      //   238: putfield T : Z
      //   241: aload_0
      //   242: aconst_null
      //   243: putfield U : Ljava/lang/String;
      //   246: aload_0
      //   247: iconst_1
      //   248: putfield V : Z
      //   251: aload_0
      //   252: iconst_1
      //   253: putfield W : Z
      //   256: aload_0
      //   257: iconst_0
      //   258: putfield X : Z
      //   261: aload_0
      //   262: iconst_0
      //   263: putfield Y : Z
      //   266: aload_0
      //   267: iconst_0
      //   268: putfield Z : Z
      //   271: aload_0
      //   272: iconst_0
      //   273: putfield a0 : Z
      //   276: aload_0
      //   277: iconst_0
      //   278: putfield b0 : Z
      //   281: aload_0
      //   282: iconst_m1
      //   283: putfield c0 : I
      //   286: aload_0
      //   287: iconst_m1
      //   288: putfield d0 : I
      //   291: aload_0
      //   292: iconst_m1
      //   293: putfield e0 : I
      //   296: aload_0
      //   297: iconst_m1
      //   298: putfield f0 : I
      //   301: aload_0
      //   302: iconst_m1
      //   303: putfield g0 : I
      //   306: aload_0
      //   307: iconst_m1
      //   308: putfield h0 : I
      //   311: aload_0
      //   312: ldc 0.5
      //   314: putfield i0 : F
      //   317: aload_0
      //   318: new b/g/b/i/d
      //   321: dup
      //   322: invokespecial <init> : ()V
      //   325: putfield m0 : Lb/g/b/i/d;
      //   328: aload_1
      //   329: aload_2
      //   330: getstatic b/g/c/k.ConstraintLayout_Layout : [I
      //   333: invokevirtual obtainStyledAttributes : (Landroid/util/AttributeSet;[I)Landroid/content/res/TypedArray;
      //   336: astore_2
      //   337: aload_2
      //   338: invokevirtual getIndexCount : ()I
      //   341: istore #7
      //   343: iconst_0
      //   344: istore #5
      //   346: iload #5
      //   348: iload #7
      //   350: if_icmpge -> 2066
      //   353: aload_2
      //   354: iload #5
      //   356: invokevirtual getIndex : (I)I
      //   359: istore #6
      //   361: getstatic androidx/constraintlayout/widget/ConstraintLayout$a$a.a : Landroid/util/SparseIntArray;
      //   364: iload #6
      //   366: invokevirtual get : (I)I
      //   369: istore #8
      //   371: iload #8
      //   373: tableswitch default -> 540, 1 -> 2046, 2 -> 2008, 3 -> 1991, 4 -> 1949, 5 -> 1932, 6 -> 1915, 7 -> 1898, 8 -> 1860, 9 -> 1822, 10 -> 1784, 11 -> 1746, 12 -> 1708, 13 -> 1670, 14 -> 1632, 15 -> 1594, 16 -> 1556, 17 -> 1518, 18 -> 1480, 19 -> 1442, 20 -> 1404, 21 -> 1387, 22 -> 1370, 23 -> 1353, 24 -> 1336, 25 -> 1319, 26 -> 1302, 27 -> 1285, 28 -> 1268, 29 -> 1251, 30 -> 1234, 31 -> 1198, 32 -> 1170, 33 -> 1128, 34 -> 1086, 35 -> 1060, 36 -> 1018, 37 -> 976, 38 -> 950
      //   540: iload #8
      //   542: tableswitch default -> 588, 44 -> 700, 45 -> 683, 46 -> 666, 47 -> 652, 48 -> 638, 49 -> 621, 50 -> 604, 51 -> 591
      //   588: goto -> 2060
      //   591: aload_0
      //   592: aload_2
      //   593: iload #6
      //   595: invokevirtual getString : (I)Ljava/lang/String;
      //   598: putfield U : Ljava/lang/String;
      //   601: goto -> 2060
      //   604: aload_0
      //   605: aload_2
      //   606: iload #6
      //   608: aload_0
      //   609: getfield Q : I
      //   612: invokevirtual getDimensionPixelOffset : (II)I
      //   615: putfield Q : I
      //   618: goto -> 2060
      //   621: aload_0
      //   622: aload_2
      //   623: iload #6
      //   625: aload_0
      //   626: getfield P : I
      //   629: invokevirtual getDimensionPixelOffset : (II)I
      //   632: putfield P : I
      //   635: goto -> 2060
      //   638: aload_0
      //   639: aload_2
      //   640: iload #6
      //   642: iconst_0
      //   643: invokevirtual getInt : (II)I
      //   646: putfield G : I
      //   649: goto -> 2060
      //   652: aload_0
      //   653: aload_2
      //   654: iload #6
      //   656: iconst_0
      //   657: invokevirtual getInt : (II)I
      //   660: putfield F : I
      //   663: goto -> 2060
      //   666: aload_0
      //   667: aload_2
      //   668: iload #6
      //   670: aload_0
      //   671: getfield E : F
      //   674: invokevirtual getFloat : (IF)F
      //   677: putfield E : F
      //   680: goto -> 2060
      //   683: aload_0
      //   684: aload_2
      //   685: iload #6
      //   687: aload_0
      //   688: getfield D : F
      //   691: invokevirtual getFloat : (IF)F
      //   694: putfield D : F
      //   697: goto -> 2060
      //   700: aload_2
      //   701: iload #6
      //   703: invokevirtual getString : (I)Ljava/lang/String;
      //   706: astore_1
      //   707: aload_0
      //   708: aload_1
      //   709: putfield B : Ljava/lang/String;
      //   712: aload_0
      //   713: iconst_m1
      //   714: putfield C : I
      //   717: aload_1
      //   718: ifnull -> 2060
      //   721: aload_1
      //   722: invokevirtual length : ()I
      //   725: istore #8
      //   727: aload_0
      //   728: getfield B : Ljava/lang/String;
      //   731: bipush #44
      //   733: invokevirtual indexOf : (I)I
      //   736: istore #6
      //   738: iload #6
      //   740: ifle -> 802
      //   743: iload #6
      //   745: iload #8
      //   747: iconst_1
      //   748: isub
      //   749: if_icmpge -> 802
      //   752: aload_0
      //   753: getfield B : Ljava/lang/String;
      //   756: iconst_0
      //   757: iload #6
      //   759: invokevirtual substring : (II)Ljava/lang/String;
      //   762: astore_1
      //   763: aload_1
      //   764: ldc_w 'W'
      //   767: invokevirtual equalsIgnoreCase : (Ljava/lang/String;)Z
      //   770: ifeq -> 781
      //   773: aload_0
      //   774: iconst_0
      //   775: putfield C : I
      //   778: goto -> 796
      //   781: aload_1
      //   782: ldc_w 'H'
      //   785: invokevirtual equalsIgnoreCase : (Ljava/lang/String;)Z
      //   788: ifeq -> 796
      //   791: aload_0
      //   792: iconst_1
      //   793: putfield C : I
      //   796: iinc #6, 1
      //   799: goto -> 805
      //   802: iconst_0
      //   803: istore #6
      //   805: aload_0
      //   806: getfield B : Ljava/lang/String;
      //   809: bipush #58
      //   811: invokevirtual indexOf : (I)I
      //   814: istore #9
      //   816: iload #9
      //   818: iflt -> 925
      //   821: iload #9
      //   823: iload #8
      //   825: iconst_1
      //   826: isub
      //   827: if_icmpge -> 925
      //   830: aload_0
      //   831: getfield B : Ljava/lang/String;
      //   834: iload #6
      //   836: iload #9
      //   838: invokevirtual substring : (II)Ljava/lang/String;
      //   841: astore_1
      //   842: aload_0
      //   843: getfield B : Ljava/lang/String;
      //   846: iload #9
      //   848: iconst_1
      //   849: iadd
      //   850: invokevirtual substring : (I)Ljava/lang/String;
      //   853: astore #10
      //   855: aload_1
      //   856: invokevirtual length : ()I
      //   859: ifle -> 2060
      //   862: aload #10
      //   864: invokevirtual length : ()I
      //   867: ifle -> 2060
      //   870: aload_1
      //   871: invokestatic parseFloat : (Ljava/lang/String;)F
      //   874: fstore_3
      //   875: aload #10
      //   877: invokestatic parseFloat : (Ljava/lang/String;)F
      //   880: fstore #4
      //   882: fload_3
      //   883: fconst_0
      //   884: fcmpl
      //   885: ifle -> 2060
      //   888: fload #4
      //   890: fconst_0
      //   891: fcmpl
      //   892: ifle -> 2060
      //   895: aload_0
      //   896: getfield C : I
      //   899: iconst_1
      //   900: if_icmpne -> 914
      //   903: fload #4
      //   905: fload_3
      //   906: fdiv
      //   907: invokestatic abs : (F)F
      //   910: pop
      //   911: goto -> 2060
      //   914: fload_3
      //   915: fload #4
      //   917: fdiv
      //   918: invokestatic abs : (F)F
      //   921: pop
      //   922: goto -> 2060
      //   925: aload_0
      //   926: getfield B : Ljava/lang/String;
      //   929: iload #6
      //   931: invokevirtual substring : (I)Ljava/lang/String;
      //   934: astore_1
      //   935: aload_1
      //   936: invokevirtual length : ()I
      //   939: ifle -> 2060
      //   942: aload_1
      //   943: invokestatic parseFloat : (Ljava/lang/String;)F
      //   946: pop
      //   947: goto -> 2060
      //   950: aload_0
      //   951: fconst_0
      //   952: aload_2
      //   953: iload #6
      //   955: aload_0
      //   956: getfield O : F
      //   959: invokevirtual getFloat : (IF)F
      //   962: invokestatic max : (FF)F
      //   965: putfield O : F
      //   968: aload_0
      //   969: iconst_2
      //   970: putfield I : I
      //   973: goto -> 2060
      //   976: aload_0
      //   977: aload_2
      //   978: iload #6
      //   980: aload_0
      //   981: getfield M : I
      //   984: invokevirtual getDimensionPixelSize : (II)I
      //   987: putfield M : I
      //   990: goto -> 2060
      //   993: astore_1
      //   994: aload_2
      //   995: iload #6
      //   997: aload_0
      //   998: getfield M : I
      //   1001: invokevirtual getInt : (II)I
      //   1004: bipush #-2
      //   1006: if_icmpne -> 2060
      //   1009: aload_0
      //   1010: bipush #-2
      //   1012: putfield M : I
      //   1015: goto -> 2060
      //   1018: aload_0
      //   1019: aload_2
      //   1020: iload #6
      //   1022: aload_0
      //   1023: getfield K : I
      //   1026: invokevirtual getDimensionPixelSize : (II)I
      //   1029: putfield K : I
      //   1032: goto -> 2060
      //   1035: astore_1
      //   1036: aload_2
      //   1037: iload #6
      //   1039: aload_0
      //   1040: getfield K : I
      //   1043: invokevirtual getInt : (II)I
      //   1046: bipush #-2
      //   1048: if_icmpne -> 2060
      //   1051: aload_0
      //   1052: bipush #-2
      //   1054: putfield K : I
      //   1057: goto -> 2060
      //   1060: aload_0
      //   1061: fconst_0
      //   1062: aload_2
      //   1063: iload #6
      //   1065: aload_0
      //   1066: getfield N : F
      //   1069: invokevirtual getFloat : (IF)F
      //   1072: invokestatic max : (FF)F
      //   1075: putfield N : F
      //   1078: aload_0
      //   1079: iconst_2
      //   1080: putfield H : I
      //   1083: goto -> 2060
      //   1086: aload_0
      //   1087: aload_2
      //   1088: iload #6
      //   1090: aload_0
      //   1091: getfield L : I
      //   1094: invokevirtual getDimensionPixelSize : (II)I
      //   1097: putfield L : I
      //   1100: goto -> 2060
      //   1103: astore_1
      //   1104: aload_2
      //   1105: iload #6
      //   1107: aload_0
      //   1108: getfield L : I
      //   1111: invokevirtual getInt : (II)I
      //   1114: bipush #-2
      //   1116: if_icmpne -> 2060
      //   1119: aload_0
      //   1120: bipush #-2
      //   1122: putfield L : I
      //   1125: goto -> 2060
      //   1128: aload_0
      //   1129: aload_2
      //   1130: iload #6
      //   1132: aload_0
      //   1133: getfield J : I
      //   1136: invokevirtual getDimensionPixelSize : (II)I
      //   1139: putfield J : I
      //   1142: goto -> 2060
      //   1145: astore_1
      //   1146: aload_2
      //   1147: iload #6
      //   1149: aload_0
      //   1150: getfield J : I
      //   1153: invokevirtual getInt : (II)I
      //   1156: bipush #-2
      //   1158: if_icmpne -> 2060
      //   1161: aload_0
      //   1162: bipush #-2
      //   1164: putfield J : I
      //   1167: goto -> 2060
      //   1170: aload_2
      //   1171: iload #6
      //   1173: iconst_0
      //   1174: invokevirtual getInt : (II)I
      //   1177: istore #6
      //   1179: aload_0
      //   1180: iload #6
      //   1182: putfield I : I
      //   1185: iload #6
      //   1187: iconst_1
      //   1188: if_icmpne -> 2060
      //   1191: ldc_w 'layout_constraintHeight_default="wrap" is deprecated.\\nUse layout_height="WRAP_CONTENT" and layout_constrainedHeight="true" instead.'
      //   1194: astore_1
      //   1195: goto -> 1223
      //   1198: aload_2
      //   1199: iload #6
      //   1201: iconst_0
      //   1202: invokevirtual getInt : (II)I
      //   1205: istore #6
      //   1207: aload_0
      //   1208: iload #6
      //   1210: putfield H : I
      //   1213: iload #6
      //   1215: iconst_1
      //   1216: if_icmpne -> 2060
      //   1219: ldc_w 'layout_constraintWidth_default="wrap" is deprecated.\\nUse layout_width="WRAP_CONTENT" and layout_constrainedWidth="true" instead.'
      //   1222: astore_1
      //   1223: ldc_w 'ConstraintLayout'
      //   1226: aload_1
      //   1227: invokestatic e : (Ljava/lang/String;Ljava/lang/String;)I
      //   1230: pop
      //   1231: goto -> 2060
      //   1234: aload_0
      //   1235: aload_2
      //   1236: iload #6
      //   1238: aload_0
      //   1239: getfield A : F
      //   1242: invokevirtual getFloat : (IF)F
      //   1245: putfield A : F
      //   1248: goto -> 2060
      //   1251: aload_0
      //   1252: aload_2
      //   1253: iload #6
      //   1255: aload_0
      //   1256: getfield z : F
      //   1259: invokevirtual getFloat : (IF)F
      //   1262: putfield z : F
      //   1265: goto -> 2060
      //   1268: aload_0
      //   1269: aload_2
      //   1270: iload #6
      //   1272: aload_0
      //   1273: getfield T : Z
      //   1276: invokevirtual getBoolean : (IZ)Z
      //   1279: putfield T : Z
      //   1282: goto -> 2060
      //   1285: aload_0
      //   1286: aload_2
      //   1287: iload #6
      //   1289: aload_0
      //   1290: getfield S : Z
      //   1293: invokevirtual getBoolean : (IZ)Z
      //   1296: putfield S : Z
      //   1299: goto -> 2060
      //   1302: aload_0
      //   1303: aload_2
      //   1304: iload #6
      //   1306: aload_0
      //   1307: getfield y : I
      //   1310: invokevirtual getDimensionPixelSize : (II)I
      //   1313: putfield y : I
      //   1316: goto -> 2060
      //   1319: aload_0
      //   1320: aload_2
      //   1321: iload #6
      //   1323: aload_0
      //   1324: getfield x : I
      //   1327: invokevirtual getDimensionPixelSize : (II)I
      //   1330: putfield x : I
      //   1333: goto -> 2060
      //   1336: aload_0
      //   1337: aload_2
      //   1338: iload #6
      //   1340: aload_0
      //   1341: getfield w : I
      //   1344: invokevirtual getDimensionPixelSize : (II)I
      //   1347: putfield w : I
      //   1350: goto -> 2060
      //   1353: aload_0
      //   1354: aload_2
      //   1355: iload #6
      //   1357: aload_0
      //   1358: getfield v : I
      //   1361: invokevirtual getDimensionPixelSize : (II)I
      //   1364: putfield v : I
      //   1367: goto -> 2060
      //   1370: aload_0
      //   1371: aload_2
      //   1372: iload #6
      //   1374: aload_0
      //   1375: getfield u : I
      //   1378: invokevirtual getDimensionPixelSize : (II)I
      //   1381: putfield u : I
      //   1384: goto -> 2060
      //   1387: aload_0
      //   1388: aload_2
      //   1389: iload #6
      //   1391: aload_0
      //   1392: getfield t : I
      //   1395: invokevirtual getDimensionPixelSize : (II)I
      //   1398: putfield t : I
      //   1401: goto -> 2060
      //   1404: aload_2
      //   1405: iload #6
      //   1407: aload_0
      //   1408: getfield s : I
      //   1411: invokevirtual getResourceId : (II)I
      //   1414: istore #8
      //   1416: aload_0
      //   1417: iload #8
      //   1419: putfield s : I
      //   1422: iload #8
      //   1424: iconst_m1
      //   1425: if_icmpne -> 2060
      //   1428: aload_0
      //   1429: aload_2
      //   1430: iload #6
      //   1432: iconst_m1
      //   1433: invokevirtual getInt : (II)I
      //   1436: putfield s : I
      //   1439: goto -> 2060
      //   1442: aload_2
      //   1443: iload #6
      //   1445: aload_0
      //   1446: getfield r : I
      //   1449: invokevirtual getResourceId : (II)I
      //   1452: istore #8
      //   1454: aload_0
      //   1455: iload #8
      //   1457: putfield r : I
      //   1460: iload #8
      //   1462: iconst_m1
      //   1463: if_icmpne -> 2060
      //   1466: aload_0
      //   1467: aload_2
      //   1468: iload #6
      //   1470: iconst_m1
      //   1471: invokevirtual getInt : (II)I
      //   1474: putfield r : I
      //   1477: goto -> 2060
      //   1480: aload_2
      //   1481: iload #6
      //   1483: aload_0
      //   1484: getfield q : I
      //   1487: invokevirtual getResourceId : (II)I
      //   1490: istore #8
      //   1492: aload_0
      //   1493: iload #8
      //   1495: putfield q : I
      //   1498: iload #8
      //   1500: iconst_m1
      //   1501: if_icmpne -> 2060
      //   1504: aload_0
      //   1505: aload_2
      //   1506: iload #6
      //   1508: iconst_m1
      //   1509: invokevirtual getInt : (II)I
      //   1512: putfield q : I
      //   1515: goto -> 2060
      //   1518: aload_2
      //   1519: iload #6
      //   1521: aload_0
      //   1522: getfield p : I
      //   1525: invokevirtual getResourceId : (II)I
      //   1528: istore #8
      //   1530: aload_0
      //   1531: iload #8
      //   1533: putfield p : I
      //   1536: iload #8
      //   1538: iconst_m1
      //   1539: if_icmpne -> 2060
      //   1542: aload_0
      //   1543: aload_2
      //   1544: iload #6
      //   1546: iconst_m1
      //   1547: invokevirtual getInt : (II)I
      //   1550: putfield p : I
      //   1553: goto -> 2060
      //   1556: aload_2
      //   1557: iload #6
      //   1559: aload_0
      //   1560: getfield l : I
      //   1563: invokevirtual getResourceId : (II)I
      //   1566: istore #8
      //   1568: aload_0
      //   1569: iload #8
      //   1571: putfield l : I
      //   1574: iload #8
      //   1576: iconst_m1
      //   1577: if_icmpne -> 2060
      //   1580: aload_0
      //   1581: aload_2
      //   1582: iload #6
      //   1584: iconst_m1
      //   1585: invokevirtual getInt : (II)I
      //   1588: putfield l : I
      //   1591: goto -> 2060
      //   1594: aload_2
      //   1595: iload #6
      //   1597: aload_0
      //   1598: getfield k : I
      //   1601: invokevirtual getResourceId : (II)I
      //   1604: istore #8
      //   1606: aload_0
      //   1607: iload #8
      //   1609: putfield k : I
      //   1612: iload #8
      //   1614: iconst_m1
      //   1615: if_icmpne -> 2060
      //   1618: aload_0
      //   1619: aload_2
      //   1620: iload #6
      //   1622: iconst_m1
      //   1623: invokevirtual getInt : (II)I
      //   1626: putfield k : I
      //   1629: goto -> 2060
      //   1632: aload_2
      //   1633: iload #6
      //   1635: aload_0
      //   1636: getfield j : I
      //   1639: invokevirtual getResourceId : (II)I
      //   1642: istore #8
      //   1644: aload_0
      //   1645: iload #8
      //   1647: putfield j : I
      //   1650: iload #8
      //   1652: iconst_m1
      //   1653: if_icmpne -> 2060
      //   1656: aload_0
      //   1657: aload_2
      //   1658: iload #6
      //   1660: iconst_m1
      //   1661: invokevirtual getInt : (II)I
      //   1664: putfield j : I
      //   1667: goto -> 2060
      //   1670: aload_2
      //   1671: iload #6
      //   1673: aload_0
      //   1674: getfield i : I
      //   1677: invokevirtual getResourceId : (II)I
      //   1680: istore #8
      //   1682: aload_0
      //   1683: iload #8
      //   1685: putfield i : I
      //   1688: iload #8
      //   1690: iconst_m1
      //   1691: if_icmpne -> 2060
      //   1694: aload_0
      //   1695: aload_2
      //   1696: iload #6
      //   1698: iconst_m1
      //   1699: invokevirtual getInt : (II)I
      //   1702: putfield i : I
      //   1705: goto -> 2060
      //   1708: aload_2
      //   1709: iload #6
      //   1711: aload_0
      //   1712: getfield h : I
      //   1715: invokevirtual getResourceId : (II)I
      //   1718: istore #8
      //   1720: aload_0
      //   1721: iload #8
      //   1723: putfield h : I
      //   1726: iload #8
      //   1728: iconst_m1
      //   1729: if_icmpne -> 2060
      //   1732: aload_0
      //   1733: aload_2
      //   1734: iload #6
      //   1736: iconst_m1
      //   1737: invokevirtual getInt : (II)I
      //   1740: putfield h : I
      //   1743: goto -> 2060
      //   1746: aload_2
      //   1747: iload #6
      //   1749: aload_0
      //   1750: getfield g : I
      //   1753: invokevirtual getResourceId : (II)I
      //   1756: istore #8
      //   1758: aload_0
      //   1759: iload #8
      //   1761: putfield g : I
      //   1764: iload #8
      //   1766: iconst_m1
      //   1767: if_icmpne -> 2060
      //   1770: aload_0
      //   1771: aload_2
      //   1772: iload #6
      //   1774: iconst_m1
      //   1775: invokevirtual getInt : (II)I
      //   1778: putfield g : I
      //   1781: goto -> 2060
      //   1784: aload_2
      //   1785: iload #6
      //   1787: aload_0
      //   1788: getfield f : I
      //   1791: invokevirtual getResourceId : (II)I
      //   1794: istore #8
      //   1796: aload_0
      //   1797: iload #8
      //   1799: putfield f : I
      //   1802: iload #8
      //   1804: iconst_m1
      //   1805: if_icmpne -> 2060
      //   1808: aload_0
      //   1809: aload_2
      //   1810: iload #6
      //   1812: iconst_m1
      //   1813: invokevirtual getInt : (II)I
      //   1816: putfield f : I
      //   1819: goto -> 2060
      //   1822: aload_2
      //   1823: iload #6
      //   1825: aload_0
      //   1826: getfield e : I
      //   1829: invokevirtual getResourceId : (II)I
      //   1832: istore #8
      //   1834: aload_0
      //   1835: iload #8
      //   1837: putfield e : I
      //   1840: iload #8
      //   1842: iconst_m1
      //   1843: if_icmpne -> 2060
      //   1846: aload_0
      //   1847: aload_2
      //   1848: iload #6
      //   1850: iconst_m1
      //   1851: invokevirtual getInt : (II)I
      //   1854: putfield e : I
      //   1857: goto -> 2060
      //   1860: aload_2
      //   1861: iload #6
      //   1863: aload_0
      //   1864: getfield d : I
      //   1867: invokevirtual getResourceId : (II)I
      //   1870: istore #8
      //   1872: aload_0
      //   1873: iload #8
      //   1875: putfield d : I
      //   1878: iload #8
      //   1880: iconst_m1
      //   1881: if_icmpne -> 2060
      //   1884: aload_0
      //   1885: aload_2
      //   1886: iload #6
      //   1888: iconst_m1
      //   1889: invokevirtual getInt : (II)I
      //   1892: putfield d : I
      //   1895: goto -> 2060
      //   1898: aload_0
      //   1899: aload_2
      //   1900: iload #6
      //   1902: aload_0
      //   1903: getfield c : F
      //   1906: invokevirtual getFloat : (IF)F
      //   1909: putfield c : F
      //   1912: goto -> 2060
      //   1915: aload_0
      //   1916: aload_2
      //   1917: iload #6
      //   1919: aload_0
      //   1920: getfield b : I
      //   1923: invokevirtual getDimensionPixelOffset : (II)I
      //   1926: putfield b : I
      //   1929: goto -> 2060
      //   1932: aload_0
      //   1933: aload_2
      //   1934: iload #6
      //   1936: aload_0
      //   1937: getfield a : I
      //   1940: invokevirtual getDimensionPixelOffset : (II)I
      //   1943: putfield a : I
      //   1946: goto -> 2060
      //   1949: aload_2
      //   1950: iload #6
      //   1952: aload_0
      //   1953: getfield o : F
      //   1956: invokevirtual getFloat : (IF)F
      //   1959: ldc_w 360.0
      //   1962: frem
      //   1963: fstore_3
      //   1964: aload_0
      //   1965: fload_3
      //   1966: putfield o : F
      //   1969: fload_3
      //   1970: fconst_0
      //   1971: fcmpg
      //   1972: ifge -> 2060
      //   1975: aload_0
      //   1976: ldc_w 360.0
      //   1979: fload_3
      //   1980: fsub
      //   1981: ldc_w 360.0
      //   1984: frem
      //   1985: putfield o : F
      //   1988: goto -> 2060
      //   1991: aload_0
      //   1992: aload_2
      //   1993: iload #6
      //   1995: aload_0
      //   1996: getfield n : I
      //   1999: invokevirtual getDimensionPixelSize : (II)I
      //   2002: putfield n : I
      //   2005: goto -> 2060
      //   2008: aload_2
      //   2009: iload #6
      //   2011: aload_0
      //   2012: getfield m : I
      //   2015: invokevirtual getResourceId : (II)I
      //   2018: istore #8
      //   2020: aload_0
      //   2021: iload #8
      //   2023: putfield m : I
      //   2026: iload #8
      //   2028: iconst_m1
      //   2029: if_icmpne -> 2060
      //   2032: aload_0
      //   2033: aload_2
      //   2034: iload #6
      //   2036: iconst_m1
      //   2037: invokevirtual getInt : (II)I
      //   2040: putfield m : I
      //   2043: goto -> 2060
      //   2046: aload_0
      //   2047: aload_2
      //   2048: iload #6
      //   2050: aload_0
      //   2051: getfield R : I
      //   2054: invokevirtual getInt : (II)I
      //   2057: putfield R : I
      //   2060: iinc #5, 1
      //   2063: goto -> 346
      //   2066: aload_2
      //   2067: invokevirtual recycle : ()V
      //   2070: aload_0
      //   2071: invokevirtual a : ()V
      //   2074: return
      //   2075: astore_1
      //   2076: goto -> 2060
      // Exception table:
      //   from	to	target	type
      //   870	882	2075	java/lang/NumberFormatException
      //   895	911	2075	java/lang/NumberFormatException
      //   914	922	2075	java/lang/NumberFormatException
      //   942	947	2075	java/lang/NumberFormatException
      //   976	990	993	java/lang/Exception
      //   1018	1032	1035	java/lang/Exception
      //   1086	1100	1103	java/lang/Exception
      //   1128	1142	1145	java/lang/Exception
    }
    
    public a(ViewGroup.LayoutParams param1LayoutParams) {
      super(param1LayoutParams);
    }
    
    public void a() {
      this.Y = false;
      this.V = true;
      this.W = true;
      if (this.width == -2 && this.S) {
        this.V = false;
        if (this.H == 0)
          this.H = 1; 
      } 
      if (this.height == -2 && this.T) {
        this.W = false;
        if (this.I == 0)
          this.I = 1; 
      } 
      int i = this.width;
      if (i == 0 || i == -1) {
        this.V = false;
        if (this.width == 0 && this.H == 1) {
          this.width = -2;
          this.S = true;
        } 
      } 
      i = this.height;
      if (i == 0 || i == -1) {
        this.W = false;
        if (this.height == 0 && this.I == 1) {
          this.height = -2;
          this.T = true;
        } 
      } 
      if (this.c != -1.0F || this.a != -1 || this.b != -1) {
        this.Y = true;
        this.V = true;
        this.W = true;
        if (!(this.m0 instanceof f))
          this.m0 = (d)new f(); 
        ((f)this.m0).E(this.R);
      } 
    }
    
    @TargetApi(17)
    public void resolveLayoutDirection(int param1Int) {
      // Byte code:
      //   0: aload_0
      //   1: getfield leftMargin : I
      //   4: istore #4
      //   6: aload_0
      //   7: getfield rightMargin : I
      //   10: istore #5
      //   12: aload_0
      //   13: iload_1
      //   14: invokespecial resolveLayoutDirection : (I)V
      //   17: aload_0
      //   18: invokevirtual getLayoutDirection : ()I
      //   21: istore_1
      //   22: iconst_0
      //   23: istore_3
      //   24: iconst_1
      //   25: iload_1
      //   26: if_icmpne -> 34
      //   29: iconst_1
      //   30: istore_1
      //   31: goto -> 36
      //   34: iconst_0
      //   35: istore_1
      //   36: aload_0
      //   37: iconst_m1
      //   38: putfield e0 : I
      //   41: aload_0
      //   42: iconst_m1
      //   43: putfield f0 : I
      //   46: aload_0
      //   47: iconst_m1
      //   48: putfield c0 : I
      //   51: aload_0
      //   52: iconst_m1
      //   53: putfield d0 : I
      //   56: aload_0
      //   57: iconst_m1
      //   58: putfield g0 : I
      //   61: aload_0
      //   62: iconst_m1
      //   63: putfield h0 : I
      //   66: aload_0
      //   67: aload_0
      //   68: getfield t : I
      //   71: putfield g0 : I
      //   74: aload_0
      //   75: aload_0
      //   76: getfield v : I
      //   79: putfield h0 : I
      //   82: aload_0
      //   83: aload_0
      //   84: getfield z : F
      //   87: putfield i0 : F
      //   90: aload_0
      //   91: aload_0
      //   92: getfield a : I
      //   95: putfield j0 : I
      //   98: aload_0
      //   99: aload_0
      //   100: getfield b : I
      //   103: putfield k0 : I
      //   106: aload_0
      //   107: aload_0
      //   108: getfield c : F
      //   111: putfield l0 : F
      //   114: iload_1
      //   115: ifeq -> 338
      //   118: aload_0
      //   119: getfield p : I
      //   122: istore_1
      //   123: iload_1
      //   124: iconst_m1
      //   125: if_icmpeq -> 138
      //   128: aload_0
      //   129: iload_1
      //   130: putfield e0 : I
      //   133: iconst_1
      //   134: istore_1
      //   135: goto -> 161
      //   138: aload_0
      //   139: getfield q : I
      //   142: istore #6
      //   144: iload_3
      //   145: istore_1
      //   146: iload #6
      //   148: iconst_m1
      //   149: if_icmpeq -> 161
      //   152: aload_0
      //   153: iload #6
      //   155: putfield f0 : I
      //   158: goto -> 133
      //   161: aload_0
      //   162: getfield r : I
      //   165: istore_3
      //   166: iload_3
      //   167: iconst_m1
      //   168: if_icmpeq -> 178
      //   171: aload_0
      //   172: iload_3
      //   173: putfield d0 : I
      //   176: iconst_1
      //   177: istore_1
      //   178: aload_0
      //   179: getfield s : I
      //   182: istore_3
      //   183: iload_3
      //   184: iconst_m1
      //   185: if_icmpeq -> 195
      //   188: aload_0
      //   189: iload_3
      //   190: putfield c0 : I
      //   193: iconst_1
      //   194: istore_1
      //   195: aload_0
      //   196: getfield x : I
      //   199: istore_3
      //   200: iload_3
      //   201: iconst_m1
      //   202: if_icmpeq -> 210
      //   205: aload_0
      //   206: iload_3
      //   207: putfield h0 : I
      //   210: aload_0
      //   211: getfield y : I
      //   214: istore_3
      //   215: iload_3
      //   216: iconst_m1
      //   217: if_icmpeq -> 225
      //   220: aload_0
      //   221: iload_3
      //   222: putfield g0 : I
      //   225: iload_1
      //   226: ifeq -> 239
      //   229: aload_0
      //   230: fconst_1
      //   231: aload_0
      //   232: getfield z : F
      //   235: fsub
      //   236: putfield i0 : F
      //   239: aload_0
      //   240: getfield Y : Z
      //   243: ifeq -> 428
      //   246: aload_0
      //   247: getfield R : I
      //   250: iconst_1
      //   251: if_icmpne -> 428
      //   254: aload_0
      //   255: getfield c : F
      //   258: fstore_2
      //   259: fload_2
      //   260: ldc -1.0
      //   262: fcmpl
      //   263: ifeq -> 286
      //   266: aload_0
      //   267: fconst_1
      //   268: fload_2
      //   269: fsub
      //   270: putfield l0 : F
      //   273: aload_0
      //   274: iconst_m1
      //   275: putfield j0 : I
      //   278: aload_0
      //   279: iconst_m1
      //   280: putfield k0 : I
      //   283: goto -> 428
      //   286: aload_0
      //   287: getfield a : I
      //   290: istore_1
      //   291: iload_1
      //   292: iconst_m1
      //   293: if_icmpeq -> 315
      //   296: aload_0
      //   297: iload_1
      //   298: putfield k0 : I
      //   301: aload_0
      //   302: iconst_m1
      //   303: putfield j0 : I
      //   306: aload_0
      //   307: ldc -1.0
      //   309: putfield l0 : F
      //   312: goto -> 428
      //   315: aload_0
      //   316: getfield b : I
      //   319: istore_1
      //   320: iload_1
      //   321: iconst_m1
      //   322: if_icmpeq -> 428
      //   325: aload_0
      //   326: iload_1
      //   327: putfield j0 : I
      //   330: aload_0
      //   331: iconst_m1
      //   332: putfield k0 : I
      //   335: goto -> 306
      //   338: aload_0
      //   339: getfield p : I
      //   342: istore_1
      //   343: iload_1
      //   344: iconst_m1
      //   345: if_icmpeq -> 353
      //   348: aload_0
      //   349: iload_1
      //   350: putfield d0 : I
      //   353: aload_0
      //   354: getfield q : I
      //   357: istore_1
      //   358: iload_1
      //   359: iconst_m1
      //   360: if_icmpeq -> 368
      //   363: aload_0
      //   364: iload_1
      //   365: putfield c0 : I
      //   368: aload_0
      //   369: getfield r : I
      //   372: istore_1
      //   373: iload_1
      //   374: iconst_m1
      //   375: if_icmpeq -> 383
      //   378: aload_0
      //   379: iload_1
      //   380: putfield e0 : I
      //   383: aload_0
      //   384: getfield s : I
      //   387: istore_1
      //   388: iload_1
      //   389: iconst_m1
      //   390: if_icmpeq -> 398
      //   393: aload_0
      //   394: iload_1
      //   395: putfield f0 : I
      //   398: aload_0
      //   399: getfield x : I
      //   402: istore_1
      //   403: iload_1
      //   404: iconst_m1
      //   405: if_icmpeq -> 413
      //   408: aload_0
      //   409: iload_1
      //   410: putfield g0 : I
      //   413: aload_0
      //   414: getfield y : I
      //   417: istore_1
      //   418: iload_1
      //   419: iconst_m1
      //   420: if_icmpeq -> 428
      //   423: aload_0
      //   424: iload_1
      //   425: putfield h0 : I
      //   428: aload_0
      //   429: getfield r : I
      //   432: iconst_m1
      //   433: if_icmpne -> 592
      //   436: aload_0
      //   437: getfield s : I
      //   440: iconst_m1
      //   441: if_icmpne -> 592
      //   444: aload_0
      //   445: getfield q : I
      //   448: iconst_m1
      //   449: if_icmpne -> 592
      //   452: aload_0
      //   453: getfield p : I
      //   456: iconst_m1
      //   457: if_icmpne -> 592
      //   460: aload_0
      //   461: getfield f : I
      //   464: istore_1
      //   465: iload_1
      //   466: iconst_m1
      //   467: if_icmpeq -> 496
      //   470: aload_0
      //   471: iload_1
      //   472: putfield e0 : I
      //   475: aload_0
      //   476: getfield rightMargin : I
      //   479: ifgt -> 526
      //   482: iload #5
      //   484: ifle -> 526
      //   487: aload_0
      //   488: iload #5
      //   490: putfield rightMargin : I
      //   493: goto -> 526
      //   496: aload_0
      //   497: getfield g : I
      //   500: istore_1
      //   501: iload_1
      //   502: iconst_m1
      //   503: if_icmpeq -> 526
      //   506: aload_0
      //   507: iload_1
      //   508: putfield f0 : I
      //   511: aload_0
      //   512: getfield rightMargin : I
      //   515: ifgt -> 526
      //   518: iload #5
      //   520: ifle -> 526
      //   523: goto -> 487
      //   526: aload_0
      //   527: getfield d : I
      //   530: istore_1
      //   531: iload_1
      //   532: iconst_m1
      //   533: if_icmpeq -> 562
      //   536: aload_0
      //   537: iload_1
      //   538: putfield c0 : I
      //   541: aload_0
      //   542: getfield leftMargin : I
      //   545: ifgt -> 592
      //   548: iload #4
      //   550: ifle -> 592
      //   553: aload_0
      //   554: iload #4
      //   556: putfield leftMargin : I
      //   559: goto -> 592
      //   562: aload_0
      //   563: getfield e : I
      //   566: istore_1
      //   567: iload_1
      //   568: iconst_m1
      //   569: if_icmpeq -> 592
      //   572: aload_0
      //   573: iload_1
      //   574: putfield d0 : I
      //   577: aload_0
      //   578: getfield leftMargin : I
      //   581: ifgt -> 592
      //   584: iload #4
      //   586: ifle -> 592
      //   589: goto -> 553
      //   592: return
    }
    
    public static class a {
      public static final SparseIntArray a;
      
      static {
        SparseIntArray sparseIntArray = new SparseIntArray();
        a = sparseIntArray;
        sparseIntArray.append(k.ConstraintLayout_Layout_layout_constraintLeft_toLeftOf, 8);
        a.append(k.ConstraintLayout_Layout_layout_constraintLeft_toRightOf, 9);
        a.append(k.ConstraintLayout_Layout_layout_constraintRight_toLeftOf, 10);
        a.append(k.ConstraintLayout_Layout_layout_constraintRight_toRightOf, 11);
        a.append(k.ConstraintLayout_Layout_layout_constraintTop_toTopOf, 12);
        a.append(k.ConstraintLayout_Layout_layout_constraintTop_toBottomOf, 13);
        a.append(k.ConstraintLayout_Layout_layout_constraintBottom_toTopOf, 14);
        a.append(k.ConstraintLayout_Layout_layout_constraintBottom_toBottomOf, 15);
        a.append(k.ConstraintLayout_Layout_layout_constraintBaseline_toBaselineOf, 16);
        a.append(k.ConstraintLayout_Layout_layout_constraintCircle, 2);
        a.append(k.ConstraintLayout_Layout_layout_constraintCircleRadius, 3);
        a.append(k.ConstraintLayout_Layout_layout_constraintCircleAngle, 4);
        a.append(k.ConstraintLayout_Layout_layout_editor_absoluteX, 49);
        a.append(k.ConstraintLayout_Layout_layout_editor_absoluteY, 50);
        a.append(k.ConstraintLayout_Layout_layout_constraintGuide_begin, 5);
        a.append(k.ConstraintLayout_Layout_layout_constraintGuide_end, 6);
        a.append(k.ConstraintLayout_Layout_layout_constraintGuide_percent, 7);
        a.append(k.ConstraintLayout_Layout_android_orientation, 1);
        a.append(k.ConstraintLayout_Layout_layout_constraintStart_toEndOf, 17);
        a.append(k.ConstraintLayout_Layout_layout_constraintStart_toStartOf, 18);
        a.append(k.ConstraintLayout_Layout_layout_constraintEnd_toStartOf, 19);
        a.append(k.ConstraintLayout_Layout_layout_constraintEnd_toEndOf, 20);
        a.append(k.ConstraintLayout_Layout_layout_goneMarginLeft, 21);
        a.append(k.ConstraintLayout_Layout_layout_goneMarginTop, 22);
        a.append(k.ConstraintLayout_Layout_layout_goneMarginRight, 23);
        a.append(k.ConstraintLayout_Layout_layout_goneMarginBottom, 24);
        a.append(k.ConstraintLayout_Layout_layout_goneMarginStart, 25);
        a.append(k.ConstraintLayout_Layout_layout_goneMarginEnd, 26);
        a.append(k.ConstraintLayout_Layout_layout_constraintHorizontal_bias, 29);
        a.append(k.ConstraintLayout_Layout_layout_constraintVertical_bias, 30);
        a.append(k.ConstraintLayout_Layout_layout_constraintDimensionRatio, 44);
        a.append(k.ConstraintLayout_Layout_layout_constraintHorizontal_weight, 45);
        a.append(k.ConstraintLayout_Layout_layout_constraintVertical_weight, 46);
        a.append(k.ConstraintLayout_Layout_layout_constraintHorizontal_chainStyle, 47);
        a.append(k.ConstraintLayout_Layout_layout_constraintVertical_chainStyle, 48);
        a.append(k.ConstraintLayout_Layout_layout_constrainedWidth, 27);
        a.append(k.ConstraintLayout_Layout_layout_constrainedHeight, 28);
        a.append(k.ConstraintLayout_Layout_layout_constraintWidth_default, 31);
        a.append(k.ConstraintLayout_Layout_layout_constraintHeight_default, 32);
        a.append(k.ConstraintLayout_Layout_layout_constraintWidth_min, 33);
        a.append(k.ConstraintLayout_Layout_layout_constraintWidth_max, 34);
        a.append(k.ConstraintLayout_Layout_layout_constraintWidth_percent, 35);
        a.append(k.ConstraintLayout_Layout_layout_constraintHeight_min, 36);
        a.append(k.ConstraintLayout_Layout_layout_constraintHeight_max, 37);
        a.append(k.ConstraintLayout_Layout_layout_constraintHeight_percent, 38);
        a.append(k.ConstraintLayout_Layout_layout_constraintLeft_creator, 39);
        a.append(k.ConstraintLayout_Layout_layout_constraintTop_creator, 40);
        a.append(k.ConstraintLayout_Layout_layout_constraintRight_creator, 41);
        a.append(k.ConstraintLayout_Layout_layout_constraintBottom_creator, 42);
        a.append(k.ConstraintLayout_Layout_layout_constraintBaseline_creator, 43);
        a.append(k.ConstraintLayout_Layout_layout_constraintTag, 51);
      }
    }
  }
  
  public static class a {
    public static final SparseIntArray a;
    
    static {
      SparseIntArray sparseIntArray = new SparseIntArray();
      a = sparseIntArray;
      sparseIntArray.append(k.ConstraintLayout_Layout_layout_constraintLeft_toLeftOf, 8);
      a.append(k.ConstraintLayout_Layout_layout_constraintLeft_toRightOf, 9);
      a.append(k.ConstraintLayout_Layout_layout_constraintRight_toLeftOf, 10);
      a.append(k.ConstraintLayout_Layout_layout_constraintRight_toRightOf, 11);
      a.append(k.ConstraintLayout_Layout_layout_constraintTop_toTopOf, 12);
      a.append(k.ConstraintLayout_Layout_layout_constraintTop_toBottomOf, 13);
      a.append(k.ConstraintLayout_Layout_layout_constraintBottom_toTopOf, 14);
      a.append(k.ConstraintLayout_Layout_layout_constraintBottom_toBottomOf, 15);
      a.append(k.ConstraintLayout_Layout_layout_constraintBaseline_toBaselineOf, 16);
      a.append(k.ConstraintLayout_Layout_layout_constraintCircle, 2);
      a.append(k.ConstraintLayout_Layout_layout_constraintCircleRadius, 3);
      a.append(k.ConstraintLayout_Layout_layout_constraintCircleAngle, 4);
      a.append(k.ConstraintLayout_Layout_layout_editor_absoluteX, 49);
      a.append(k.ConstraintLayout_Layout_layout_editor_absoluteY, 50);
      a.append(k.ConstraintLayout_Layout_layout_constraintGuide_begin, 5);
      a.append(k.ConstraintLayout_Layout_layout_constraintGuide_end, 6);
      a.append(k.ConstraintLayout_Layout_layout_constraintGuide_percent, 7);
      a.append(k.ConstraintLayout_Layout_android_orientation, 1);
      a.append(k.ConstraintLayout_Layout_layout_constraintStart_toEndOf, 17);
      a.append(k.ConstraintLayout_Layout_layout_constraintStart_toStartOf, 18);
      a.append(k.ConstraintLayout_Layout_layout_constraintEnd_toStartOf, 19);
      a.append(k.ConstraintLayout_Layout_layout_constraintEnd_toEndOf, 20);
      a.append(k.ConstraintLayout_Layout_layout_goneMarginLeft, 21);
      a.append(k.ConstraintLayout_Layout_layout_goneMarginTop, 22);
      a.append(k.ConstraintLayout_Layout_layout_goneMarginRight, 23);
      a.append(k.ConstraintLayout_Layout_layout_goneMarginBottom, 24);
      a.append(k.ConstraintLayout_Layout_layout_goneMarginStart, 25);
      a.append(k.ConstraintLayout_Layout_layout_goneMarginEnd, 26);
      a.append(k.ConstraintLayout_Layout_layout_constraintHorizontal_bias, 29);
      a.append(k.ConstraintLayout_Layout_layout_constraintVertical_bias, 30);
      a.append(k.ConstraintLayout_Layout_layout_constraintDimensionRatio, 44);
      a.append(k.ConstraintLayout_Layout_layout_constraintHorizontal_weight, 45);
      a.append(k.ConstraintLayout_Layout_layout_constraintVertical_weight, 46);
      a.append(k.ConstraintLayout_Layout_layout_constraintHorizontal_chainStyle, 47);
      a.append(k.ConstraintLayout_Layout_layout_constraintVertical_chainStyle, 48);
      a.append(k.ConstraintLayout_Layout_layout_constrainedWidth, 27);
      a.append(k.ConstraintLayout_Layout_layout_constrainedHeight, 28);
      a.append(k.ConstraintLayout_Layout_layout_constraintWidth_default, 31);
      a.append(k.ConstraintLayout_Layout_layout_constraintHeight_default, 32);
      a.append(k.ConstraintLayout_Layout_layout_constraintWidth_min, 33);
      a.append(k.ConstraintLayout_Layout_layout_constraintWidth_max, 34);
      a.append(k.ConstraintLayout_Layout_layout_constraintWidth_percent, 35);
      a.append(k.ConstraintLayout_Layout_layout_constraintHeight_min, 36);
      a.append(k.ConstraintLayout_Layout_layout_constraintHeight_max, 37);
      a.append(k.ConstraintLayout_Layout_layout_constraintHeight_percent, 38);
      a.append(k.ConstraintLayout_Layout_layout_constraintLeft_creator, 39);
      a.append(k.ConstraintLayout_Layout_layout_constraintTop_creator, 40);
      a.append(k.ConstraintLayout_Layout_layout_constraintRight_creator, 41);
      a.append(k.ConstraintLayout_Layout_layout_constraintBottom_creator, 42);
      a.append(k.ConstraintLayout_Layout_layout_constraintBaseline_creator, 43);
      a.append(k.ConstraintLayout_Layout_layout_constraintTag, 51);
    }
  }
  
  public class b implements b.g.b.i.l.b.b {
    public ConstraintLayout a;
    
    public int b;
    
    public int c;
    
    public int d;
    
    public int e;
    
    public int f;
    
    public int g;
    
    public b(ConstraintLayout this$0, ConstraintLayout param1ConstraintLayout1) {
      this.a = param1ConstraintLayout1;
    }
    
    @SuppressLint({"WrongCall"})
    public final void a(d param1d, b.g.b.i.l.b.a param1a) {
      // Byte code:
      //   0: getstatic b/g/b/i/d$a.b : Lb/g/b/i/d$a;
      //   3: astore #21
      //   5: getstatic b/g/b/i/d$a.e : Lb/g/b/i/d$a;
      //   8: astore #22
      //   10: getstatic b/g/b/i/d$a.d : Lb/g/b/i/d$a;
      //   13: astore #20
      //   15: aload_1
      //   16: ifnonnull -> 20
      //   19: return
      //   20: aload_1
      //   21: getfield X : I
      //   24: bipush #8
      //   26: if_icmpne -> 52
      //   29: aload_1
      //   30: getfield x : Z
      //   33: ifne -> 52
      //   36: aload_2
      //   37: iconst_0
      //   38: putfield e : I
      //   41: aload_2
      //   42: iconst_0
      //   43: putfield f : I
      //   46: aload_2
      //   47: iconst_0
      //   48: putfield g : I
      //   51: return
      //   52: aload_2
      //   53: getfield a : Lb/g/b/i/d$a;
      //   56: astore #23
      //   58: aload_2
      //   59: getfield b : Lb/g/b/i/d$a;
      //   62: astore #24
      //   64: aload_2
      //   65: getfield c : I
      //   68: istore #5
      //   70: aload_2
      //   71: getfield d : I
      //   74: istore #7
      //   76: aload_0
      //   77: getfield b : I
      //   80: aload_0
      //   81: getfield c : I
      //   84: iadd
      //   85: istore #8
      //   87: aload_0
      //   88: getfield d : I
      //   91: istore #6
      //   93: aload_1
      //   94: getfield W : Ljava/lang/Object;
      //   97: checkcast android/view/View
      //   100: astore #19
      //   102: aload #23
      //   104: invokevirtual ordinal : ()I
      //   107: istore #4
      //   109: iload #4
      //   111: ifeq -> 370
      //   114: iload #4
      //   116: iconst_1
      //   117: if_icmpeq -> 343
      //   120: iload #4
      //   122: iconst_2
      //   123: if_icmpeq -> 221
      //   126: iload #4
      //   128: iconst_3
      //   129: if_icmpeq -> 141
      //   132: iconst_0
      //   133: istore #4
      //   135: iconst_0
      //   136: istore #6
      //   138: goto -> 390
      //   141: aload_0
      //   142: getfield f : I
      //   145: istore #9
      //   147: aload_1
      //   148: getfield y : Lb/g/b/i/c;
      //   151: astore #25
      //   153: aload #25
      //   155: ifnull -> 170
      //   158: aload #25
      //   160: getfield e : I
      //   163: iconst_0
      //   164: iadd
      //   165: istore #4
      //   167: goto -> 173
      //   170: iconst_0
      //   171: istore #4
      //   173: aload_1
      //   174: getfield A : Lb/g/b/i/c;
      //   177: astore #25
      //   179: iload #4
      //   181: istore #5
      //   183: aload #25
      //   185: ifnull -> 198
      //   188: iload #4
      //   190: aload #25
      //   192: getfield e : I
      //   195: iadd
      //   196: istore #5
      //   198: iload #9
      //   200: iload #6
      //   202: iload #5
      //   204: iadd
      //   205: iconst_m1
      //   206: invokestatic getChildMeasureSpec : (III)I
      //   209: istore #4
      //   211: aload_1
      //   212: getfield g : [I
      //   215: iconst_2
      //   216: iconst_m1
      //   217: iastore
      //   218: goto -> 135
      //   221: aload_0
      //   222: getfield f : I
      //   225: iload #6
      //   227: bipush #-2
      //   229: invokestatic getChildMeasureSpec : (III)I
      //   232: istore #6
      //   234: aload_1
      //   235: getfield j : I
      //   238: iconst_1
      //   239: if_icmpne -> 248
      //   242: iconst_1
      //   243: istore #4
      //   245: goto -> 251
      //   248: iconst_0
      //   249: istore #4
      //   251: aload_1
      //   252: getfield g : [I
      //   255: astore #25
      //   257: aload #25
      //   259: iconst_2
      //   260: iconst_0
      //   261: iastore
      //   262: aload_2
      //   263: getfield j : Z
      //   266: ifeq -> 333
      //   269: iload #4
      //   271: ifeq -> 292
      //   274: aload #25
      //   276: iconst_3
      //   277: iaload
      //   278: ifeq -> 292
      //   281: aload #25
      //   283: iconst_0
      //   284: iaload
      //   285: aload_1
      //   286: invokevirtual o : ()I
      //   289: if_icmpne -> 300
      //   292: aload #19
      //   294: instanceof b/g/c/i
      //   297: ifeq -> 306
      //   300: iconst_1
      //   301: istore #5
      //   303: goto -> 309
      //   306: iconst_0
      //   307: istore #5
      //   309: iload #4
      //   311: ifeq -> 319
      //   314: iload #5
      //   316: ifeq -> 333
      //   319: aload_1
      //   320: invokevirtual o : ()I
      //   323: ldc 1073741824
      //   325: invokestatic makeMeasureSpec : (II)I
      //   328: istore #4
      //   330: goto -> 135
      //   333: iload #6
      //   335: istore #4
      //   337: iconst_1
      //   338: istore #6
      //   340: goto -> 138
      //   343: aload_0
      //   344: getfield f : I
      //   347: iload #6
      //   349: bipush #-2
      //   351: invokestatic getChildMeasureSpec : (III)I
      //   354: istore #4
      //   356: aload_1
      //   357: getfield g : [I
      //   360: iconst_2
      //   361: bipush #-2
      //   363: iastore
      //   364: iconst_1
      //   365: istore #6
      //   367: goto -> 390
      //   370: iload #5
      //   372: ldc 1073741824
      //   374: invokestatic makeMeasureSpec : (II)I
      //   377: istore #4
      //   379: aload_1
      //   380: getfield g : [I
      //   383: iconst_2
      //   384: iload #5
      //   386: iastore
      //   387: iconst_0
      //   388: istore #6
      //   390: aload #24
      //   392: invokevirtual ordinal : ()I
      //   395: istore #5
      //   397: iload #5
      //   399: ifeq -> 651
      //   402: iload #5
      //   404: iconst_1
      //   405: if_icmpeq -> 624
      //   408: iload #5
      //   410: iconst_2
      //   411: if_icmpeq -> 505
      //   414: iload #5
      //   416: iconst_3
      //   417: if_icmpeq -> 429
      //   420: iconst_0
      //   421: istore #7
      //   423: iconst_0
      //   424: istore #5
      //   426: goto -> 671
      //   429: aload_0
      //   430: getfield g : I
      //   433: istore #9
      //   435: aload_1
      //   436: getfield y : Lb/g/b/i/c;
      //   439: ifnull -> 456
      //   442: aload_1
      //   443: getfield z : Lb/g/b/i/c;
      //   446: getfield e : I
      //   449: iconst_0
      //   450: iadd
      //   451: istore #5
      //   453: goto -> 459
      //   456: iconst_0
      //   457: istore #5
      //   459: iload #5
      //   461: istore #7
      //   463: aload_1
      //   464: getfield A : Lb/g/b/i/c;
      //   467: ifnull -> 482
      //   470: iload #5
      //   472: aload_1
      //   473: getfield B : Lb/g/b/i/c;
      //   476: getfield e : I
      //   479: iadd
      //   480: istore #7
      //   482: iload #9
      //   484: iload #8
      //   486: iload #7
      //   488: iadd
      //   489: iconst_m1
      //   490: invokestatic getChildMeasureSpec : (III)I
      //   493: istore #5
      //   495: aload_1
      //   496: getfield g : [I
      //   499: iconst_3
      //   500: iconst_m1
      //   501: iastore
      //   502: goto -> 668
      //   505: aload_0
      //   506: getfield g : I
      //   509: iload #8
      //   511: bipush #-2
      //   513: invokestatic getChildMeasureSpec : (III)I
      //   516: istore #8
      //   518: aload_1
      //   519: getfield k : I
      //   522: iconst_1
      //   523: if_icmpne -> 532
      //   526: iconst_1
      //   527: istore #5
      //   529: goto -> 535
      //   532: iconst_0
      //   533: istore #5
      //   535: aload_1
      //   536: getfield g : [I
      //   539: astore #25
      //   541: aload #25
      //   543: iconst_3
      //   544: iconst_0
      //   545: iastore
      //   546: aload_2
      //   547: getfield j : Z
      //   550: ifeq -> 617
      //   553: iload #5
      //   555: ifeq -> 576
      //   558: aload #25
      //   560: iconst_2
      //   561: iaload
      //   562: ifeq -> 576
      //   565: aload #25
      //   567: iconst_1
      //   568: iaload
      //   569: aload_1
      //   570: invokevirtual i : ()I
      //   573: if_icmpne -> 584
      //   576: aload #19
      //   578: instanceof b/g/c/i
      //   581: ifeq -> 590
      //   584: iconst_1
      //   585: istore #7
      //   587: goto -> 593
      //   590: iconst_0
      //   591: istore #7
      //   593: iload #5
      //   595: ifeq -> 603
      //   598: iload #7
      //   600: ifeq -> 617
      //   603: aload_1
      //   604: invokevirtual i : ()I
      //   607: ldc 1073741824
      //   609: invokestatic makeMeasureSpec : (II)I
      //   612: istore #5
      //   614: goto -> 502
      //   617: iload #8
      //   619: istore #5
      //   621: goto -> 645
      //   624: aload_0
      //   625: getfield g : I
      //   628: iload #8
      //   630: bipush #-2
      //   632: invokestatic getChildMeasureSpec : (III)I
      //   635: istore #5
      //   637: aload_1
      //   638: getfield g : [I
      //   641: iconst_3
      //   642: bipush #-2
      //   644: iastore
      //   645: iconst_1
      //   646: istore #7
      //   648: goto -> 671
      //   651: iload #7
      //   653: ldc 1073741824
      //   655: invokestatic makeMeasureSpec : (II)I
      //   658: istore #5
      //   660: aload_1
      //   661: getfield g : [I
      //   664: iconst_3
      //   665: iload #7
      //   667: iastore
      //   668: iconst_0
      //   669: istore #7
      //   671: aload #23
      //   673: aload #20
      //   675: if_acmpne -> 684
      //   678: iconst_1
      //   679: istore #8
      //   681: goto -> 687
      //   684: iconst_0
      //   685: istore #8
      //   687: aload #24
      //   689: aload #20
      //   691: if_acmpne -> 700
      //   694: iconst_1
      //   695: istore #13
      //   697: goto -> 703
      //   700: iconst_0
      //   701: istore #13
      //   703: aload #24
      //   705: aload #22
      //   707: if_acmpeq -> 726
      //   710: aload #24
      //   712: aload #21
      //   714: if_acmpne -> 720
      //   717: goto -> 726
      //   720: iconst_0
      //   721: istore #9
      //   723: goto -> 729
      //   726: iconst_1
      //   727: istore #9
      //   729: aload #23
      //   731: aload #22
      //   733: if_acmpeq -> 752
      //   736: aload #23
      //   738: aload #21
      //   740: if_acmpne -> 746
      //   743: goto -> 752
      //   746: iconst_0
      //   747: istore #10
      //   749: goto -> 755
      //   752: iconst_1
      //   753: istore #10
      //   755: iload #8
      //   757: ifeq -> 775
      //   760: aload_1
      //   761: getfield N : F
      //   764: fconst_0
      //   765: fcmpl
      //   766: ifle -> 775
      //   769: iconst_1
      //   770: istore #12
      //   772: goto -> 778
      //   775: iconst_0
      //   776: istore #12
      //   778: iload #13
      //   780: ifeq -> 798
      //   783: aload_1
      //   784: getfield N : F
      //   787: fconst_0
      //   788: fcmpl
      //   789: ifle -> 798
      //   792: iconst_1
      //   793: istore #11
      //   795: goto -> 801
      //   798: iconst_0
      //   799: istore #11
      //   801: aload #19
      //   803: invokevirtual getLayoutParams : ()Landroid/view/ViewGroup$LayoutParams;
      //   806: checkcast androidx/constraintlayout/widget/ConstraintLayout$a
      //   809: astore #20
      //   811: aload_2
      //   812: getfield j : Z
      //   815: ifne -> 857
      //   818: iload #8
      //   820: ifeq -> 857
      //   823: aload_1
      //   824: getfield j : I
      //   827: ifne -> 857
      //   830: iload #13
      //   832: ifeq -> 857
      //   835: aload_1
      //   836: getfield k : I
      //   839: ifeq -> 845
      //   842: goto -> 857
      //   845: iconst_0
      //   846: istore #6
      //   848: iconst_0
      //   849: istore #5
      //   851: iconst_0
      //   852: istore #4
      //   854: goto -> 1281
      //   857: aload #19
      //   859: instanceof b/g/c/l
      //   862: ifeq -> 889
      //   865: aload_1
      //   866: instanceof b/g/b/i/j
      //   869: ifeq -> 889
      //   872: aload_1
      //   873: checkcast b/g/b/i/j
      //   876: astore #21
      //   878: aload #19
      //   880: checkcast b/g/c/l
      //   883: invokevirtual j : ()V
      //   886: goto -> 898
      //   889: aload #19
      //   891: iload #4
      //   893: iload #5
      //   895: invokevirtual measure : (II)V
      //   898: aload #19
      //   900: invokevirtual getMeasuredWidth : ()I
      //   903: istore #15
      //   905: aload #19
      //   907: invokevirtual getMeasuredHeight : ()I
      //   910: istore #13
      //   912: aload #19
      //   914: invokevirtual getBaseline : ()I
      //   917: istore #14
      //   919: iload #6
      //   921: ifeq -> 945
      //   924: aload_1
      //   925: getfield g : [I
      //   928: astore #21
      //   930: aload #21
      //   932: iconst_0
      //   933: iload #15
      //   935: iastore
      //   936: aload #21
      //   938: iconst_2
      //   939: iload #13
      //   941: iastore
      //   942: goto -> 961
      //   945: aload_1
      //   946: getfield g : [I
      //   949: astore #21
      //   951: aload #21
      //   953: iconst_0
      //   954: iconst_0
      //   955: iastore
      //   956: aload #21
      //   958: iconst_2
      //   959: iconst_0
      //   960: iastore
      //   961: iload #7
      //   963: ifeq -> 987
      //   966: aload_1
      //   967: getfield g : [I
      //   970: astore #21
      //   972: aload #21
      //   974: iconst_1
      //   975: iload #13
      //   977: iastore
      //   978: aload #21
      //   980: iconst_3
      //   981: iload #15
      //   983: iastore
      //   984: goto -> 1003
      //   987: aload_1
      //   988: getfield g : [I
      //   991: astore #21
      //   993: aload #21
      //   995: iconst_1
      //   996: iconst_0
      //   997: iastore
      //   998: aload #21
      //   1000: iconst_3
      //   1001: iconst_0
      //   1002: iastore
      //   1003: aload_1
      //   1004: getfield m : I
      //   1007: istore #6
      //   1009: iload #6
      //   1011: ifle -> 1026
      //   1014: iload #6
      //   1016: iload #15
      //   1018: invokestatic max : (II)I
      //   1021: istore #7
      //   1023: goto -> 1030
      //   1026: iload #15
      //   1028: istore #7
      //   1030: aload_1
      //   1031: getfield n : I
      //   1034: istore #8
      //   1036: iload #7
      //   1038: istore #6
      //   1040: iload #8
      //   1042: ifle -> 1054
      //   1045: iload #8
      //   1047: iload #7
      //   1049: invokestatic min : (II)I
      //   1052: istore #6
      //   1054: aload_1
      //   1055: getfield p : I
      //   1058: istore #7
      //   1060: iload #7
      //   1062: ifle -> 1077
      //   1065: iload #7
      //   1067: iload #13
      //   1069: invokestatic max : (II)I
      //   1072: istore #8
      //   1074: goto -> 1081
      //   1077: iload #13
      //   1079: istore #8
      //   1081: aload_1
      //   1082: getfield q : I
      //   1085: istore #16
      //   1087: iload #8
      //   1089: istore #7
      //   1091: iload #16
      //   1093: ifle -> 1105
      //   1096: iload #16
      //   1098: iload #8
      //   1100: invokestatic min : (II)I
      //   1103: istore #7
      //   1105: iload #12
      //   1107: ifeq -> 1138
      //   1110: iload #9
      //   1112: ifeq -> 1138
      //   1115: aload_1
      //   1116: getfield N : F
      //   1119: fstore_3
      //   1120: iload #7
      //   1122: i2f
      //   1123: fload_3
      //   1124: fmul
      //   1125: ldc 0.5
      //   1127: fadd
      //   1128: f2i
      //   1129: istore #9
      //   1131: iload #7
      //   1133: istore #8
      //   1135: goto -> 1184
      //   1138: iload #6
      //   1140: istore #9
      //   1142: iload #7
      //   1144: istore #8
      //   1146: iload #11
      //   1148: ifeq -> 1184
      //   1151: iload #6
      //   1153: istore #9
      //   1155: iload #7
      //   1157: istore #8
      //   1159: iload #10
      //   1161: ifeq -> 1184
      //   1164: aload_1
      //   1165: getfield N : F
      //   1168: fstore_3
      //   1169: iload #6
      //   1171: i2f
      //   1172: fload_3
      //   1173: fdiv
      //   1174: ldc 0.5
      //   1176: fadd
      //   1177: f2i
      //   1178: istore #8
      //   1180: iload #6
      //   1182: istore #9
      //   1184: iload #15
      //   1186: iload #9
      //   1188: if_icmpne -> 1216
      //   1191: iload #13
      //   1193: iload #8
      //   1195: if_icmpeq -> 1201
      //   1198: goto -> 1216
      //   1201: iload #9
      //   1203: istore #6
      //   1205: iload #8
      //   1207: istore #5
      //   1209: iload #14
      //   1211: istore #4
      //   1213: goto -> 1281
      //   1216: iload #15
      //   1218: iload #9
      //   1220: if_icmpeq -> 1232
      //   1223: iload #9
      //   1225: ldc 1073741824
      //   1227: invokestatic makeMeasureSpec : (II)I
      //   1230: istore #4
      //   1232: iload #13
      //   1234: iload #8
      //   1236: if_icmpeq -> 1248
      //   1239: iload #8
      //   1241: ldc 1073741824
      //   1243: invokestatic makeMeasureSpec : (II)I
      //   1246: istore #5
      //   1248: aload #19
      //   1250: iload #4
      //   1252: iload #5
      //   1254: invokevirtual measure : (II)V
      //   1257: aload #19
      //   1259: invokevirtual getMeasuredWidth : ()I
      //   1262: istore #6
      //   1264: aload #19
      //   1266: invokevirtual getMeasuredHeight : ()I
      //   1269: istore #5
      //   1271: aload #19
      //   1273: invokevirtual getBaseline : ()I
      //   1276: istore #4
      //   1278: goto -> 1213
      //   1281: iload #4
      //   1283: iconst_m1
      //   1284: if_icmpeq -> 1293
      //   1287: iconst_1
      //   1288: istore #17
      //   1290: goto -> 1296
      //   1293: iconst_0
      //   1294: istore #17
      //   1296: iload #6
      //   1298: aload_2
      //   1299: getfield c : I
      //   1302: if_icmpne -> 1323
      //   1305: iload #5
      //   1307: aload_2
      //   1308: getfield d : I
      //   1311: if_icmpeq -> 1317
      //   1314: goto -> 1323
      //   1317: iconst_0
      //   1318: istore #18
      //   1320: goto -> 1326
      //   1323: iconst_1
      //   1324: istore #18
      //   1326: aload_2
      //   1327: iload #18
      //   1329: putfield i : Z
      //   1332: aload #20
      //   1334: getfield X : Z
      //   1337: ifeq -> 1346
      //   1340: iconst_1
      //   1341: istore #17
      //   1343: goto -> 1346
      //   1346: iload #17
      //   1348: ifeq -> 1371
      //   1351: iload #4
      //   1353: iconst_m1
      //   1354: if_icmpeq -> 1371
      //   1357: aload_1
      //   1358: getfield R : I
      //   1361: iload #4
      //   1363: if_icmpeq -> 1371
      //   1366: aload_2
      //   1367: iconst_1
      //   1368: putfield i : Z
      //   1371: aload_2
      //   1372: iload #6
      //   1374: putfield e : I
      //   1377: aload_2
      //   1378: iload #5
      //   1380: putfield f : I
      //   1383: aload_2
      //   1384: iload #17
      //   1386: putfield h : Z
      //   1389: aload_2
      //   1390: iload #4
      //   1392: putfield g : I
      //   1395: return
    }
  }
}


/* Location:              C:\Users\panch\Downloads\dvba_v1.1.0-dex2jar.jar!\androidx\constraintlayout\widget\ConstraintLayout.class
 * Java compiler version: 6 (50.0)
 * JD-Core Version:       1.1.3
 */