package c.c.b.k;

import android.content.Context;

public class b implements c {
  public b(Context paramContext) {
    // Byte code:
    //   0: aload_0
    //   1: invokespecial <init> : ()V
    //   4: ldc c/c/b/k/d
    //   6: monitorenter
    //   7: getstatic c/c/b/k/d.a : Lc/c/b/k/d;
    //   10: ifnonnull -> 26
    //   13: new c/c/b/k/d
    //   16: astore_2
    //   17: aload_2
    //   18: aload_1
    //   19: invokespecial <init> : (Landroid/content/Context;)V
    //   22: aload_2
    //   23: putstatic c/c/b/k/d.a : Lc/c/b/k/d;
    //   26: ldc c/c/b/k/d
    //   28: monitorexit
    //   29: return
    //   30: astore_1
    //   31: ldc c/c/b/k/d
    //   33: monitorexit
    //   34: aload_1
    //   35: athrow
    // Exception table:
    //   from	to	target	type
    //   7	26	30	finally
  }
}


/* Location:              C:\Users\panch\Downloads\dvba_v1.1.0-dex2jar.jar!\c\c\b\k\b.class
 * Java compiler version: 6 (50.0)
 * JD-Core Version:       1.1.3
 */