package b.n;

import java.util.HashMap;

public class s {
  public final HashMap<String, p> a = new HashMap<String, p>();
  
  public final void a() {
    // Byte code:
    //   0: aload_0
    //   1: getfield a : Ljava/util/HashMap;
    //   4: invokevirtual values : ()Ljava/util/Collection;
    //   7: invokeinterface iterator : ()Ljava/util/Iterator;
    //   12: astore #5
    //   14: aload #5
    //   16: invokeinterface hasNext : ()Z
    //   21: ifeq -> 135
    //   24: aload #5
    //   26: invokeinterface next : ()Ljava/lang/Object;
    //   31: checkcast b/n/p
    //   34: astore_3
    //   35: aload_3
    //   36: getfield a : Ljava/util/Map;
    //   39: astore_2
    //   40: aload_2
    //   41: ifnull -> 128
    //   44: aload_2
    //   45: monitorenter
    //   46: aload_3
    //   47: getfield a : Ljava/util/Map;
    //   50: invokeinterface values : ()Ljava/util/Collection;
    //   55: invokeinterface iterator : ()Ljava/util/Iterator;
    //   60: astore #4
    //   62: aload #4
    //   64: invokeinterface hasNext : ()Z
    //   69: ifeq -> 118
    //   72: aload #4
    //   74: invokeinterface next : ()Ljava/lang/Object;
    //   79: astore #6
    //   81: aload #6
    //   83: instanceof java/io/Closeable
    //   86: istore_1
    //   87: iload_1
    //   88: ifeq -> 62
    //   91: aload #6
    //   93: checkcast java/io/Closeable
    //   96: invokeinterface close : ()V
    //   101: goto -> 62
    //   104: astore #4
    //   106: new java/lang/RuntimeException
    //   109: astore_3
    //   110: aload_3
    //   111: aload #4
    //   113: invokespecial <init> : (Ljava/lang/Throwable;)V
    //   116: aload_3
    //   117: athrow
    //   118: aload_2
    //   119: monitorexit
    //   120: goto -> 128
    //   123: astore_3
    //   124: aload_2
    //   125: monitorexit
    //   126: aload_3
    //   127: athrow
    //   128: aload_3
    //   129: invokevirtual a : ()V
    //   132: goto -> 14
    //   135: aload_0
    //   136: getfield a : Ljava/util/HashMap;
    //   139: invokevirtual clear : ()V
    //   142: return
    // Exception table:
    //   from	to	target	type
    //   46	62	123	finally
    //   62	87	123	finally
    //   91	101	104	java/io/IOException
    //   91	101	123	finally
    //   106	118	123	finally
    //   118	120	123	finally
    //   124	126	123	finally
  }
}


/* Location:              C:\Users\panch\Downloads\dvba_v1.1.0-dex2jar.jar!\b\n\s.class
 * Java compiler version: 6 (50.0)
 * JD-Core Version:       1.1.3
 */